Workbook
Name SCENARIO_ACTIF: '00_CONFIG__T_PARAMETRES'!$H$2

Sheet DIM_FAM_METIER
A1: FAM_METIER_ID | B1: CODE_FAM_METIER | C1: LIBELLE_FAM_METIER | D1: CATEGORIE_METIER | E1: ORDRE_AFFICHAGE
A2: FM_01 | B2: STRUCTURE | C2: Structure & Gros Œuvre | D2: STRUCTURE | E2: 1
A3: FM_02 | B3: ENVELOPPE | C3: Enveloppe & Étanchéité | D3: FINITION | E3: 2
A4: FM_03 | B4: FINITION | C4: Menuiserie & Finitions | D4: FINITION | E4: 3
A5: FM_04 | B5: TECHNIQUE | C5: Corps Techniques | D5: TECHNIQUE | E5: 4

Sheet 00_ARCHITECTURE
A1: 🏗️ ARCHITECTURE OFFICIELLE — MOTEUR DÉCISIONNEL CHANTIER V2.0
B3: ⚙️ COUCHE CONFIG
B4: → 00_CONFIG__T_PARAMETRES_ACTIVE
B5: → 00_CONFIG__T_PARAMETRES (scénarios)
B6: → T_PROJET
C7: ℹ️ Pilote tout le moteur — paramètres dynamiques — simulation scénarios
B9: 📐 COUCHE DIMENSIONS
B10: → DIM_FAM_METIER
B11: → DIM_FAM_ARTICLE (17 familles)
B12: → DIM_LOT (17 lots)
C13: ℹ️ Tables stables — modèle étoile Power BI — référentiels analytiques
B15: 📥 COUCHE RAW — Données Brutes
B16: → 01_RAW__METRE (318 articles)
B17: → 01_RAW__BPU_LOCAL
B18: → 01_RAW__BPU_CHINE
C19: ℹ️ Source immuable — jamais modifiée — traçabilité garantie
B21: 🧹 COUCHE CLEAN — Données Nettoyées
B22: → 02_CLEAN__T_METRE
B23: → 02_CLEAN__BPU_LOCAL
B24: → 02_CLEAN__BPU_CHINE
C25: ℹ️ Harmonisation unités — suppression erreurs — normalisation texte
B27: ⚡ COUCHE STAGING — Cœur Décisionnel
B28: → 03_STAGING__METRE_ENRICHI
B29: → → PU_LOCAL + PU_IMPORT_NET
B30: → → TAUX_ECONOMIE + DECISION_IMPORT
C31: ℹ️ Jointures + calculs — 163 IMPORT | 142 LOCAL | 13 ARBITRAGE
B33: 📊 COUCHE FACT — Table Consolidée
B34: → 04_FACT_METRE (318 lignes)
C35: ℹ️ Table économique finale — base de toutes les agrégations
B37: 🗄️ COUCHE DATAMART — Agrégations
B38: → 05_DM_LOT (17 lots)
B39: → 05_DM_FAM_ARTICLE (17 familles)
B40: → 05_DM_PROJET (KPIs globaux)
C41: ℹ️ Optimisé Power BI — granularités LOT / FAM / PROJET
B43: 🧠 COUCHE ANALYTICS — Intelligence
B44: → 06_ANALYTICS__SCORE_STRATEGIQUE
B45: → 07_INTELLIGENCE__DECISION
B46: → 09_DM_MATRICE_GAIN_RISQUE
C47: ℹ️ Scores multicritères — IPI — quadrant stratégique — classe A/B/C
B49: 📋 COUCHE DASHBOARD — Direction
B50: → 08_KPI__PROJET
B51: → 10_DASHBOARD__DIRECTION
B52: → RECAP_DASHBOARD
C53: ℹ️ Vue exécutive — top opportunités — alertes risque — KPIs clés

Sheet ---01_CONFIGURATION ---

Sheet PARAM_GLOBAL
A1: PARAM | B1: VALUE | C1: TYPE
A2: Mode_Sourcing | B2: Mixte | C2: GENERAL
A3: Devise_Modele | B3: FCFA | C3: GENERAL
A4: COUT_CONTAINER | B4: 2500000 | C4: LOGISTIQUE
A5: CAPACITE_CONTAINER | B5: 28 | C5: LOGISTIQUE
A6: SEUIL_DECISION_IMPORT | B6: 0.05 | C6: DECISION
A7: POIDS_PRIX | B7: 0.4 | C7: DECISION
A8: POIDS_RISQUE | B8: 0.3 | C8: DECISION
A9: POIDS_DELAI | B9: 0.2 | C9: DECISION
A10: POIDS_VOLUME | B10: 0.1 | C10: DECISION
A11: TAUX_MARGE_LOCAL | B11: 0.15 | C11: FINANCE
A12: TAUX_MARGE_IMPORT | B12: 0.08 | C12: FINANCE
A13: TAUX_TRANSPORT_MARITIME | B13: 0.12 | C13: LOGISTIQUE
A14: TAUX_ASSURANCE | B14: 0.005 | C14: LOGISTIQUE
A15: TAUX_DOUANE | B15: 0.18 | C15: LOGISTIQUE
... A20: TAUX_CHANGE_USD | B20: 600 | C20: FINANCE

Sheet T_PARAM_IMPORT
A1: PROJET_ID | B1: TRANSPORT | C1: ASSURANCE | D1: DOUANE | E1: PORT | F1: LOGISTIQUE | G1: TRANSPORT_LOCAL | H1: CHANGE | I1: MARGE | J1: IMPREVUS | K1: TAUX_TRANSPORT_MARITIME | L1: TAUX_ASSURANCE | M1: TAUX_DOUANE | N1: TAUX_FRAIS_PORT | O1: TAUX_LOGISTIQUE | P1: TAUX_TRANSPORT_LOCAL | Q1: TAUX_CHANGE_USD | R1: TAUX_MARGE_IMPORT | S1: TAUX_IMPREVUS_IMPORT
A2: PNR_MEDICAL_CENTER | B2: 0.12 | C2: 0.005 | D2: 0.18 | E2: 0.04 | F2: 0.03 | G2: 0.05 | H2: 600 | I2: 0.08 | J2: 0.03 | K2: 0.12 | L2: 0.005 | M2: 0.18 | N2: 0.04 | O2: 0.03 | P2: 0.05 | Q2: 600 | R2: 0.08 | S2: 0.03

Sheet 00_POWER_QUERY
B1: ⚡ MOTEUR POWER QUERY M — Centre Médical Pointe Noire
B2: Version | C2: 2.0 — Formules dynamiques · Scénarios OPTIMISTE / RÉALISTE / STRESS · 318 articles · 17 lots
B3: Architecture | C3: CONFIG → DIMENSIONS → RAW → CLEAN → STAGING → FACT → DATAMART → ANALYTICS
B4: Clé de jointure | C4: CODE_BPU — relie METRE ↔ BPU_LOCAL ↔ BPU_CHINE (ex : "2.1", "7.A.3")
B5: Levier scénario | C5: Changer H2 dans T_PARAMETRES → tous les calculs STAGING se mettent à jour
B7: 📐 ARCHITECTURE DU FLUX DE DONNÉES
B8: 00_CONFIG | C8: T_PARAMETRES → H2 = scénario actif → T_PARAMETRES_ACTIVE → STAGING
B9: DIMENSIONS | C9: DIM_LOT / DIM_FAM_* → Tables de référence stables — enrichissent STAGING
B10: 01_RAW | C10: METRE / BPU_LOCAL / BPU_CHINE → Sources brutes immuables — ne jamais modifier
B11: 02_CLEAN | C11: CLEAN_METRE / CLEAN_BPU_LOCAL / CLEAN_BPU_CHINE → Nettoyage + contrôle qualité
B12: 03_STAGING | C12: METRE_ENRICHI → ★ CŒUR — Jointures + calculs économiques dynamiques
B13: 04_FACT | C13: FACT_METRE → Table de faits finale — 318 lignes × 14 colonnes
B14: 05_DM | C14: DM_LOT / DM_FAM / DM_PROJET → Agrégations par lot, famille, projet
B15: 06-07 ANALYTICS | C15: SCORE + INTELLIGENCE → Scoring multicritères + matrice décisionnelle
B16: 08-10 DASH | C16: KPI + MATRICE + DASHBOARD → Synthèse exécutive
B18: ═══ COUCHE 0 — CONNEXION SOURCE ═══
B20: Source_ExcelFichier — Connexion centralisée au classeur
B21: 🎯 Rôle : Point d'entrée unique vers BE_MONOPROJET_V2_PNMC.xlsx. Toutes les requêtes référencent Source_ExcelFichier — changer le chemin ici suffit pour pointer vers un autre fichier.
B22: 🏷 CONNEXION · PARAMÈTRE · SOURCE
B23: // Source_ExcelFichier.pq | Power Query M Language
B24: // ─────────────────────────────────────────────────────────────────────────
B25: // CONNEXION CENTRALISÉE AU FICHIER EXCEL SOURCE
B26: // Modifier UNIQUEMENT ici pour changer le chemin du fichier.
B27: // ─────────────────────────────────────────────────────────────────────────
B28: let
B29: // ⚠️ ADAPTER CE CHEMIN À VOTRE ENVIRONNEMENT :
B30: // • Local Windows : "C:\\Projets\\PNMC\\BE_MONOPROJET_V2_PNMC.xlsx"
... B36: // delayTypes = true → ne pas inférer les types tout de suite (+ rapide)
B37: Source = Excel.Workbook( | C37: // ← Point de départ de TOUTES les requêtes
B38: File.Contents(CheminFichier),
B39: true, // useHeaders
B40: true // delayTypes
B41: )
B42: in
B43: Source
B45: ═══ COUCHE 00_CONFIG — SCÉNARIOS & PARAMÈTRES ═══
B47: T_PARAMETRES — Table des 3 scénarios — OPTIMISTE / RÉALISTE / STRESS
B48: 🎯 Rôle : Lit les 14 paramètres projet (marges, taux transport/douane, seuil décision, poids multicritères) sous forme de 3 colonnes scénarios. Source de vérité de TOUT le modèle financier.
B49: 🏷 CONFIG · SCÉNARIOS · PARAMÈTRES · SOURCE_VÉRITÉ
B50: // T_PARAMETRES.pq | Power Query M Language
B51: // ─── STRUCTURE DE L'ONGLET EXCEL 00_CONFIG__T_PARAMETRES ───────────────────
... B67: // Supprimer la ligne fantôme R1 (titre fusionné devenu donnée)
B68: SupprimerTitre = Table.Skip(Onglet, 1), | C68: // Sauter 1 ligne
B70: // Supprimer les colonnes inutiles pour cette requête
B71: SupprimerColonnesVides = Table.SelectColumns(SupprimerTitre, {
B72: "CATEGORIE", "PARAMETRE", "OPTIMISTE", "RÉALISTE", "STRESS", "DESCRIPTION"
B73: }),
B75: // Filtrer les lignes sans PARAMETRE (lignes vides en bas de feuille)
B76: SupprimerVides = Table.SelectRows(SupprimerColonnesVides,
B77: each [PARAMETRE] <> null and [PARAMETRE] <> "" | C77: // Exclure vides
B78: ),
B80: // Typer les colonnes
B81: // "any" pour les colonnes valeurs : mixte texte (Nom_Projet) + nombres (0.15)
B82: Resultat = Table.TransformColumnTypes(SupprimerVides, {
B83: {"CATEGORIE", type text},
B84: {"PARAMETRE", type text},
B85: {"OPTIMISTE", type any}, // Mixte : "PNMC" ou 0.12
B86: {"RÉALISTE", type any},
B87: {"STRESS", type any},
B88: {"DESCRIPTION", type text}
B89: })
B90: in
... B1082: ═══ GUIDE D'UTILISATION POWER QUERY / POWER BI ═══
B1084: CONNEXION AU FICHIER | C1084: Power BI Desktop → Accueil → Obtenir des données → Excel Sélectionner BE_MONOPROJET_V2_PNMC.xlsx Ne charger QUE les tables RAW, CONFIG et DIM en premier
B1085: ORDRE DE CHARGEMENT | C1085: 1. Source_ExcelFichier 2. T_PARAMETRES + T_PARAMETRES_ACTIVE + fxGetParam 3. T_PROJET + DIM_FAM_METIER + DIM_FAM_ARTICLE + DIM_LOT 4. RAW_METRE + RAW_BPU_LOCAL + RAW_BPU_CHINE 5. CLEAN_METRE + CLEAN_BPU_LOCAL + CLEAN_BPU_CHINE 6. STAGING → FACT_METRE 7. DM_LOT + DM_FAM_ARTICLE + DM_PROJET 8. ANALYTICS_SCORE_STRATEGIQUE → INTELLIGENCE_DECISION → KPI_PROJET
B1086: CHANGER DE SCÉNARIO | C1086: Excel : ouvrir T_PARAMETRES → cellule H2 → taper OPTIMISTE, RÉALISTE ou STRESS Power BI : Accueil → Actualiser (tout recalcule automatiquement)
B1087: AJOUTER UN ARTICLE | C1087: Ajouter la ligne dans 01_RAW__METRE (QTE + CODE_BPU) Ajouter les prix dans 01_RAW__BPU_LOCAL et 01_RAW__BPU_CHINE (même CODE_BPU) Actualiser Power BI → la ligne apparaît dans STAGING + FACT + tous les DM
B1088: MODIFIER UN PARAMÈTRE | C1088: Ouvrir 00_CONFIG__T_PARAMETRES Modifier la valeur dans la colonne du scénario souhaité (OPTIMISTE/RÉALISTE/STRESS) Actualiser → STAGING et FACT se recalculent entièrement
B1089: TABLES À CHARGER EN PBI | C1089: ✅ CHARGER (activer « Charger » dans l'éditeur) : FACT_METRE, DM_LOT, DM_FAM_ARTICLE, DM_PROJET ANALYTICS_SCORE_STRATEGIQUE, INTELLIGENCE_DECISION, KPI_PROJET T_PARAMETRES_ACTIVE (pour carte scénario actif) DIM_LOT, DIM_FAM_ARTICLE, DIM_FAM_METIER, T_PROJET ⛔ NE PAS CHARGER (tables intermédiaires — désactiver le chargement) : Source_ExcelFichier, T_PARAMETRES RAW_METRE, RAW_BPU_LOCAL, RAW_BPU_CHINE CLEAN_METRE, CLEAN_BPU_LOCAL, CLEAN_BPU_CHINE STAGING (table intermédiaire — charger uniquement FACT_METRE) fxGetParam
B1090: MODÈLE DE DONNÉES PBI | C1090: Créer ces relations dans la vue Modèle : FACT_METRE[CODE_BPU] → STAGING n'est pas chargé donc pas besoin FACT_METRE[FAM_ARTICLE_ID]→ DIM_FAM_ARTICLE[FAM_ARTICLE_ID] (M:1) FACT_METRE[LOT] → DM_LOT[LOT] (M:1) DM_LOT[FAM_ARTICLE_ID] → DIM_FAM_ARTICLE[FAM_ARTICLE_ID] (M:1) DIM_FAM_ARTICLE[FAM_METIER_ID] → DIM_FAM_METIER[FAM_METIER_ID] (M:1) ANALYTICS[LOT] → DM_LOT[LOT] (M:1)
B1091: MESURES DAX CLÉS | C1091: // Économie Totale (FCFA) ECONOMIE_TOTALE = SUM(FACT_METRE[GAIN]) // Taux économie global TAUX_ECO = DIVIDE(SUM(FACT_METRE[GAIN]), SUM(FACT_METRE[TOTAL_LOCAL])) // Nb articles IMPORT NB_IMPORT = COUNTROWS(FILTER(FACT_METRE, FACT_METRE[DECISION_IMPORT]="IMPORT")) // Scénario actif (carte) SCENARIO_ACTIF = FIRSTNONBLANK(T_PARAMETRES_ACTIVE[SCENARIO], 1)
B1093: 📄 Code Power Query M complet — BE_MONOPROJET_V2_PNMC · Projet Centre Médical Pointe Noire · v2.0 · 2026

Sheet CONFIG__MOTEUR_FORMULES
A1: 📐 DOCUMENTATION DES FORMULES DYNAMIQUES — MOTEUR DÉCISIONNEL PNMC
A2: SÉLECTEUR SCÉNARIO
A3: Cellule | B3: Valeur | C3: Effet sur le modèle
A4: T_PARAMETRES!H2 | B4: OPTIMISTE / RÉALISTE / STRESS | C4: Change tous les paramètres actifs en cascade
A6: FORMULES PARAMÈTRES ACTIFS
A7: Paramètre | B7: Formule dans T_PARAMETRES_ACTIVE | C7: Description
A8: Taux_Marge_Local | B8: INDEX('00_CONFIG__T_PARAMETRES'!C6:E6, 1, MATCH('00_CONFIG__T_PARAMETRES'!H2, 'T_PARAMETRES'!C2:E2, 0)) | C8: Lit la colonne scénario correspondante
A9: Taux_Marge_Chine | B9: INDEX('00_CONFIG__T_PARAMETRES'!C7:E7, 1, MATCH(...)) | C9: idem
A10: Taux_Transport | B10: INDEX('00_CONFIG__T_PARAMETRES'!C8:E8, 1, MATCH(...)) | C10: idem
A11: Taux_Douane | B11: INDEX('00_CONFIG__T_PARAMETRES'!C9:E9, 1, MATCH(...)) | C11: idem
A12: Seuil_Decision_Import | B12: INDEX('00_CONFIG__T_PARAMETRES'!C12:E12, 1, MATCH(...)) | C12: idem
A14: FORMULES STAGING
A15: Colonne | B15: Formule type | C15: Description
A16: M — PU_CHINE_FOB | B16: 0 | C16: Prix FOB source Chine (fallback = PU_LOCAL si non trouvé)
A17: N — PU_IMPORT_NET | B17: M4 * (1 + T_TRANSPORT + T_DOUANE) * (1 + T_MARGE_CHINE) | C17: Prix de revient import avec tous les coûts logistiques et marge
A18: O — PU_LOCAL_MARGE | B18: L4 * (1 + T_MARGE_LOCAL) | C18: Prix local avec marge entreprise appliquée
A19: P — MONTANT_LOCAL | B19: =J4*O4 -> 0 | C19: Montant total si exécution 100% locale
A20: Q — MONTANT_IMPORT | B20: =J4*N4 -> 0 | C20: Montant total si sourcing Chine
A21: R — ÉCONOMIE_NETTE | B21: =P4-Q4 -> 0 | C21: Gain financier net par article
A22: S — TAUX_ÉCONOMIE | B22: =IF(P4=0,0,R4/P4) -> 0 | C22: Taux de réduction CAPEX par article
A23: V — DECISION | B23: =IF(T4=0,"LOCAL",IF(S4>seuil,"IMPORT","ARBITRAGE")) -> LOCAL | C23: Décision finale — pilotée par le seuil paramétrable
A25: IMPACT DU CHANGEMENT DE SCÉNARIO
A26: Paramètre | B26: OPTIMISTE | C26: RÉALISTE | D26: STRESS | E26: Δ Impact
A27: Taux_Transport | B27: 6% | C27: 8% | D27: 12% | E27: ↑ coût import → moins de IMPORT
A28: Taux_Douane | B28: 12% | C28: 15% | D28: 20% | E28: ↑ coût import → moins de IMPORT
A29: Taux_Marge_Chine | B29: 8% | C29: 10% | D29: 15% | E29: ↑ PU_IMPORT_NET → taux éco baisse
A30: Taux_Marge_Local | B30: 12% | C30: 15% | D30: 20% | E30: ↑ PU_LOCAL_MARGE → taux éco monte
A31: Seuil_Decision_Import | B31: 3% | C31: 5% | D31: 8% | E31: ↑ seuil → moins de IMPORT décidés

Sheet 00_CONFIG__T_PARAMETRES_ACTIVE
A1: ⚙️ PARAMÈTRES ACTIFS — Pilotés par le scénario sélectionné
A2: =CONCATENATE("📊 Scénario actif : ", '00_CONFIG__T_PARAMETRES'!$H$2) -> 📊 Scénario actif : REALISTE
A3: PARAMETRE | B3: VALEUR ACTIVE | C3: OPTIMISTE | D3: RÉALISTE | E3: STRESS
A4: Nom_Projet | B4: =INDEX('00_CONFIG__T_PARAMETRES'!$C$3:$E$3,1,MATCH('00_CONFIG__T_PARAMETRES'!$H$2,'00_CONFIG__T_PARAMETRES'!$C$2:$E$2,0)) -> PNMC | C4: ='00_CONFIG__T_PARAMETRES'!$C$3 -> PNMC | D4: ='00_CONFIG__T_PARAMETRES'!$D$3 -> PNMC | E4: ='00_CONFIG__T_PARAMETRES'!$E$3 -> PNMC
A5: Mode_Sourcing | B5: =INDEX('00_CONFIG__T_PARAMETRES'!$C$4:$E$4,1,MATCH('00_CONFIG__T_PARAMETRES'!$H$2,'00_CONFIG__T_PARAMETRES'!$C$2:$E$2,0)) -> Mixte | C5: ='00_CONFIG__T_PARAMETRES'!$C$4 -> Mixte | D5: ='00_CONFIG__T_PARAMETRES'!$D$4 -> Mixte | E5: ='00_CONFIG__T_PARAMETRES'!$E$4 -> Local
A6: Devise_Modele | B6: =INDEX('00_CONFIG__T_PARAMETRES'!$C$5:$E$5,1,MATCH('00_CONFIG__T_PARAMETRES'!$H$2,'00_CONFIG__T_PARAMETRES'!$C$2:$E$2,0)) -> FCFA | C6: ='00_CONFIG__T_PARAMETRES'!$C$5 -> FCFA | D6: ='00_CONFIG__T_PARAMETRES'!$D$5 -> FCFA | E6: ='00_CONFIG__T_PARAMETRES'!$E$5 -> FCFA
A7: Taux_Marge_Local | B7: =INDEX('00_CONFIG__T_PARAMETRES'!$C$6:$E$6,1,MATCH('00_CONFIG__T_PARAMETRES'!$H$2,'00_CONFIG__T_PARAMETRES'!$C$2:$E$2,0)) -> 0.15 | C7: ='00_CONFIG__T_PARAMETRES'!$C$6 -> 0.12 | D7: ='00_CONFIG__T_PARAMETRES'!$D$6 -> 0.15 | E7: ='00_CONFIG__T_PARAMETRES'!$E$6 -> 0.2
A8: Taux_Marge_Chine | B8: =INDEX('00_CONFIG__T_PARAMETRES'!$C$7:$E$7,1,MATCH('00_CONFIG__T_PARAMETRES'!$H$2,'00_CONFIG__T_PARAMETRES'!$C$2:$E$2,0)) -> 0.1 | C8: ='00_CONFIG__T_PARAMETRES'!$C$7 -> 0.08 | D8: ='00_CONFIG__T_PARAMETRES'!$D$7 -> 0.1 | E8: ='00_CONFIG__T_PARAMETRES'!$E$7 -> 0.15
A9: Taux_Transport | B9: =INDEX('00_CONFIG__T_PARAMETRES'!$C$8:$E$8,1,MATCH('00_CONFIG__T_PARAMETRES'!$H$2,'00_CONFIG__T_PARAMETRES'!$C$2:$E$2,0)) -> 0.08 | C9: ='00_CONFIG__T_PARAMETRES'!$C$8 -> 0.06 | D9: ='00_CONFIG__T_PARAMETRES'!$D$8 -> 0.08 | E9: ='00_CONFIG__T_PARAMETRES'!$E$8 -> 0.12
A10: Taux_Douane | B10: =INDEX('00_CONFIG__T_PARAMETRES'!$C$9:$E$9,1,MATCH('00_CONFIG__T_PARAMETRES'!$H$2,'00_CONFIG__T_PARAMETRES'!$C$2:$E$2,0)) -> 0.15 | C10: ='00_CONFIG__T_PARAMETRES'!$C$9 -> 0.12 | D10: ='00_CONFIG__T_PARAMETRES'!$D$9 -> 0.15 | E10: ='00_CONFIG__T_PARAMETRES'!$E$9 -> 0.2
A11: Cout_Container | B11: =INDEX('00_CONFIG__T_PARAMETRES'!$C$10:$E$10,1,MATCH('00_CONFIG__T_PARAMETRES'!$H$2,'00_CONFIG__T_PARAMETRES'!$C$2:$E$2,0)) -> 2500000 | C11: ='00_CONFIG__T_PARAMETRES'!$C$10 -> 2200000 | D11: ='00_CONFIG__T_PARAMETRES'!$D$10 -> 2500000 | E11: ='00_CONFIG__T_PARAMETRES'!$E$10 -> 3000000
A12: Capacite_Container | B12: =INDEX('00_CONFIG__T_PARAMETRES'!$C$11:$E$11,1,MATCH('00_CONFIG__T_PARAMETRES'!$H$2,'00_CONFIG__T_PARAMETRES'!$C$2:$E$2,0)) -> 28 | C12: ='00_CONFIG__T_PARAMETRES'!$C$11 -> 30 | D12: ='00_CONFIG__T_PARAMETRES'!$D$11 -> 28 | E12: ='00_CONFIG__T_PARAMETRES'!$E$11 -> 25
A13: Seuil_Decision_Import | B13: =INDEX('00_CONFIG__T_PARAMETRES'!$C$12:$E$12,1,MATCH('00_CONFIG__T_PARAMETRES'!$H$2,'00_CONFIG__T_PARAMETRES'!$C$2:$E$2,0)) -> 0.05 | C13: ='00_CONFIG__T_PARAMETRES'!$C$12 -> 0.03 | D13: ='00_CONFIG__T_PARAMETRES'!$D$12 -> 0.05 | E13: ='00_CONFIG__T_PARAMETRES'!$E$12 -> 0.08
A14: Poids_Prix | B14: =INDEX('00_CONFIG__T_PARAMETRES'!$C$13:$E$13,1,MATCH('00_CONFIG__T_PARAMETRES'!$H$2,'00_CONFIG__T_PARAMETRES'!$C$2:$E$2,0)) -> 0.4 | C14: ='00_CONFIG__T_PARAMETRES'!$C$13 -> 0.45 | D14: ='00_CONFIG__T_PARAMETRES'!$D$13 -> 0.4 | E14: ='00_CONFIG__T_PARAMETRES'!$E$13 -> 0.35
A15: Poids_Risque | B15: =INDEX('00_CONFIG__T_PARAMETRES'!$C$14:$E$14,1,MATCH('00_CONFIG__T_PARAMETRES'!$H$2,'00_CONFIG__T_PARAMETRES'!$C$2:$E$2,0)) -> 0.3 | C15: ='00_CONFIG__T_PARAMETRES'!$C$14 -> 0.25 | D15: ='00_CONFIG__T_PARAMETRES'!$D$14 -> 0.3 | E15: ='00_CONFIG__T_PARAMETRES'!$E$14 -> 0.35
A16: Poids_Delai | B16: =INDEX('00_CONFIG__T_PARAMETRES'!$C$15:$E$15,1,MATCH('00_CONFIG__T_PARAMETRES'!$H$2,'00_CONFIG__T_PARAMETRES'!$C$2:$E$2,0)) -> 0.2 | C16: ='00_CONFIG__T_PARAMETRES'!$C$15 -> 0.2 | D16: ='00_CONFIG__T_PARAMETRES'!$D$15 -> 0.2 | E16: ='00_CONFIG__T_PARAMETRES'!$E$15 -> 0.2
A17: Poids_Volume | B17: =INDEX('00_CONFIG__T_PARAMETRES'!$C$16:$E$16,1,MATCH('00_CONFIG__T_PARAMETRES'!$H$2,'00_CONFIG__T_PARAMETRES'!$C$2:$E$2,0)) -> 0.1 | C17: ='00_CONFIG__T_PARAMETRES'!$C$16 -> 0.1 | D17: ='00_CONFIG__T_PARAMETRES'!$D$16 -> 0.1 | E17: ='00_CONFIG__T_PARAMETRES'!$E$16 -> 0.1

Sheet 00_CONFIG__T_PARAMETRES
A1: ⚙️ PARAMÈTRES PROJET — SCÉNARIOS OPTIMISTE / RÉALISTE / STRESS | B1: Colonne1 | C1: Colonne2 | D1: Colonne3 | E1: Colonne4 | F1: Colonne5 | H1: 🎯 SCENARIO ACTIF
A2: CATEGORIE | B2: PARAMETRE | C2: OPTIMISTE | D2: REALISTE | E2: STRESS | F2: DESCRIPTION | H2: REALISTE
A3: GENERAL | B3: Nom_Projet | C3: PNMC | D3: PNMC | E3: PNMC | F3: Nom officiel du projet | H3: ↑ Modifier ici : OPTIMISTE / RÉALISTE / STRESS
A4: GENERAL | B4: Mode_Sourcing | C4: Mixte | D4: Mixte | E4: Local | F4: Stratégie approvisionnement
A5: GENERAL | B5: Devise_Modele | C5: FCFA | D5: FCFA | E5: FCFA | F5: Devise de référence
A6: FINANCE | B6: Taux_Marge_Local | C6: 0.12 | D6: 0.15 | E6: 0.2 | F6: Marge sur PU locaux
A7: FINANCE | B7: Taux_Marge_Chine | C7: 0.08 | D7: 0.1 | E7: 0.15 | F7: Marge sur PU importés
A8: LOGISTIQUE | B8: Taux_Transport | C8: 0.06 | D8: 0.08 | E8: 0.12 | F8: Transport maritime + terrestre
A9: LOGISTIQUE | B9: Taux_Douane | C9: 0.12 | D9: 0.15 | E9: 0.2 | F9: Droits de douane Congo
A10: LOGISTIQUE | B10: Cout_Container | C10: 2200000 | D10: 2500000 | E10: 3000000 | F10: Coût/container 20 pieds (FCFA)
A11: LOGISTIQUE | B11: Capacite_Container | C11: 30 | D11: 28 | E11: 25 | F11: Capacité utile m³/container
A12: DECISION | B12: Seuil_Decision_Import | C12: 0.03 | D12: 0.05 | E12: 0.08 | F12: Seuil taux éco pour importer
A13: DECISION | B13: Poids_Prix | C13: 0.45 | D13: 0.4 | E13: 0.35 | F13: Poids critère prix
A14: DECISION | B14: Poids_Risque | C14: 0.25 | D14: 0.3 | E14: 0.35 | F14: Poids critère risque
A15: DECISION | B15: Poids_Delai | C15: 0.2 | D15: 0.2 | E15: 0.2 | F15: Poids critère délai
A16: DECISION | B16: Poids_Volume | C16: 0.1 | D16: 0.1 | E16: 0.1 | F16: Poids critère volume

Sheet PARAM_PROJET_ID
A1: PARAM_PROJET_ID
A2: PNR_MEDICAL_CENTER

Sheet T_PROJET
A1: PROJET_ID | B1: NOM_PROJET | C1: TYPE_PROJET | D1: STATUT | E1: DATE_CREATION | F1: DEVISE | G1: MODE_SOURCING | H1: NB_LOTS
A2: PNR_MEDICAL_CENTER | B2: Centre Médical Pointe Noire | C2: Médical | D2: Etude | E2: 2026-01-01 | F2: FCFA | G2: Mixte | H2: 17

Sheet T_FAM_ARTICLE
A1: FAM_ARTICLE_ID | B1: CODE_FAM_ARTICLE | C1: LIBELLE_FAM_ARTICLE | D1: FAM_METIER_ID | E1: IMPORTABLE | F1: TAUX_MAIN_OEUVRE | G1: RISQUE_IMPORT
A2: FA_001 | B2: GROS_OEUVRE | C2: Gros Œuvre & Démolition | D2: FM_01 | E2: 0 | F2: 0.4 | G2: 0
A3: FA_002 | B3: ETANCHEITE | C3: Étanchéité | D3: FM_02 | E3: 1 | F3: 0.3 | G3: 1
A4: FA_003 | B4: ALUCOBOND | C4: Alucobond – Bardage Façade | D4: FM_02 | E4: 1 | F4: 0.2 | G4: 2
A5: FA_004 | B5: REVETEMENTS_DURS | C5: Revêtements Durs | D5: FM_03 | E5: 1 | F5: 0.2 | G5: 2
A6: FA_005 | B6: MENUISERIE_ALU | C6: Menuiserie Aluminium & Vitrerie | D6: FM_03 | E6: 1 | F6: 0.25 | G6: 2
A7: FA_006 | B7: MENUISERIE_MET | C7: Menuiserie Métallique | D7: FM_03 | E7: 1 | F7: 0.3 | G7: 2
A8: FA_007 | B8: MENUISERIE_BOIS | C8: Menuiserie Bois | D8: FM_03 | E8: 1 | F8: 0.2 | G8: 2
A9: FA_008 | B9: ELECTRICITE | C9: Électricité | D9: FM_04 | E9: 1 | F9: 0.15 | G9: 3
A10: FA_009 | B10: CLIMATISATION | C10: Climatisation | D10: FM_04 | E10: 1 | F10: 0.1 | G10: 2.5
A11: FA_010 | B11: SECURITE_INCENDIE | C11: Sécurité Incendie & Vidéo | D11: FM_04 | E11: 1 | F11: 0.25 | G11: 2
A12: FA_011 | B12: PLOMBERIE | C12: Plomberie Sanitaire | D12: FM_04 | E12: 1 | F12: 0.2 | G12: 1.5
A13: FA_012 | B13: FAUX_PLAFONDS | C13: Faux Plafonds & Cloisons | D13: FM_03 | E13: 1 | F13: 0.1 | G13: 3.5
... A18: FA_017 | B18: GROUPE_ELECTROGENE | C18: Groupe Électrogène | D18: FM_04 | E18: 1 | F18: 0.1 | G18: 3

Sheet T_FAM_METIER
A1: FAM_METIER_ID | B1: CODE_FAM_METIER | C1: LIBELLE_FAM_METIER | D1: CATEGORIE_METIER | E1: ORDRE_AFFICHAGE
A2: FM_01 | B2: STRUCTURE | C2: Structure & Gros Œuvre | D2: STRUCTURE | E2: 1
A3: FM_02 | B3: ENVELOPPE | C3: Enveloppe & Étanchéité | D3: FINITION | E3: 2
A4: FM_03 | B4: FINITION | C4: Menuiserie & Finitions | D4: FINITION | E4: 3
A5: FM_04 | B5: TECHNIQUE | C5: Corps Techniques | D5: TECHNIQUE | E5: 4

Sheet T_BATIMENT
A1: BATIMENT_ID | B1: NOM_BATIMENT | C1: PROJET_ID | D1: ORDRE_AFFICHAGE
A2: BAT_PRINCIPAL | B2: Bâtiment Principal | C2: PNR_MEDICAL_CENTER | D2: 1
A3: BAT_ANNEXE | B3: Bâtiment Annexe | C3: PNR_MEDICAL_CENTER | D3: 0

Sheet T_MAPPING_DOMAINE_FAM
A1: DOMAINE | B1: FAM_ARTICLE_ID
A2: INSTALL | B2: FA_001
A3: DEMO | B3: FA_001
A4: MACON | B4: FA_001
A5: ETANCH | B5: FA_002
A6: ALUCOBOND | B6: FA_003
A7: REVET | B7: FA_004
A8: MEN | B8: FA_005
A9: ELEC | B9: FA_008
A10: CLIM | B10: FA_009
A11: SSI | B11: FA_010
A12: VIDEO | B12: FA_015
... A17: CDA | B17: FA_010

Sheet ---02_RAW---

Sheet ANALYTICS_PARETO_IMPORT

Sheet CLEAN_METRE_AGG
A1: PROJET_ID | B1: CODE_BPU | C1: DESIGNATION | D1: LOT | E1: BATIMENT_ID | F1: NIVEAU_ID | G1: UNITE | H1: QTE
A2: PNR_MEDICAL_CENTER | B2: BPU-INSTALL-GEN-MOB-001 | C2: Mobilisation | D2: LOT 1 | E2: BAT_PRINCIPAL | F2: GLOBAL | G2: FORFAIT | H2: 1
A3: PNR_MEDICAL_CENTER | B3: BPU-INSTALL-GEN-BASEVIE-002 | C3: Bureau de chantier, atelier, baraquement et clôture provisoire | D3: LOT 1 | E3: BAT_PRINCIPAL | F3: GLOBAL | G3: FORFAIT | H3: 1
A4: PNR_MEDICAL_CENTER | B4: BPU-INSTALL-GEN-CONC-003 | C4: Abonnement, mensualité concessionnaires | D4: LOT 1 | E4: BAT_PRINCIPAL | F4: GLOBAL | G4: FORFAIT | H4: 1
A5: PNR_MEDICAL_CENTER | B5: BPU-INSTALL-GEN-MAT-004 | C5: Matériel de chantier (engins, manutention etc) | D5: LOT 1 | E5: BAT_PRINCIPAL | F5: GLOBAL | G5: FORFAIT | H5: 1
A6: PNR_MEDICAL_CENTER | B6: BPU-INSTALL-GEN-DIVERS-005 | C6: Divers (sécurité, ASE, panneau de chantier...) | D6: LOT 1 | E6: BAT_PRINCIPAL | F6: GLOBAL | G6: FORFAIT | H6: 1
A7: PNR_MEDICAL_CENTER | B7: BPU-INSTALL-GEN-ETUDE-006 | C7: Études techniques et Essais | D7: LOT 1 | E7: BAT_PRINCIPAL | F7: GLOBAL | G7: FORFAIT | H7: 1
A8: PNR_MEDICAL_CENTER | B8: BPU-INSTALL-GEN-AXE-007 | C8: Ensemble des axes necessaires | D8: LOT 1 | E8: BAT_PRINCIPAL | F8: GLOBAL | G8: FORFAIT | H8: 1
A9: PNR_MEDICAL_CENTER | B9: BPU-DEMO-MUR-ESC-RDC-008 | C9: Démolition des murs et l'escalier (RDC) | D9: LOT 1 | E9: BAT_PRINCIPAL | F9: RDC | G9: FORFAIT | H9: 1
A10: PNR_MEDICAL_CENTER | B10: BPU-DEMO-MUR-ESC-ET1-ANNEXE-009 | C10: Démolition des murs et l'escalier y compris la dalle existente bâtiment annexe (ÉTAGE 1) | D10: LOT 1 | E10: BAT_ANNEXE | F10: ETAGE 1 | G10: FORFAIT | H10: 1
A11: PNR_MEDICAL_CENTER | B11: BPU-DEMO-MUR-ESC-ET2-010 | C11: Démolition des murs et l'escalier (ÉTAGE 2) | D11: LOT 1 | E11: BAT_PRINCIPAL | F11: ETAGE 2 | G11: FORFAIT | H11: 1
A12: PNR_MEDICAL_CENTER | B12: BPU-DEMO-EVAC-GRAVAT-011 | C12: Évacuation des gravats hors site | D12: LOT 1 | E12: BAT_PRINCIPAL | F12: GLOBAL | G12: FORFAIT | H12: 1
A13: PNR_MEDICAL_CENTER | B13: BPU-DEMO-DECAP-CARREAU-012 | C13: Décapage des carreaux sol existants en RDC | D13: LOT 1 | E13: BAT_PRINCIPAL | F13: RDC | G13: M2 | H13: 460
... A301: PNR_MEDICAL_CENTER | B301: BPU-PEINT-PLAF-INT-PANTEX-188 | C301: Peinture intérieure comprissant une impression en pantiprim, 02 couches d'enduits repassés et 02 couches de finitions en pante 800 | D301: LOT 14 | E301: BAT_PRINCIPAL | F301: DUPLEX 1 | G301: M2 | H301: 182

Sheet RAW__METRE
A1: PROJET_ID | B1: CODE_BPU | C1: DESIGNATION | D1: LOT | E1: BATIMENT_ID | F1: NIVEAU_ID | G1: UNITE | H1: QTE | I1: DATE_MAJ
A2: PROJ-MED-PNR-2025 | B2: BPU-INSTALL-GEN-MOB-001 | C2: Mobilisation | D2: LOT 1 | E2: PRINCIPAL | F2: GLOBAL | G2: FORFAIT | H2: 1 | I2: 46084
A3: PROJ-MED-PNR-2025 | B3: BPU-INSTALL-GEN-BASEVIE-002 | C3: Bureau de chantier, atelier, baraquement et clôture provisoire | D3: LOT 1 | E3: PRINCIPAL | F3: GLOBAL | G3: FORFAIT | H3: 1 | I3: 46084
A4: PROJ-MED-PNR-2025 | B4: BPU-INSTALL-GEN-CONC-003 | C4: Abonnement, mensualité concessionnaires | D4: LOT 1 | E4: PRINCIPAL | F4: GLOBAL | G4: FORFAIT | H4: 1 | I4: 46084
A5: PROJ-MED-PNR-2025 | B5: BPU-INSTALL-GEN-MAT-004 | C5: Matériel de chantier (engins, manutention etc) | D5: LOT 1 | E5: PRINCIPAL | F5: GLOBAL | G5: FORFAIT | H5: 1 | I5: 46084
A6: PROJ-MED-PNR-2025 | B6: BPU-INSTALL-GEN-DIVERS-005 | C6: Divers (sécurité, ASE, panneau de chantier...) | D6: LOT 1 | E6: PRINCIPAL | F6: GLOBAL | G6: FORFAIT | H6: 1 | I6: 46084
A7: PROJ-MED-PNR-2025 | B7: BPU-INSTALL-GEN-ETUDE-006 | C7: Études techniques et Essais | D7: LOT 1 | E7: PRINCIPAL | F7: GLOBAL | G7: FORFAIT | H7: 1 | I7: 46084
A8: PROJ-MED-PNR-2025 | B8: BPU-INSTALL-GEN-AXE-007 | C8: Ensemble des axes necessaires | D8: LOT 1 | E8: PRINCIPAL | F8: GLOBAL | G8: FORFAIT | H8: 1 | I8: 46084
A9: PROJ-MED-PNR-2025 | B9: BPU-DEMO-MUR-ESC-RDC-008 | C9: Démolition des murs et l'escalier (RDC) | D9: LOT 1 | E9: PRINCIPAL | F9: RDC | G9: FORFAIT | H9: 1 | I9: 46084
A10: PROJ-MED-PNR-2025 | B10: BPU-DEMO-MUR-ESC-ET1-ANNEXE-009 | C10: Démolition des murs et l'escalier y compris la dalle existente bâtiment annexe (ÉTAGE 1) | D10: LOT 1 | E10: ANNEXE | F10: ETAGE 1 | G10: FORFAIT | H10: 1 | I10: 46084
A11: PROJ-MED-PNR-2025 | B11: BPU-DEMO-MUR-ESC-ET2-010 | C11: Démolition des murs et l'escalier (ÉTAGE 2) | D11: LOT 1 | E11: PRINCIPAL | F11: ETAGE 2 | G11: FORFAIT | H11: 1 | I11: 46084
A12: PROJ-MED-PNR-2025 | B12: BPU-DEMO-EVAC-GRAVAT-011 | C12: Évacuation des gravats hors site | D12: LOT 1 | E12: PRINCIPAL | F12: GLOBAL | G12: FORFAIT | H12: 1 | I12: 46084
A13: PROJ-MED-PNR-2025 | B13: BPU-DEMO-DECAP-CARREAU-012 | C13: Décapage des carreaux sol existants en RDC | D13: LOT 1 | E13: PRINCIPAL | F13: RDC | G13: M2 | H13: 460 | I13: 46084
... A302: PROJ-MED-PNR-2025 | B302: BPU-PEINT-PLAF-INT-PANTEX-188 | C302: Peinture intérieure comprissant une impression en pantiprim, 02 couches d'enduits repassés et 02 couches de finitions en pante 800 | D302: LOT 14 | E302: PRINCIPAL | F302: DUPLEX 1 | G302: M2 | H302: 182 | I302: 46084

Sheet CLEAN__LOT
A1: LOT_ID | B1: CODE_LOT | C1: NOM_LOT | D1: DESCRIPTION_LOT | E1: ORDRE_LOT | F1: TYPE_LOT
A2: 1 | B2: L01 | C2: LOT 1 | D2: Gros œuvre et démolition | E2: 1 | F2: STRUCTURE
A3: 2 | B3: L02 | C3: LOT 2 | D3: Étanchéité | E3: 2 | F3: ARCHI
A4: 3 | B4: L03 | C4: LOT 3 | D4: Revêtement durs | E4: 3 | F4: ARCHI
A5: 4 | B5: L04 | C5: LOT 4 | D5: Menuiserie aluminium et vitrerie | E5: 4 | F5: ARCHI
A6: 5 | B6: L05 | C6: LOT 5 | D6: Menuiserie métallique et ferronnerie | E6: 5 | F6: ARCHI
A7: 6 | B7: L06 | C7: LOT 6 | D7: Menuiserie bois | E7: 6 | F7: ARCHI
A8: 7 | B8: L07 | C8: LOT 7 | D8: Electricité | E8: 7 | F8: TECH
A9: 8 | B9: L08 | C9: LOT 8 | D9: Climatisation | E9: 8 | F9: TECH
A10: 9 | B10: L09 | C10: LOT 9 | D10: Sécurité incendie et vidéo surveillance | E10: 9 | F10: TECH
A11: 10 | B11: L10 | C11: LOT 10 | D11: Plomberie sanitaire | E11: 10 | F11: TECH
A12: 11 | B12: L11 | C12: LOT 11 | D12: Faux plafond et cloisons BA13 | E12: 11 | F12: ARCHI
A13: 12 | B13: L12 | C13: L0T 12 | D13: Ascenseur | E13: 12 | F13: EQUIPEMENT
... A15: 14 | B15: L14 | C15: LOT 14 | D15: Peinture | E15: 14 | F15: FINITION

Sheet RAW__LOT
A1: LOT_ID | B1: CODE_LOT | C1: NOM_LOT | D1: DESCRIPTION_LOT | E1: ORDRE_LOT | F1: TYPE_LOT
A2: 1 | B2: L01 | C2: LOT 1 | D2: Gros œuvre et démolition | E2: 1 | F2: STRUCTURE
A3: 2 | B3: L02 | C3: LOT 2 | D3: Étanchéité | E3: 2 | F3: ARCHI
A4: 3 | B4: L03 | C4: LOT 3 | D4: Revêtement durs | E4: 3 | F4: ARCHI
A5: 4 | B5: L04 | C5: LOT 4 | D5: Menuiserie aluminium et vitrerie | E5: 4 | F5: ARCHI
A6: 5 | B6: L05 | C6: LOT 5 | D6: Menuiserie métallique et ferronnerie | E6: 5 | F6: ARCHI
A7: 6 | B7: L06 | C7: LOT 6 | D7: Menuiserie bois | E7: 6 | F7: ARCHI
A8: 7 | B8: L07 | C8: LOT 7 | D8: Electricité | E8: 7 | F8: TECH
A9: 8 | B9: L08 | C9: LOT 8 | D9: Climatisation | E9: 8 | F9: TECH
A10: 9 | B10: L09 | C10: LOT 9 | D10: Sécurité incendie et vidéo surveillance | E10: 9 | F10: TECH
A11: 10 | B11: L10 | C11: LOT 10 | D11: Plomberie sanitaire | E11: 10 | F11: TECH
A12: 11 | B12: L11 | C12: LOT 11 | D12: Faux plafond et cloisons BA13 | E12: 11 | F12: ARCHI
A13: 12 | B13: L12 | C13: L0T 12 | D13: Ascenseur | E13: 12 | F13: EQUIPEMENT
... A15: 14 | B15: L14 | C15: LOT 14 | D15: Peinture | E15: 14 | F15: FINITION

Sheet T_LOT
A1: LOT_ID | B1: CODE_LOT | C1: NOM_LOT | D1: DESCRIPTION_LOT | E1: ORDRE_LOT | F1: TYPE_LOT
A2: 1 | B2: L01 | C2: LOT 1 | D2: Gros œuvre et démolition | E2: 1 | F2: STRUCTURE
A3: 2 | B3: L02 | C3: LOT 2 | D3: Étanchéité | E3: 2 | F3: ARCHI
A4: 3 | B4: L03 | C4: LOT 3 | D4: Revêtement durs | E4: 3 | F4: ARCHI
A5: 4 | B5: L04 | C5: LOT 4 | D5: Menuiserie aluminium et vitrerie | E5: 4 | F5: ARCHI
A6: 5 | B6: L05 | C6: LOT 5 | D6: Menuiserie métallique et ferronnerie | E6: 5 | F6: ARCHI
A7: 6 | B7: L06 | C7: LOT 6 | D7: Menuiserie bois | E7: 6 | F7: ARCHI
A8: 7 | B8: L07 | C8: LOT 7 | D8: Electricité | E8: 7 | F8: TECH
A9: 8 | B9: L08 | C9: LOT 8 | D9: Climatisation | E9: 8 | F9: TECH
A10: 9 | B10: L09 | C10: LOT 9 | D10: Sécurité incendie et vidéo surveillance | E10: 9 | F10: TECH
A11: 10 | B11: L10 | C11: LOT 10 | D11: Plomberie sanitaire | E11: 10 | F11: TECH
A12: 11 | B12: L11 | C12: LOT 11 | D12: Faux plafond et cloisons BA13 | E12: 11 | F12: ARCHI
A13: 12 | B13: L12 | C13: L0T 12 | D13: Ascenseur | E13: 12 | F13: EQUIPEMENT
... A15: 14 | B15: L14 | C15: LOT 14 | D15: Peinture | E15: 14 | F15: FINITION

Sheet T_RAW__LOT
A1: LOT_ID | B1: CODE_LOT | C1: NOM_LOT | D1: DESCRIPTION_LOT | E1: ORDRE_LOT | F1: TYPE_LOT
A2: 1 | B2: L01 | C2: LOT 1 | D2: Gros œuvre et démolition | E2: 1 | F2: STRUCTURE
A3: 2 | B3: L02 | C3: LOT 2 | D3: Étanchéité | E3: 2 | F3: ARCHI
A4: 3 | B4: L03 | C4: LOT 3 | D4: Revêtement durs | E4: 3 | F4: ARCHI
A5: 4 | B5: L04 | C5: LOT 4 | D5: Menuiserie aluminium et vitrerie | E5: 4 | F5: ARCHI
A6: 5 | B6: L05 | C6: LOT 5 | D6: Menuiserie métallique et ferronnerie | E6: 5 | F6: ARCHI
A7: 6 | B7: L06 | C7: LOT 6 | D7: Menuiserie bois | E7: 6 | F7: ARCHI
A8: 7 | B8: L07 | C8: LOT 7 | D8: Electricité | E8: 7 | F8: TECH
A9: 8 | B9: L08 | C9: LOT 8 | D9: Climatisation | E9: 8 | F9: TECH
A10: 9 | B10: L09 | C10: LOT 9 | D10: Sécurité incendie et vidéo surveillance | E10: 9 | F10: TECH
A11: 10 | B11: L10 | C11: LOT 10 | D11: Plomberie sanitaire | E11: 10 | F11: TECH
A12: 11 | B12: L11 | C12: LOT 11 | D12: Faux plafond et cloisons BA13 | E12: 11 | F12: ARCHI
A13: 12 | B13: L12 | C13: L0T 12 | D13: Ascenseur | E13: 12 | F13: EQUIPEMENT
... A15: 14 | B15: L14 | C15: LOT 14 | D15: Peinture | E15: 14 | F15: FINITION

Sheet RAW_BPU_LOCAL
A1: CODE_BPU | B1: DESIGNATION | C1: LOT | D1: UNITE | E1: PU_LOCAL | F1: DATE_REFERENCE | G1: SOURCE | H1: FAM_ARTICLE_ID | I1: PROJET_ID | J1: TYPE_COUT | K1: ACTIF
A2: BPU-INSTALL-GEN-MOB-001 | B2: Mobilisation | C2: LOT 1 | D2: FORFAIT | E2: 4755250 | F2: 45882 | G2: DQE_MEDICAL CENTER_13-08-2025 | I2: PNMC_2025 | J2: MATERIAU | K2: 1
A3: BPU-INSTALL-GEN-BASEVIE-002 | B3: Bureau de chantier, atelier, baraquement et clôture provisoire | C3: LOT 1 | D3: FORFAIT | E3: 3758730 | F3: 45882 | G3: DQE_MEDICAL CENTER_13-08-2025 | I3: PNMC_2025 | J3: MATERIAU | K3: 1
A4: BPU-INSTALL-GEN-CONC-003 | B4: Abonnement, mensualité concessionnaires | C4: LOT 1 | D4: FORFAIT | E4: 2507000 | F4: 45882 | G4: DQE_MEDICAL CENTER_13-08-2025 | I4: PNMC_2025 | J4: MATERIAU | K4: 1
A5: BPU-INSTALL-GEN-MAT-004 | B5: Matériel de chantier (engins, manutention etc) | C5: LOT 1 | D5: FORFAIT | E5: 4213438 | F5: 45882 | G5: DQE_MEDICAL CENTER_13-08-2025 | I5: PNMC_2025 | J5: MATERIAU | K5: 1
A6: BPU-INSTALL-GEN-DIVERS-005 | B6: Divers (sécurité, ASE, panneau de chantier...) | C6: LOT 1 | D6: FORFAIT | E6: 4945000 | F6: 45882 | G6: DQE_MEDICAL CENTER_13-08-2025 | I6: PNMC_2025 | J6: MATERIAU | K6: 1
A7: BPU-INSTALL-GEN-ETUDE-006 | B7: Études techniques et Essais | C7: LOT 1 | D7: FORFAIT | E7: 4795500 | F7: 45882 | G7: DQE_MEDICAL CENTER_13-08-2025 | I7: PNMC_2025 | J7: MATERIAU | K7: 1
A8: BPU-INSTALL-GEN-AXE-007 | B8: Ensemble des axes necessaires | C8: LOT 1 | D8: FORFAIT | E8: 1265000 | F8: 45882 | G8: DQE_MEDICAL CENTER_13-08-2025 | I8: PNMC_2025 | J8: MATERIAU | K8: 1
A9: BPU-DEMO-MUR-ESC-RDC-008 | B9: Démolition des murs et l'escalier (RDC) | C9: LOT 1 | D9: FORFAIT | E9: 1725000 | F9: 45882 | G9: DQE_MEDICAL CENTER_13-08-2025 | I9: PNMC_2025 | J9: MATERIAU | K9: 1
A10: BPU-DEMO-MUR-ESC-ET1-ANNEXE-009 | B10: Démolition des murs et l'escalier y compris la dalle existente bâtiment annexe (ÉTAGE 1) | C10: LOT 1 | D10: FORFAIT | E10: 2587500 | F10: 45882 | G10: DQE_MEDICAL CENTER_13-08-2025 | I10: PNMC_2025 | J10: MATERIAU | K10: 1
A11: BPU-DEMO-MUR-ESC-ET2-010 | B11: Démolition des murs et l'escalier (ÉTAGE 2) | C11: LOT 1 | D11: FORFAIT | E11: 1725000 | F11: 45882 | G11: DQE_MEDICAL CENTER_13-08-2025 | I11: PNMC_2025 | J11: MATERIAU | K11: 1
A12: BPU-DEMO-EVAC-GRAVAT-011 | B12: Évacuation des gravats hors site | C12: LOT 1 | D12: FORFAIT | E12: 552000 | F12: 45882 | G12: DQE_MEDICAL CENTER_13-08-2025 | I12: PNMC_2025 | J12: MATERIAU | K12: 1
A13: BPU-DEMO-DECAP-CARREAU-012 | B13: Décapage des carreaux sol existants en RDC | C13: LOT 1 | D13: M2 | E13: 5750 | F13: 45882 | G13: DQE_MEDICAL CENTER_13-08-2025 | I13: PNMC_2025 | J13: MATERIAU | K13: 1
... A168: BPU-PLOMB-SURPRESSION-167 | B168: Station de surpression au complet comprenant les 2 pompes de surpression sanitaire de 27 m3/h - 35 mCE y compris une vessie de 300 litres, accessoires de raccordement et équipements de la bâche à eau | C168: LOT 10 | D168: FORFAIT | E168: 1725000 | F168: 45882 | G168: DQE_MEDICAL CENTER_13-08-2025 | I168: PNMC_2025 | J168: MATERIAU | K168: 1
A169: BPU-PLOMB-RACC-BACHE-168 | B169: Raccordement des bâches à eau y compris raccordement au réseau avec tous les accessoires (vannes | C169: LOT 11 | D169: FORFAIT | E169: 402500 | F169: 45883 | G169: DQE_MEDICAL CENTER_13-08-2026 | H169: 45882 | I169: PNMC_2025 | J169: MATERIAU | K169: 1
A170: BPU-PLOMB-TAMPON-FONTE-169 | B170: Tampon de fermeture en fonte pour fosses | C170: LOT 10 | D170: FORFAIT | E170: 402500 | F170: 45882 | G170: DQE_MEDICAL CENTER_13-08-2025 | I170: PNMC_2025 | J170: MATERIAU | K170: 1
A171: BPU-PLOMB-SIPHON-SOL-D63-170 | B171: Siphon de sol D63 | C171: LOT 10 | D171: FORFAIT | E171: 11500 | F171: 45882 | G171: DQE_MEDICAL CENTER_13-08-2025 | I171: PNMC_2025 | J171: MATERIAU | K171: 1
A172: BPU-PLOMB-COMPT-CLAPET-171 | B172: Ensemble vanne, compteur, clapet anti- | C172: LOT 10 | D172: FORFAIT | E172: 862500 | F172: 45882 | G172: DQE_MEDICAL CENTER_13-08-2025 | I172: PNMC_2025 | J172: MATERIAU | K172: 1
A173: BPU-PLOMB-VMC-CAIS-01-172 | B173: Caisson de Ventilation Mécanique Contrôlée | C173: LOT 10 | D173: FORFAIT | E173: 575000 | F173: 45882 | G173: DQE_MEDICAL CENTER_13-08-2025 | I173: PNMC_2025 | J173: MATERIAU | K173: 1
A174: BPU-PLOMB-VMC-CAIS-02-173 | B174: Caisson de Ventilation Mécanique Contrôlée | C174: LOT 10 | D174: FORFAIT | E174: 402500 | F174: 45882 | G174: DQE_MEDICAL CENTER_13-08-2025 | I174: PNMC_2025 | J174: MATERIAU | K174: 1
A175: BPU-PLOMB-BOUCHE-EXTR-ALIZE-01-174 | B175: Bouche d'extraction de type Alizé | C175: LOT 10 | D175: FORFAIT | E175: 26450 | F175: 45882 | G175: DQE_MEDICAL CENTER_13-08-2025 | I175: PNMC_2025 | J175: MATERIAU | K175: 1
A176: BPU-PLOMB-BOUCHE-EXTR-ALIZE-02-175 | B176: Bouche d'extraction de type Alizé | C176: LOT 10 | D176: FORFAIT | E176: 28750 | F176: 45882 | G176: DQE_MEDICAL CENTER_13-08-2025 | I176: PNMC_2025 | J176: MATERIAU | K176: 1
A177: BPU-PLOMB-CONDUIT-SPIR-AC-GALV-D125-176 | B177: Conduit spiralé en acier galvanisé D125 | C177: LOT 10 | D177: ML | E177: 14375 | F177: 45882 | G177: DQE_MEDICAL CENTER_13-08-2025 | I177: PNMC_2025 | J177: MATERIAU | K177: 1
A178: BPU-PLOMB-CONDUIT-SPIR-AC-GALV-D160-177 | B178: Conduit spiralé en acier galvanisé D160 | C178: LOT 10 | D178: ML | E178: 19550 | F178: 45882 | G178: DQE_MEDICAL CENTER_13-08-2025 | I178: PNMC_2025 | J178: MATERIAU | K178: 1
A179: BPU-PLOMB-CONDUIT-SPIR-AC-GALV-D200-178 | B179: Conduit spiralé en acier galvanisé D200 | C179: LOT 10 | D179: ML | E179: 29210 | F179: 45882 | G179: DQE_MEDICAL CENTER_13-08-2025 | I179: PNMC_2025 | J179: MATERIAU | K179: 1
A180: BPU-FP-FP-ISORELLE-179 | B180: Faux plafonds en plaquette d'isorelle ou | C180: LOT 11 | D180: M2 | E180: 26450 | F180: 45882 | G180: DQE_MEDICAL CENTER_13-08-2025 | I180: PNMC_2025 | J180: MATERIAU | K180: 1
A181: BPU-FP-CLOISON-BA13-LV-180 | B181: Cloison en BA 13 avec laine de verre | C181: LOT 11 | D181: M2 | E181: 39100 | F181: 45882 | G181: DQE_MEDICAL CENTER_13-08-2025 | I181: PNMC_2025 | J181: MATERIAU | K181: 1
... A189: BPU-PEINT-PLAF-INT-PANTEX-188 | B189: Peinture intérieure comprissant une impression en pantiprim, 02 couches d'enduits repassés et 02 couches de finitions en pante 800 | C189: LOT 14 | D189: M2 | E189: 6325 | F189: 45882 | G189: DQE_MEDICAL CENTER_13-08-2025 | I189: PNMC_2025 | J189: MATERIAU | K189: 1

Sheet TEST_COHERENCE_PRIX
A1: CODE_BPU | B1: DESIGNATION | C1: LOT | D1: BATIMENT_ID | E1: NIVEAU_ID | F1: UNITE | G1: QTE | H1: DATE_MAJ | I1: PROJET_ID | J1: PU_LOCAL | K1: PU_CHINE | L1: PRIX_LOCAL_OK | M1: PRIX_CHINE_OK
A2: BPU-INSTALL-GEN-MOB-001 | B2: Mobilisation | C2: LOT 1 | D2: BAT_PRINCIPAL | E2: GLOBAL | F2: FORFAIT | G2: 1 | H2: 46084 | I2: PNR_MEDICAL_CENTER | J2: 4755250 | K2: 4755250 | L2: 1 | M2: 1
A3: BPU-INSTALL-GEN-BASEVIE-002 | B3: Bureau de chantier, atelier, baraquement et clôture provisoire | C3: LOT 1 | D3: BAT_PRINCIPAL | E3: GLOBAL | F3: FORFAIT | G3: 1 | H3: 46084 | I3: PNR_MEDICAL_CENTER | J3: 3758730 | K3: 3758730 | L3: 1 | M3: 1
A4: BPU-INSTALL-GEN-CONC-003 | B4: Abonnement, mensualité concessionnaires | C4: LOT 1 | D4: BAT_PRINCIPAL | E4: GLOBAL | F4: FORFAIT | G4: 1 | H4: 46084 | I4: PNR_MEDICAL_CENTER | J4: 2507000 | K4: 2507000 | L4: 1 | M4: 1
A5: BPU-INSTALL-GEN-MAT-004 | B5: Matériel de chantier (engins, manutention etc) | C5: LOT 1 | D5: BAT_PRINCIPAL | E5: GLOBAL | F5: FORFAIT | G5: 1 | H5: 46084 | I5: PNR_MEDICAL_CENTER | J5: 4213438 | K5: 4213438 | L5: 1 | M5: 1
A6: BPU-INSTALL-GEN-DIVERS-005 | B6: Divers (sécurité, ASE, panneau de chantier...) | C6: LOT 1 | D6: BAT_PRINCIPAL | E6: GLOBAL | F6: FORFAIT | G6: 1 | H6: 46084 | I6: PNR_MEDICAL_CENTER | J6: 4945000 | K6: 4945000 | L6: 1 | M6: 1
A7: BPU-INSTALL-GEN-ETUDE-006 | B7: Études techniques et Essais | C7: LOT 1 | D7: BAT_PRINCIPAL | E7: GLOBAL | F7: FORFAIT | G7: 1 | H7: 46084 | I7: PNR_MEDICAL_CENTER | J7: 4795500 | K7: 4795500 | L7: 1 | M7: 1
A8: BPU-INSTALL-GEN-AXE-007 | B8: Ensemble des axes necessaires | C8: LOT 1 | D8: BAT_PRINCIPAL | E8: GLOBAL | F8: FORFAIT | G8: 1 | H8: 46084 | I8: PNR_MEDICAL_CENTER | J8: 1265000 | K8: 1265000 | L8: 1 | M8: 1
A9: BPU-DEMO-MUR-ESC-RDC-008 | B9: Démolition des murs et l'escalier (RDC) | C9: LOT 1 | D9: BAT_PRINCIPAL | E9: RDC | F9: FORFAIT | G9: 1 | H9: 46084 | I9: PNR_MEDICAL_CENTER | J9: 1725000 | K9: 1725000 | L9: 1 | M9: 1
A10: BPU-DEMO-MUR-ESC-ET1-ANNEXE-009 | B10: Démolition des murs et l'escalier y compris la dalle existente bâtiment annexe (ÉTAGE 1) | C10: LOT 1 | D10: BAT_ANNEXE | E10: ETAGE 1 | F10: FORFAIT | G10: 1 | H10: 46084 | I10: PNR_MEDICAL_CENTER | J10: 2587500 | K10: 2587500 | L10: 1 | M10: 1
A11: BPU-DEMO-MUR-ESC-ET2-010 | B11: Démolition des murs et l'escalier (ÉTAGE 2) | C11: LOT 1 | D11: BAT_PRINCIPAL | E11: ETAGE 2 | F11: FORFAIT | G11: 1 | H11: 46084 | I11: PNR_MEDICAL_CENTER | J11: 1725000 | K11: 1725000 | L11: 1 | M11: 1
A12: BPU-DEMO-EVAC-GRAVAT-011 | B12: Évacuation des gravats hors site | C12: LOT 1 | D12: BAT_PRINCIPAL | E12: GLOBAL | F12: FORFAIT | G12: 1 | H12: 46084 | I12: PNR_MEDICAL_CENTER | J12: 552000 | K12: 552000 | L12: 1 | M12: 1
A13: BPU-DEMO-DECAP-CARREAU-012 | B13: Décapage des carreaux sol existants en RDC | C13: LOT 1 | D13: BAT_PRINCIPAL | E13: RDC | F13: M2 | G13: 460 | H13: 46084 | I13: PNR_MEDICAL_CENTER | J13: 5750 | L13: 1 | M13: 0
A14: BPU-MACON-FOND-BET-PROP-013 | B14: Béton de propreté | C14: LOT 1 | D14: BAT_PRINCIPAL | E14: FONDATIONS | F14: M3 | G14: 3.07 | H14: 46084 | I14: PNR_MEDICAL_CENTER | J14: 338720 | K14: 338720 | L14: 1 | M14: 1
A15: BPU-MACON-FOND-BET-400-014 | B15: Béton 400 hydr | C15: LOT 1 | D15: BAT_PRINCIPAL | E15: FONDATIONS | F15: M3 | G15: 4.36 | H15: 46084 | I15: PNR_MEDICAL_CENTER | J15: 189175 | K15: 189175 | L15: 1 | M15: 1
A16: BPU-MACON-FOND-COF-015 | B16: Coffrage | C16: LOT 1 | D16: BAT_PRINCIPAL | E16: FONDATIONS | F16: M2 | G16: 15.84 | H16: 46084 | I16: PNR_MEDICAL_CENTER | J16: 5750 | K16: 3350 | L16: 1 | M16: 1
A17: BPU-MACON-FOND-AC-016 | B17: Acier | C17: LOT 1 | D17: BAT_PRINCIPAL | E17: FONDATIONS | F17: KG | G17: 436 | H17: 46084 | I17: PNR_MEDICAL_CENTER | J17: 1380 | K17: 370 | L17: 1 | M17: 1
A18: BPU-MACON-SSO-AGGL-PLEIN-026 | B18: Agglos pleins 20x20x50 | C18: LOT 1 | D18: BAT_PRINCIPAL | E18: FONDATIONS | F18: M2 | G18: 78.98 | H18: 46084 | I18: PNR_MEDICAL_CENTER | J18: 12180 | K18: 12180 | L18: 1 | M18: 1
A19: BPU-MACON-ELEV-POT-BET-400-017 | B19: Béton 400 hydr (Amorces poteaux) | C19: LOT 1 | D19: BAT_PRINCIPAL | E19: FONDATIONS | F19: M3 | G19: 1.65 | H19: 46084 | I19: PNR_MEDICAL_CENTER | J19: 189175 | L19: 1 | M19: 0
A20: BPU-MACON-AGGL-CREUX-20-046 | B20: Agglos creux 20x20x50 | C20: LOT 1 | D20: BAT_PRINCIPAL | E20: RDC | F20: M2 | G20: 1 | H20: 46084 | I20: PNR_MEDICAL_CENTER | J20: 11185 | K20: 11185 | L20: 1 | M20: 1
A21: BPU-MACON-ELEV-POT-COF-018 | B21: Coffrage (Amorces poteaux) | C21: LOT 1 | D21: BAT_PRINCIPAL | E21: FONDATIONS | F21: M2 | G21: 26.4 | H21: 46084 | I21: PNR_MEDICAL_CENTER | J21: 5750 | L21: 1 | M21: 0
A22: BPU-MACON-END-INT-EXT-047 | B22: Enduits intérieurs et extérieurs sur murs | C22: LOT 1 | D22: BAT_PRINCIPAL | E22: RDC | F22: M2 | G22: 1 | H22: 46084 | I22: PNR_MEDICAL_CENTER | J22: 3827 | K22: 3827 | L22: 1 | M22: 1
A23: BPU-MACON-ELEV-POT-AC-019 | B23: Acier (Amorces poteaux) | C23: LOT 1 | D23: BAT_PRINCIPAL | E23: FONDATIONS | F23: KG | G23: 198 | H23: 46084 | I23: PNR_MEDICAL_CENTER | J23: 1380 | L23: 1 | M23: 0
A24: BPU-MACON-END-SOUS-PLF-048 | B24: Enduits sous plafond | C24: LOT 1 | D24: BAT_PRINCIPAL | E24: RDC | F24: M2 | G24: 1 | H24: 46084 | I24: PNR_MEDICAL_CENTER | J24: 3827 | K24: 3827 | L24: 1 | M24: 1
A25: BPU-MACON-ELEV-LONG-BET-400-020 | B25: Béton 400 hydr (Longrines) | C25: LOT 1 | D25: BAT_PRINCIPAL | E25: FONDATIONS | F25: M3 | G25: 3.72 | H25: 46084 | I25: PNR_MEDICAL_CENTER | J25: 189175 | L25: 1 | M25: 0
A26: BPU-ETANCH-TERR-ACC-FORME-059 | B26: Forme de pente | C26: LOT 2 | D26: BAT_PRINCIPAL | E26: DUPLEX 1 | F26: M2 | G26: 320 | H26: 46084 | I26: PNR_MEDICAL_CENTER | J26: 11793 | K26: 11793 | L26: 1 | M26: 1
A27: BPU-MACON-ELEV-LONG-COF-021 | B27: Coffrage (Longrines) | C27: LOT 1 | D27: BAT_PRINCIPAL | E27: FONDATIONS | F27: M2 | G27: 37.33 | H27: 46084 | I27: PNR_MEDICAL_CENTER | J27: 5750 | L27: 1 | M27: 0
A28: BPU-ETANCH-TERR-ACC-BI-060 | B28: Revêtement bicouche sous protection lourde | C28: LOT 2 | D28: BAT_PRINCIPAL | E28: DUPLEX 1 | F28: M2 | G28: 320 | H28: 46084 | I28: PNR_MEDICAL_CENTER | J28: 34552 | K28: 6100 | L28: 1 | M28: 1
A29: BPU-MACON-ELEV-LONG-AC-022 | B29: Acier (Longrines) | C29: LOT 1 | D29: BAT_PRINCIPAL | E29: FONDATIONS | F29: KG | G29: 484 | H29: 46084 | I29: PNR_MEDICAL_CENTER | J29: 1380 | L29: 1 | M29: 0
A30: BPU-ETANCH-TERR-ACC-RELEV-061 | B30: Relevé d'étanchéité h=50 cm | C30: LOT 2 | D30: BAT_PRINCIPAL | E30: DUPLEX 1 | F30: ML | G30: 120 | H30: 46084 | I30: PNR_MEDICAL_CENTER | J30: 8641 | K30: 3050 | L30: 1 | M30: 1
A31: BPU-MACON-ELEV-DALL-BET-023 | B31: Béton (Dallage sol) | C31: LOT 1 | D31: BAT_PRINCIPAL | E31: FONDATIONS | F31: M3 | G31: 33.2 | H31: 46084 | I31: PNR_MEDICAL_CENTER | J31: 189175 | L31: 1 | M31: 0
A32: BPU-ETANCH-TERR-INACC-FORME-062 | B32: Forme de pente | C32: LOT 2 | D32: BAT_PRINCIPAL | E32: DUPLEX 1 | F32: M2 | G32: 56.75 | H32: 46084 | I32: PNR_MEDICAL_CENTER | J32: 11793 | K32: 11793 | L32: 1 | M32: 1
A33: BPU-ETANCH-TERR-INACC-FORME-062 | B33: Forme de pente | C33: LOT 2 | D33: BAT_PRINCIPAL | E33: TERRASSE | F33: M2 | G33: 83 | H33: 46084 | I33: PNR_MEDICAL_CENTER | J33: 11793 | K33: 11793 | L33: 1 | M33: 1
A34: BPU-ETANCH-TERR-INACC-FORME-062 | B34: Forme de pente | C34: LOT 2 | D34: BAT_ANNEXE | E34: TERRASSE | F34: M2 | G34: 231 | H34: 46084 | I34: PNR_MEDICAL_CENTER | J34: 11793 | K34: 11793 | L34: 1 | M34: 1
A35: BPU-MACON-ELEV-DALL-COF-024 | B35: Coffrage (Dallage sol) | C35: LOT 1 | D35: BAT_PRINCIPAL | E35: FONDATIONS | F35: M2 | G35: 66.8 | H35: 46084 | I35: PNR_MEDICAL_CENTER | J35: 5750 | L35: 1 | M35: 0
A36: BPU-ETANCH-TERR-INACC-MONO-063 | B36: Revêtement monocouche sous protection lourde | C36: LOT 2 | D36: BAT_PRINCIPAL | E36: DUPLEX 1 | F36: M2 | G36: 56.75 | H36: 46084 | I36: PNR_MEDICAL_CENTER | J36: 17276 | K36: 4575 | L36: 1 | M36: 1
A37: BPU-ETANCH-TERR-INACC-MONO-063 | B37: Revêtement monocouche sous protection | C37: LOT 2 | D37: BAT_PRINCIPAL | E37: TERRASSE | F37: M2 | G37: 83 | H37: 46084 | I37: PNR_MEDICAL_CENTER | J37: 17276 | K37: 4575 | L37: 1 | M37: 1
A38: BPU-ETANCH-TERR-INACC-MONO-063 | B38: Revêtement bicouche sous protection | C38: LOT 2 | D38: BAT_ANNEXE | E38: TERRASSE | F38: M2 | G38: 231 | H38: 46084 | I38: PNR_MEDICAL_CENTER | J38: 17276 | K38: 4575 | L38: 1 | M38: 1
A39: BPU-MACON-ELEV-DALL-AC-025 | B39: Acier (Dallage sol) | C39: LOT 1 | D39: BAT_PRINCIPAL | E39: FONDATIONS | F39: KG | G39: 2324 | H39: 46084 | I39: PNR_MEDICAL_CENTER | J39: 1380 | L39: 1 | M39: 0
A40: BPU-ETANCH-TERR-INACC-RELEV-064 | B40: Relevé d'étanchéité h=50 cm | C40: LOT 2 | D40: BAT_PRINCIPAL | E40: DUPLEX 1 | F40: ML | G40: 36 | H40: 46084 | I40: PNR_MEDICAL_CENTER | J40: 8641 | K40: 3050 | L40: 1 | M40: 1
A41: BPU-ETANCH-TERR-INACC-RELEV-064 | B41: Relevé d'étanchéité h=50 cm | C41: LOT 2 | D41: BAT_PRINCIPAL | E41: TERRASSE | F41: ML | G41: 11.87 | H41: 46084 | I41: PNR_MEDICAL_CENTER | J41: 8641 | K41: 3050 | L41: 1 | M41: 1
A42: BPU-ETANCH-TERR-INACC-RELEV-064 | B42: Relevé d'étanchéité h=50 cm | C42: LOT 2 | D42: BAT_ANNEXE | E42: TERRASSE | F42: ML | G42: 101.1 | H42: 46084 | I42: PNR_MEDICAL_CENTER | J42: 8641 | K42: 3050 | L42: 1 | M42: 1
A43: BPU-REVET-FAIENCE-GRANIT-065 | B43: Faïence murale en granite ou similaire | C43: LOT 3 | D43: BAT_PRINCIPAL | E43: RDC | F43: M2 | G43: 314.59 | H43: 46084 | I43: PNR_MEDICAL_CENTER | J43: 28175 | K43: 5490 | L43: 1 | M43: 1
A44: BPU-REVET-FAIENCE-GRANIT-065 | B44: Faïence murale en granite ou similaire | C44: LOT 3 | D44: BAT_PRINCIPAL | E44: ETAGE 1 | F44: M2 | G44: 351.33 | H44: 46084 | I44: PNR_MEDICAL_CENTER | J44: 28175 | K44: 5490 | L44: 1 | M44: 1
A45: BPU-REVET-FAIENCE-GRANIT-065 | B45: Faïence murale en granite ou similaire | C45: LOT 3 | D45: BAT_PRINCIPAL | E45: ETAGE 2 | F45: M2 | G45: 278.2 | H45: 46084 | I45: PNR_MEDICAL_CENTER | J45: 28175 | K45: 5490 | L45: 1 | M45: 1
A46: BPU-REVET-FAIENCE-GRANIT-065 | B46: Faïence murale en granite ou similaire | C46: LOT 3 | D46: BAT_PRINCIPAL | E46: DUPLEX 1 | F46: M2 | G46: 162.06 | H46: 46084 | I46: PNR_MEDICAL_CENTER | J46: 28175 | K46: 5490 | L46: 1 | M46: 1
A47: BPU-REVET-FAIENCE-GRANIT-065 | B47: Faïence murale en granite ou similaire | C47: LOT 3 | D47: BAT_PRINCIPAL | E47: DUPLEX 2 | F47: M2 | G47: 99.33 | H47: 46084 | I47: PNR_MEDICAL_CENTER | J47: 28175 | K47: 5490 | L47: 1 | M47: 1
A48: BPU-REVET-FAIENCE-GRANIT-065 | B48: Faïence murale en granite ou similaire | C48: LOT 3 | D48: BAT_ANNEXE | E48: RDC | F48: M2 | G48: 87.52 | H48: 46084 | I48: PNR_MEDICAL_CENTER | J48: 28175 | K48: 5490 | L48: 1 | M48: 1
A49: BPU-REVET-FAIENCE-GRANIT-065 | B49: Faïence murale en granite ou similaire | C49: LOT 3 | D49: BAT_ANNEXE | E49: RDC | F49: M2 | G49: 56.71 | H49: 46084 | I49: PNR_MEDICAL_CENTER | J49: 28175 | K49: 5490 | L49: 1 | M49: 1
A50: BPU-REVET-FAIENCE-GRANIT-065 | B50: Faïence murale en granite ou similaire | C50: LOT 3 | D50: BAT_ANNEXE | E50: ETAGE 1 | F50: M2 | G50: 60.7 | H50: 46084 | I50: PNR_MEDICAL_CENTER | J50: 28175 | K50: 5490 | L50: 1 | M50: 1
A51: BPU-MACON-ELEV-POT-BET-400-027 | B51: Béton 400 hydr (Dallage sol - Annexe) | C51: LOT 1 | D51: BAT_ANNEXE | E51: FONDATIONS | F51: M3 | G51: 30.3 | H51: 46084 | I51: PNR_MEDICAL_CENTER | J51: 189175 | L51: 1 | M51: 0
A52: BPU-REVET-SOL-GRANIT-60X60-066 | B52: Granite tile : SARADO Grey-Flamed 60x60 | C52: LOT 3 | D52: BAT_PRINCIPAL | E52: RDC | F52: M2 | G52: 559 | H52: 46084 | I52: PNR_MEDICAL_CENTER | J52: 33925 | K52: 10065 | L52: 1 | M52: 1
A53: BPU-REVET-SOL-GRANIT-60X60-066 | B53: Granite tile : SARADO Grey-Flamed 60x60 | C53: LOT 3 | D53: BAT_PRINCIPAL | E53: ETAGE 1 | F53: M2 | G53: 594 | H53: 46084 | I53: PNR_MEDICAL_CENTER | J53: 33925 | K53: 10065 | L53: 1 | M53: 1
A54: BPU-REVET-SOL-GRANIT-60X60-066 | B54: Granite tile : SARADO Grey-Flamed 60x60 | C54: LOT 3 | D54: BAT_PRINCIPAL | E54: ETAGE 2 | F54: M2 | G54: 557 | H54: 46084 | I54: PNR_MEDICAL_CENTER | J54: 33925 | K54: 10065 | L54: 1 | M54: 1
A55: BPU-REVET-SOL-GRANIT-60X60-066 | B55: Granite tile : SARADO Grey-Flamed 60x60 | C55: LOT 3 | D55: BAT_PRINCIPAL | E55: DUPLEX 1 | F55: M2 | G55: 557 | H55: 46084 | I55: PNR_MEDICAL_CENTER | J55: 33925 | K55: 10065 | L55: 1 | M55: 1
A56: BPU-REVET-SOL-GRANIT-60X60-066 | B56: Granite tile : SARADO Grey-Flamed 60x60 | C56: LOT 3 | D56: BAT_PRINCIPAL | E56: DUPLEX 2 | F56: M2 | G56: 182 | H56: 46084 | I56: PNR_MEDICAL_CENTER | J56: 33925 | K56: 10065 | L56: 1 | M56: 1
A57: BPU-REVET-SOL-GRANIT-60X60-066 | B57: Granite tile : SARADO Grey-Flamed 60x60 | C57: LOT 3 | D57: BAT_ANNEXE | E57: RDC | F57: M2 | G57: 210 | H57: 46084 | I57: PNR_MEDICAL_CENTER | J57: 33925 | K57: 10065 | L57: 1 | M57: 1
A58: BPU-REVET-SOL-GRANIT-60X60-066 | B58: Granite tile : SARADO Grey-Flamed 60x60 | C58: LOT 3 | D58: BAT_ANNEXE | E58: ETAGE 1 | F58: M2 | G58: 210 | H58: 46084 | I58: PNR_MEDICAL_CENTER | J58: 33925 | K58: 10065 | L58: 1 | M58: 1
A59: BPU-MACON-ELEV-POT-COF-028 | B59: Coffrage (Dallage sol - Annexe) | C59: LOT 1 | D59: BAT_ANNEXE | E59: FONDATIONS | F59: M2 | G59: 10.8 | H59: 46084 | I59: PNR_MEDICAL_CENTER | J59: 5750 | L59: 1 | M59: 0
A60: BPU-REVET-PLINTH-GRANIT-067 | B60: Plinthe 10x60 Granite tile : SARADO Grey-Flamed | C60: LOT 3 | D60: BAT_PRINCIPAL | E60: RDC | F60: ML | G60: 418.68 | H60: 46084 | I60: PNR_MEDICAL_CENTER | J60: 5750 | K60: 2745 | L60: 1 | M60: 1
A61: BPU-REVET-PLINTH-GRANIT-067 | B61: Plinthe 10x60 Granite tile : SARADO Grey-Flamed | C61: LOT 3 | D61: BAT_PRINCIPAL | E61: ETAGE 1 | F61: ML | G61: 494.58 | H61: 46084 | I61: PNR_MEDICAL_CENTER | J61: 5750 | K61: 2745 | L61: 1 | M61: 1
A62: BPU-REVET-PLINTH-GRANIT-067 | B62: Plinthe 10x60 Granite tile : SARADO Grey-Flamed | C62: LOT 3 | D62: BAT_PRINCIPAL | E62: ETAGE 2 | F62: ML | G62: 499.38 | H62: 46084 | I62: PNR_MEDICAL_CENTER | J62: 5750 | K62: 2745 | L62: 1 | M62: 1
A63: BPU-REVET-PLINTH-GRANIT-067 | B63: Plinthe 10x60 Granite tile : SARADO Grey-Flamed | C63: LOT 3 | D63: BAT_PRINCIPAL | E63: DUPLEX 1 | F63: ML | G63: 300.82 | H63: 46084 | I63: PNR_MEDICAL_CENTER | J63: 5750 | K63: 2745 | L63: 1 | M63: 1
A64: BPU-REVET-PLINTH-GRANIT-067 | B64: Plinthe 10x60 Granite tile : SARADO Grey-Flamed | C64: LOT 3 | D64: BAT_PRINCIPAL | E64: DUPLEX 2 | F64: ML | G64: 172.84 | H64: 46084 | I64: PNR_MEDICAL_CENTER | J64: 5750 | K64: 2745 | L64: 1 | M64: 1
A65: BPU-REVET-PLINTH-GRANIT-067 | B65: Plinthe 10x60 Granite tile : SARADO Grey-Flamed | C65: LOT 3 | D65: BAT_ANNEXE | E65: RDC | F65: ML | G65: 119.94 | H65: 46084 | I65: PNR_MEDICAL_CENTER | J65: 5750 | K65: 2745 | L65: 1 | M65: 1
A66: BPU-REVET-PLINTH-GRANIT-067 | B66: Plinthe 10x60 Granite tile : SARADO Grey-Flamed | C66: LOT 3 | D66: BAT_ANNEXE | E66: ETAGE 1 | F66: ML | G66: 192.38 | H66: 46084 | I66: PNR_MEDICAL_CENTER | J66: 5750 | K66: 2745 | L66: 1 | M66: 1
A67: BPU-MACON-ELEV-POT-AC-029 | B67: Acier (Dallage sol - Annexe) | C67: LOT 1 | D67: BAT_ANNEXE | E67: FONDATIONS | F67: KG | G67: 1818 | H67: 46084 | I67: PNR_MEDICAL_CENTER | J67: 1380 | L67: 1 | M67: 0
A68: BPU-REVET-PLAN-TRAV-GRANIT-068 | B68: Table de travail en granite ou similaire | C68: LOT 3 | D68: BAT_ANNEXE | E68: RDC | F68: ML | G68: 5.19 | H68: 46084 | I68: PNR_MEDICAL_CENTER | J68: 517500 | K68: 42700 | L68: 1 | M68: 1
A69: BPU-MACON-ELEV-POUT-BET-350-030 | B69: Béton 400 (Poteaux RDC) | C69: LOT 1 | D69: BAT_PRINCIPAL | E69: RDC | F69: M3 | G69: 2.48 | H69: 46084 | I69: PNR_MEDICAL_CENTER | J69: 189175 | L69: 1 | M69: 0
A70: BPU-MACON-ELEV-POUT-COF-031 | B70: Coffrage (Poteaux RDC) | C70: LOT 1 | D70: BAT_PRINCIPAL | E70: RDC | F70: M2 | G70: 39.6 | H70: 46084 | I70: PNR_MEDICAL_CENTER | J70: 5750 | L70: 1 | M70: 0
A71: BPU-MACON-ELEV-POUT-AC-032 | B71: Acier (Poteaux RDC) | C71: LOT 1 | D71: BAT_PRINCIPAL | E71: RDC | F71: KG | G71: 297.6 | H71: 46084 | I71: PNR_MEDICAL_CENTER | J71: 1380 | L71: 1 | M71: 0
A72: BPU-MACON-ELEV-CH-BET-350-033 | B72: Béton 350 (Poutres RDC) | C72: LOT 1 | D72: BAT_PRINCIPAL | E72: RDC | F72: M3 | G72: 3.72 | H72: 46084 | I72: PNR_MEDICAL_CENTER | J72: 189175 | L72: 1 | M72: 0
A73: BPU-MACON-ELEV-CH-COF-034 | B73: Coffrage (Poutres RDC) | C73: LOT 1 | D73: BAT_PRINCIPAL | E73: RDC | F73: M2 | G73: 46.46 | H73: 46084 | I73: PNR_MEDICAL_CENTER | J73: 5750 | L73: 1 | M73: 0
A74: BPU-MACON-ELEV-CH-AC-035 | B74: Acier (Poutres RDC) | C74: LOT 1 | D74: BAT_PRINCIPAL | E74: RDC | F74: KG | G74: 483.6 | H74: 46084 | I74: PNR_MEDICAL_CENTER | J74: 1380 | L74: 1 | M74: 0
A75: BPU-MACON-ELEV-LINT-BET-400-036 | B75: Béton 350 (Chainages RDC) | C75: LOT 1 | D75: BAT_PRINCIPAL | E75: RDC | F75: M3 | G75: 5.31 | H75: 46084 | I75: PNR_MEDICAL_CENTER | J75: 189175 | L75: 1 | M75: 0
A76: BPU-MACON-ELEV-LINT-COF-037 | B76: Coffrage (Chainages RDC) | C76: LOT 1 | D76: BAT_PRINCIPAL | E76: RDC | F76: M2 | G76: 79.63 | H76: 46084 | I76: PNR_MEDICAL_CENTER | J76: 5750 | L76: 1 | M76: 0
A77: BPU-MACON-ELEV-LINT-AC-038 | B77: Acier (Chainages RDC) | C77: LOT 1 | D77: BAT_PRINCIPAL | E77: RDC | F77: KG | G77: 1113.6 | H77: 46084 | I77: PNR_MEDICAL_CENTER | J77: 1380 | L77: 1 | M77: 0
A78: BPU-MACON-ELEV-ESC-BET-350-039 | B78: Béton 400 (Linteaux RDC) | C78: LOT 1 | D78: BAT_PRINCIPAL | E78: RDC | F78: M3 | G78: 4.74 | H78: 46084 | I78: PNR_MEDICAL_CENTER | J78: 189175 | L78: 1 | M78: 0
A79: BPU-MACON-ELEV-ESC-COF-040 | B79: Coffrage (Linteaux RDC) | C79: LOT 1 | D79: BAT_PRINCIPAL | E79: RDC | F79: M2 | G79: 71.1 | H79: 46084 | I79: PNR_MEDICAL_CENTER | J79: 5750 | L79: 1 | M79: 0
A80: BPU-MACON-ELEV-ESC-AC-041 | B80: Acier (Linteaux RDC) | C80: LOT 1 | D80: BAT_PRINCIPAL | E80: RDC | F80: KG | G80: 331.8 | H80: 46084 | I80: PNR_MEDICAL_CENTER | J80: 1380 | L80: 1 | M80: 0
... A102: BPU-ETANCH-LOC-RELEV-058 | B102: Relevé d'étanchéité h=50 cm | C102: LOT 2 | D102: BAT_ANNEXE | E102: ETAGE 1 | F102: ML | G102: 77.72 | H102: 46084 | I102: PNR_MEDICAL_CENTER | J102: 8641 | L102: 1 | M102: 0
A103: BPU-MEN-ALUM-BAIE-069 | B103: Baie vitrée en alu 220x527 | C103: LOT 4 | D103: BAT_PRINCIPAL | E103: RDC | F103: M2 | G103: 46.38 | H103: 46084 | I103: PNR_MEDICAL_CENTER | J103: 138000 | K103: 35075 | L103: 1 | M103: 1
A104: BPU-MEN-ALUM-BAIE-069 | B104: Baie vitrée en alu 220x242 | C104: LOT 4 | D104: BAT_PRINCIPAL | E104: RDC | F104: M2 | G104: 5.32 | H104: 46084 | I104: PNR_MEDICAL_CENTER | J104: 138000 | K104: 35075 | L104: 1 | M104: 1
A105: BPU-MEN-ALUM-BAIE-069 | B105: Baie vitrée en alu 120x200 | C105: LOT 4 | D105: BAT_PRINCIPAL | E105: RDC | F105: M2 | G105: 12 | H105: 46084 | I105: PNR_MEDICAL_CENTER | J105: 138000 | K105: 35075 | L105: 1 | M105: 1
A106: BPU-MEN-ALUM-BAIE-069 | B106: Baie vitrée en alu 120x140 | C106: LOT 4 | D106: BAT_PRINCIPAL | E106: RDC | F106: M2 | G106: 3.36 | H106: 46084 | I106: PNR_MEDICAL_CENTER | J106: 138000 | K106: 35075 | L106: 1 | M106: 1
A107: BPU-MEN-ALUM-BAIE-069 | B107: Baie vitrée en alu 120x160 | C107: LOT 4 | D107: BAT_PRINCIPAL | E107: RDC | F107: M2 | G107: 1.92 | H107: 46084 | I107: PNR_MEDICAL_CENTER | J107: 138000 | K107: 35075 | L107: 1 | M107: 1
A108: BPU-MEN-ALUM-BAIE-069 | B108: Baie vitrée en alu 100x120 | C108: LOT 4 | D108: BAT_PRINCIPAL | E108: RDC | F108: M2 | G108: 1.2 | H108: 46084 | I108: PNR_MEDICAL_CENTER | J108: 138000 | K108: 35075 | L108: 1 | M108: 1
A109: BPU-MEN-ALUM-BAIE-069 | B109: Baie vitrée en alu 60x60 | C109: LOT 4 | D109: BAT_PRINCIPAL | E109: RDC | F109: M2 | G109: 1.44 | H109: 46084 | I109: PNR_MEDICAL_CENTER | J109: 138000 | K109: 35075 | L109: 1 | M109: 1
A110: BPU-MEN-ALUM-BAIE-069 | B110: Baie vitrée en alu 220x245 | C110: LOT 4 | D110: BAT_PRINCIPAL | E110: RDC | F110: M2 | G110: 5.39 | H110: 46084 | I110: PNR_MEDICAL_CENTER | J110: 138000 | K110: 35075 | L110: 1 | M110: 1
A111: BPU-MEN-ALUM-BAIE-069 | B111: Baie vitrée en alu 220x150 | C111: LOT 4 | D111: BAT_PRINCIPAL | E111: RDC | F111: M2 | G111: 9.9 | H111: 46084 | I111: PNR_MEDICAL_CENTER | J111: 138000 | K111: 35075 | L111: 1 | M111: 1
A112: BPU-MEN-ALUM-BAIE-069 | B112: Baie vitrée en alu 220x120 | C112: LOT 4 | D112: BAT_PRINCIPAL | E112: RDC | F112: M2 | G112: 5.28 | H112: 46084 | I112: PNR_MEDICAL_CENTER | J112: 138000 | K112: 35075 | L112: 1 | M112: 1
A113: BPU-MEN-ALUM-BAIE-069 | B113: Baie vitrée en alu 220x90 | C113: LOT 4 | D113: BAT_PRINCIPAL | E113: RDC | F113: M2 | G113: 31.68 | H113: 46084 | I113: PNR_MEDICAL_CENTER | J113: 138000 | K113: 35075 | L113: 1 | M113: 1
A114: BPU-MEN-ALUM-BAIE-069 | B114: Baie vitrée en alu 220x80 | C114: LOT 4 | D114: BAT_PRINCIPAL | E114: RDC | F114: M2 | G114: 19.36 | H114: 46084 | I114: PNR_MEDICAL_CENTER | J114: 138000 | K114: 35075 | L114: 1 | M114: 1
... A214: BPU-CLIM-VRV-UI-GAINABLE-3CV-110 | B214: Unité intérieure 3CV type gainable encastrable de SAMSUNG et toutes sujétions de pose | C214: LOT 8 | D214: BAT_PRINCIPAL | E214: GLOBAL | F214: FORFAIT | G214: 12 | H214: 46084 | I214: PNR_MEDICAL_CENTER | J214: 575000 | K214: 152500 | L214: 1 | M214: 1
A215: BPU-CLIM-KIT-REFNET-111 | B215: Kit de raccordement REFNET de différentes dimensions suivant plans | C215: LOT 8 | D215: BAT_PRINCIPAL | E215: GLOBAL | F215: FORFAIT | G215: 1 | H215: 46084 | I215: PNR_MEDICAL_CENTER | J215: 690000 | L215: 1 | M215: 0
A216: BPU-CLIM-TELECOM-IR-112 | B216: Télécommande à infrarouge pour les unités intérieures | C216: LOT 8 | D216: BAT_PRINCIPAL | E216: GLOBAL | F216: FORFAIT | G216: 62 | H216: 46084 | I216: PNR_MEDICAL_CENTER | J216: 126500 | K216: 2745 | L216: 1 | M216: 1
A217: BPU-CLIM-RACC-FRIGO-113 | B217: Raccordements frigorifiques y compris toutes sujétions | C217: LOT 8 | D217: BAT_PRINCIPAL | E217: GLOBAL | F217: FORFAIT | G217: 1 | H217: 46084 | I217: PNR_MEDICAL_CENTER | J217: 1035000 | L217: 1 | M217: 0
A218: BPU-CLIM-RACC-ELEC-114 | B218: Raccordements électriques et liaisons de communication | C218: LOT 8 | D218: BAT_PRINCIPAL | E218: GLOBAL | F218: FORFAIT | G218: 1 | H218: 46084 | I218: PNR_MEDICAL_CENTER | J218: 1265000 | L218: 1 | M218: 0
A219: BPU-CLIM-EVAC-COND-115 | B219: Evacuation des condensats | C219: LOT 8 | D219: BAT_PRINCIPAL | E219: GLOBAL | F219: FORFAIT | G219: 1 | H219: 46084 | I219: PNR_MEDICAL_CENTER | J219: 1437500 | L219: 1 | M219: 0
A220: BPU-CLIM-GAINE-SOUF-REPR-116 | B220: Gaine de soufflage et de reprise en laine de verre ou en acier galva ou équivalent y compris toutes sujétions | C220: LOT 8 | D220: BAT_PRINCIPAL | E220: GLOBAL | F220: FORFAIT | G220: 1 | H220: 46084 | I220: PNR_MEDICAL_CENTER | J220: 13800000 | L220: 1 | M220: 0
...

Sheet RAW_BPU_CHINE
A1: CODE_BPU | B1: DESIGNATION | C1: LOT | D1: UNITE | E1: PU_CHINE_FOB | F1: TYPE_COUT | G1: SOURCE | H1: PROJET_ID | I1: FAM_ARTICLE_ID | J1: PU_IMPORT_NET | K1: DATE_VALIDATION | L1: STATUT
A2: BPU-INSTALL-GEN-MOB-001 | B2: Mobilisation | C2: LOT 1 | D2: Forfait | E2: 4755250 | F2: FORFAIT | G2: PU_CHINE_BPU_LOCAL_01_03 | H2: PNMC_2025 | J2: 4755250 | K2: 46084 | L2: VALIDE
A3: BPU-INSTALL-GEN-BASEVIE-002 | B3: Bureau de chantier, atelier, baraquement et clôture provisoire | C3: LOT 1 | D3: Forfait | E3: 3758730 | F3: FORFAIT | G3: PU_CHINE_BPU_LOCAL_01_03 | H3: PNMC_2025 | J3: 3758730 | K3: 46084 | L3: VALIDE
A4: BPU-INSTALL-GEN-CONC-003 | B4: Abonnement et mensualités concessionnaires | C4: LOT 1 | D4: Forfait | E4: 2507000 | F4: FORFAIT | G4: PU_CHINE_BPU_LOCAL_01_03 | H4: PNMC_2025 | J4: 2507000 | K4: 46084 | L4: VALIDE
A5: BPU-INSTALL-GEN-MAT-004 | B5: Matériel de chantier (engins, manutention) | C5: LOT 1 | D5: Forfait | E5: 4213438 | F5: MATERIAU | G5: PU_CHINE_BPU_LOCAL_01_03 | H5: PNMC_2025 | J5: 4213438 | K5: 46084 | L5: VALIDE
A6: BPU-INSTALL-GEN-DIVERS-005 | B6: Divers (sécurité, ASE, panneau de chantier) | C6: LOT 1 | D6: Forfait | E6: 4945000 | F6: MATERIAU | G6: PU_CHINE_BPU_LOCAL_01_03 | H6: PNMC_2025 | J6: 4945000 | K6: 46084 | L6: VALIDE
A7: BPU-INSTALL-GEN-ETUDE-006 | B7: Études techniques et Essais | C7: LOT 1 | D7: Forfait | E7: 4795500 | F7: MATERIAU | G7: PU_CHINE_BPU_LOCAL_01_03 | H7: PNMC_2025 | J7: 4795500 | K7: 46084 | L7: VALIDE
A8: BPU-INSTALL-GEN-AXE-007 | B8: Ensemble des axes nécessaires / piquetage | C8: LOT 1 | D8: Forfait | E8: 1265000 | F8: FORFAIT | G8: PU_CHINE_BPU_LOCAL_01_03 | H8: PNMC_2025 | J8: 1265000 | K8: 46084 | L8: VALIDE
A9: BPU-DEMO-MUR-ESC-RDC-008 | B9: Démolition murs et escalier (RDC) | C9: LOT 1 | D9: Forfait | E9: 1725000 | F9: MATERIAU | G9: PU_CHINE_BPU_LOCAL_01_03 | H9: PNMC_2025 | J9: 1725000 | K9: 46084 | L9: VALIDE
A10: BPU-DEMO-MUR-ESC-ET1-ANNEXE-009 | B10: Démolition murs, escalier et dalle existante (Bât. Annexe) | C10: LOT 1 | D10: Forfait | E10: 2587500 | F10: MATERIAU | G10: PU_CHINE_BPU_LOCAL_01_03 | H10: PNMC_2025 | J10: 2587500 | K10: 46084 | L10: VALIDE
A11: BPU-DEMO-MUR-ESC-ET2-010 | B11: Démolition murs et escalier (Étage 2) | C11: LOT 1 | D11: Forfait | E11: 1725000 | F11: MATERIAU | G11: PU_CHINE_BPU_LOCAL_01_03 | H11: PNMC_2025 | J11: 1725000 | K11: 46084 | L11: VALIDE
A12: BPU-DEMO-EVAC-GRAVAT-011 | B12: Évacuation des gravats hors site | C12: LOT 1 | D12: Forfait | E12: 552000 | F12: MATERIAU | G12: PU_CHINE_BPU_LOCAL_01_03 | H12: PNMC_2025 | J12: 552000 | K12: 46084 | L12: VALIDE
A13: BPU-MACON-FOND-BET-PROP-013 | B13: Béton de propreté | C13: LOT 1 | D13: m3 | E13: 338720 | F13: MATERIAU | G13: PU_CHINE_BPU_LOCAL_01_03 | H13: PNMC_2025 | J13: 338720 | K13: 46084 | L13: VALIDE
... A101: BPU-PEINT-PLAF-INT-PANTEX-188 | B101: Peinture intérieure plafond (primaire + 2 couches) | C101: LOT 14 | D101: m2 | E101: 6325 | F101: MATERIAU | G101: PU_CHINE_BPU_LOCAL_01_03 | H101: PNMC_2025 | J101: 6325 | K101: 46084 | L101: VALIDE

Sheet ---03_CLEAN---

Sheet CLEAN_METRE
A1: CODE_BPU | B1: DESIGNATION | C1: LOT | D1: BATIMENT_ID | E1: NIVEAU_ID | F1: UNITE | G1: QTE | H1: DATE_MAJ | I1: PROJET_ID
A2: BPU-INSTALL-GEN-MOB-001 | B2: Mobilisation | C2: LOT 1 | D2: BAT_PRINCIPAL | E2: GLOBAL | F2: FORFAIT | G2: 1 | H2: 46084 | I2: PNR_MEDICAL_CENTER
A3: BPU-INSTALL-GEN-BASEVIE-002 | B3: Bureau de chantier, atelier, baraquement et clôture provisoire | C3: LOT 1 | D3: BAT_PRINCIPAL | E3: GLOBAL | F3: FORFAIT | G3: 1 | H3: 46084 | I3: PNR_MEDICAL_CENTER
A4: BPU-INSTALL-GEN-CONC-003 | B4: Abonnement, mensualité concessionnaires | C4: LOT 1 | D4: BAT_PRINCIPAL | E4: GLOBAL | F4: FORFAIT | G4: 1 | H4: 46084 | I4: PNR_MEDICAL_CENTER
A5: BPU-INSTALL-GEN-MAT-004 | B5: Matériel de chantier (engins, manutention etc) | C5: LOT 1 | D5: BAT_PRINCIPAL | E5: GLOBAL | F5: FORFAIT | G5: 1 | H5: 46084 | I5: PNR_MEDICAL_CENTER
A6: BPU-INSTALL-GEN-DIVERS-005 | B6: Divers (sécurité, ASE, panneau de chantier...) | C6: LOT 1 | D6: BAT_PRINCIPAL | E6: GLOBAL | F6: FORFAIT | G6: 1 | H6: 46084 | I6: PNR_MEDICAL_CENTER
A7: BPU-INSTALL-GEN-ETUDE-006 | B7: Études techniques et Essais | C7: LOT 1 | D7: BAT_PRINCIPAL | E7: GLOBAL | F7: FORFAIT | G7: 1 | H7: 46084 | I7: PNR_MEDICAL_CENTER
A8: BPU-INSTALL-GEN-AXE-007 | B8: Ensemble des axes necessaires | C8: LOT 1 | D8: BAT_PRINCIPAL | E8: GLOBAL | F8: FORFAIT | G8: 1 | H8: 46084 | I8: PNR_MEDICAL_CENTER
A9: BPU-DEMO-MUR-ESC-RDC-008 | B9: Démolition des murs et l'escalier (RDC) | C9: LOT 1 | D9: BAT_PRINCIPAL | E9: RDC | F9: FORFAIT | G9: 1 | H9: 46084 | I9: PNR_MEDICAL_CENTER
A10: BPU-DEMO-MUR-ESC-ET1-ANNEXE-009 | B10: Démolition des murs et l'escalier y compris la dalle existente bâtiment annexe (ÉTAGE 1) | C10: LOT 1 | D10: BAT_ANNEXE | E10: ETAGE 1 | F10: FORFAIT | G10: 1 | H10: 46084 | I10: PNR_MEDICAL_CENTER
A11: BPU-DEMO-MUR-ESC-ET2-010 | B11: Démolition des murs et l'escalier (ÉTAGE 2) | C11: LOT 1 | D11: BAT_PRINCIPAL | E11: ETAGE 2 | F11: FORFAIT | G11: 1 | H11: 46084 | I11: PNR_MEDICAL_CENTER
A12: BPU-DEMO-EVAC-GRAVAT-011 | B12: Évacuation des gravats hors site | C12: LOT 1 | D12: BAT_PRINCIPAL | E12: GLOBAL | F12: FORFAIT | G12: 1 | H12: 46084 | I12: PNR_MEDICAL_CENTER
A13: BPU-DEMO-DECAP-CARREAU-012 | B13: Décapage des carreaux sol existants en RDC | C13: LOT 1 | D13: BAT_PRINCIPAL | E13: RDC | F13: M2 | G13: 460 | H13: 46084 | I13: PNR_MEDICAL_CENTER
... A302: BPU-PEINT-PLAF-INT-PANTEX-188 | B302: Peinture intérieure comprissant une impression en pantiprim, 02 couches d'enduits repassés et 02 couches de finitions en pante 800 | C302: LOT 14 | D302: BAT_PRINCIPAL | E302: DUPLEX 1 | F302: M2 | G302: 182 | H302: 46084 | I302: PNR_MEDICAL_CENTER

Sheet DIM_ARTICLE_BPU
A1: CODE_BPU | B1: DESIGNATION | C1: LOT | D1: FAM_ARTICLE_ID | E1: PU_LOCAL | F1: UNITE | G1: PU_CHINE_FOB | H1: PROJET_ID | I1: TYPE_ARTICLE | J1: PU_IMPORT_ESTIME | K1: IMPORTABLE | L1: CATEGORIE_IMPORT | M1: POIDS_KG | N1: VOLUME_M3 | O1: SENSIBILITE_TRANSPORT | P1: SOURCE_PRIX_LOCAL | Q1: SOURCE_PRIX_CHINE | R1: DATE_REFERENCE_PRIX | S1: ACTIF | T1: COMMENTAIRE
A2: BPU-ALUCOBOND-FP-184 | B2: F & P panneau composite de type Alucobond sur toute la façade extérieure | C2: LOT 13 | D2: FA_003 | E2: 174750 | F2: M2 | G2: 9760 | K2: 1 | S2: 1
A3: BPU-ASC-630KG-4ARR-183 | B3: Ascenseur de 630 kg, 4 arrêts, vitesse de 1 m/s etc | C3: LOT 12 | D3: FA_013 | E3: 25300000 | F3: FORFAIT | K3: 1 | S3: 1
A4: BPU-CDA-KIT-PORTE-141 | B4: kit contrôle d'accès porte | C4: LOT 9 | D4: FA_010 | E4: 230000 | F4: FORFAIT | G4: 33550 | K4: 1 | S4: 1
A5: BPU-CLIM-EVAC-COND-115 | B5: Evacuation des condensats | C5: LOT 8 | D5: FA_009 | E5: 1437500 | F5: FORFAIT | K5: 1 | S5: 1
A6: BPU-CLIM-GAINE-SOUF-REPR-116 | B6: Gaine de soufflage et de reprise en laine de verre ou en acier galva ou équivalent y compris toutes sujétions | C6: LOT 8 | D6: FA_009 | E6: 13800000 | F6: FORFAIT | K6: 1 | S6: 1
A7: BPU-CLIM-GRILLE-SOUF-REPR-1000X150-119 | B7: Grille de soufflage et de reprise type LAC 40 (à ailettes inclinées) de France Air ou similaire dimensions 1000x150 mm (pour les débits superieur ou égal à 870 m3/h) avec tous les accessoires de pose suivant plans | C7: LOT 8 | D7: FA_009 | E7: 138000 | F7: FORFAIT | G7: 7930 | K7: 1 | S7: 1
A8: BPU-CLIM-GRILLE-SOUF-REPR-600X150-117 | B8: Grille de soufflage et de reprise type LAC 40 (à ailettes inclinées) de France Air ou similaire dimensions 600x150 mm (pour les débits jusqu'à 660 m3/h) avec tous les accessoires de pose suivant plans | C8: LOT 8 | D8: FA_009 | E8: 80500 | F8: FORFAIT | G8: 4880 | K8: 1 | S8: 1
A9: BPU-CLIM-GRILLE-SOUF-REPR-800X150-118 | B9: Grille de soufflage et de reprise type LAC 40 (à ailettes inclinées) de France Air ou similaire dimensions 800x150 mm (pour les débits comprise entre 660 à 870 m3/h) avec tous les accessoires de pose suivant plans | C9: LOT 8 | D9: FA_009 | E9: 97750 | F9: FORFAIT | G9: 6405 | K9: 1 | S9: 1
A10: BPU-CLIM-KIT-REFNET-111 | B10: Kit de raccordement REFNET de différentes dimensions suivant plans | C10: LOT 8 | D10: FA_009 | E10: 690000 | F10: FORFAIT | K10: 1 | S10: 1
A11: BPU-CLIM-RACC-ELEC-114 | B11: Raccordements électriques et liaisons de communication | C11: LOT 8 | D11: FA_009 | E11: 1265000 | F11: FORFAIT | K11: 1 | S11: 1
A12: BPU-CLIM-RACC-FRIGO-113 | B12: Raccordements frigorifiques y compris toutes sujétions | C12: LOT 8 | D12: FA_009 | E12: 1035000 | F12: FORFAIT | K12: 1 | S12: 1
A13: BPU-CLIM-TELECOM-IR-112 | B13: Télécommande à infrarouge pour les unités intérieures | C13: LOT 8 | D13: FA_009 | E13: 126500 | F13: FORFAIT | G13: 2745 | K13: 1 | S13: 1
A14: BPU-CLIM-VRV-UE-107 | B14: Unité Extérieure Multi-Split Réversible Samsung - Climatisation Multi Split - R32 y compris toutes les sujétions de pose et de raccordement | C14: LOT 8 | D14: FA_009 | E14: 2300000 | F14: FORFAIT | G14: 457500 | K14: 1 | S14: 1
A15: BPU-CLIM-VRV-UI-GAINABLE-1.5CV-108 | B15: Unité intérieure 1.5CV type gainable encastrable de SAMSUNG et toutes sujétions de pose | C15: LOT 8 | D15: FA_009 | E15: 345000 | F15: FORFAIT | G15: 91500 | K15: 1 | S15: 1
A16: BPU-CLIM-VRV-UI-GAINABLE-2CV-109 | B16: Unité intérieure 2CV type gainable encastrable de SAMSUNG et toutes sujétions de pose | C16: LOT 8 | D16: FA_009 | E16: 460000 | F16: FORFAIT | G16: 118950 | K16: 1 | S16: 1
A17: BPU-CLIM-VRV-UI-GAINABLE-3CV-110 | B17: Unité intérieure 3CV type gainable encastrable de SAMSUNG et toutes sujétions de pose | C17: LOT 8 | D17: FA_009 | E17: 575000 | F17: FORFAIT | G17: 152500 | K17: 1 | S17: 1
A18: BPU-DEMO-DECAP-CARREAU-012 | B18: Décapage des carreaux sol existants en RDC | C18: LOT 1 | D18: FA_001 | E18: 5750 | F18: M2 | K18: 1 | S18: 1
A19: BPU-DEMO-EVAC-GRAVAT-011 | B19: Évacuation des gravats hors site | C19: LOT 1 | D19: FA_001 | E19: 552000 | F19: FORFAIT | G19: 552000 | K19: 1 | S19: 1
A20: BPU-DEMO-MUR-ESC-ET1-ANNEXE-009 | B20: Démolition des murs et l'escalier y compris la dalle existente bâtiment annexe (ÉTAGE 1) | C20: LOT 1 | D20: FA_001 | E20: 2587500 | F20: FORFAIT | G20: 2587500 | K20: 1 | S20: 1
A21: BPU-DEMO-MUR-ESC-ET2-010 | B21: Démolition des murs et l'escalier (ÉTAGE 2) | C21: LOT 1 | D21: FA_001 | E21: 1725000 | F21: FORFAIT | G21: 1725000 | K21: 1 | S21: 1
A22: BPU-DEMO-MUR-ESC-RDC-008 | B22: Démolition des murs et l'escalier (RDC) | C22: LOT 1 | D22: FA_001 | E22: 1725000 | F22: FORFAIT | G22: 1725000 | K22: 1 | S22: 1
A23: BPU-ELEC-APPLIQUE-MURALE-088 | B23: Applique mural | C23: LOT 7 | D23: FA_008 | E23: 13800 | F23: FORFAIT | G23: 3355 | K23: 1 | S23: 1
A24: BPU-ELEC-APPLIQUE-MURALE-ETANCHE-089 | B24: Applique mural étanche | C24: LOT 7 | D24: FA_008 | E24: 20700 | F24: FORFAIT | G24: 4880 | K24: 1 | S24: 1
A25: BPU-ELEC-APPLIQUE-SANITAIRE-087 | B25: Applique sanitaire PC+Int | C25: LOT 7 | D25: FA_008 | E25: 10350 | F25: FORFAIT | G25: 2440 | K25: 1 | S25: 1
A26: BPU-ELEC-BAES-AMBIANCE-094 | B26: Bloc autonome d'éclairage de sécurité étanche type à incandescence autonomie 1h de LEGRAND ou similaire : Ambiance | C26: LOT 7 | D26: FA_008 | E26: 67275 | F26: FORFAIT | G26: 14030 | K26: 1 | S26: 1
A27: BPU-ELEC-BAES-DIRECTION-095 | B27: Bloc autonome d'éclairage de sécurité étanche type à incandescence autonomie 1h de LEGRAND ou similaire : Direction | C27: LOT 7 | D27: FA_008 | E27: 43125 | F27: FORFAIT | G27: 9760 | K27: 1 | S27: 1
A28: BPU-ELEC-BP-TEMOIN-098 | B28: Bouton poussoire avec témoin | C28: LOT 7 | D28: FA_008 | E28: 10350 | F28: FORFAIT | G28: 855 | K28: 1 | S28: 1
A29: BPU-ELEC-DALLE-LED-40W-083 | B29: Dalle led 60x60 40W | C29: LOT 7 | D29: FA_008 | E29: 40250 | F29: FORFAIT | G29: 7320 | K29: 1 | S29: 1
A30: BPU-ELEC-DETECT-PRES-099 | B30: Détecteur de presence | C30: LOT 7 | D30: FA_008 | E30: 46000 | F30: FORFAIT | G30: 4270 | K30: 1 | S30: 1
... A46: BPU-ELEC-SPOT-LED-22W-092 | B46: Spot led 22w | C46: LOT 7 | D46: FA_008 | E46: 20700 | F46: FORFAIT | G46: 3050 | K46: 1 | S46: 1
A47: BPU-ETANCH-LOC-RELEV-058 | B47: Relevé d'étanchéité h=50 cm | C47: LOT 2 | D47: FA_002 | E47: 8641 | F47: ML | K47: 1 | S47: 1
A48: BPU-ETANCH-LOC-REV-MONO-057 | B48: Revêtement monocouche | C48: LOT 2 | D48: FA_002 | E48: 17276 | F48: M2 | K48: 1 | S48: 1
A49: BPU-ETANCH-TERR-ACC-BI-060 | B49: Revêtement bicouche sous protection lourde | C49: LOT 2 | D49: FA_002 | E49: 34552 | F49: M2 | G49: 6100 | K49: 1 | S49: 1
A50: BPU-ETANCH-TERR-ACC-FORME-059 | B50: Forme de pente | C50: LOT 2 | D50: FA_002 | E50: 11793 | F50: M2 | G50: 11793 | K50: 1 | S50: 1
A51: BPU-ETANCH-TERR-ACC-RELEV-061 | B51: Relevé d'étanchéité h=50 cm | C51: LOT 2 | D51: FA_002 | E51: 8641 | F51: ML | G51: 3050 | K51: 1 | S51: 1
A52: BPU-ETANCH-TERR-INACC-FORME-062 | B52: Forme de pente | C52: LOT 2 | D52: FA_002 | E52: 11793 | F52: M2 | G52: 11793 | K52: 1 | S52: 1
A53: BPU-ETANCH-TERR-INACC-MONO-063 | B53: Revêtement monocouche sous protection lourde | C53: LOT 2 | D53: FA_002 | E53: 17276 | F53: M2 | G53: 4575 | K53: 1 | S53: 1
A54: BPU-ETANCH-TERR-INACC-RELEV-064 | B54: Relevé d'étanchéité h=50 cm | C54: LOT 2 | D54: FA_002 | E54: 8641 | F54: ML | G54: 3050 | K54: 1 | S54: 1
A55: BPU-FP-CLOISON-BA13-LV-180 | B55: Cloison en BA 13 avec laine de verre | C55: LOT 11 | D55: FA_012 | E55: 39100 | F55: M2 | K55: 1 | S55: 1
A56: BPU-FP-CORNICHE-182 | B56: Corniche décorative | C56: LOT 11 | D56: FA_012 | E56: 5750 | F56: ML | K56: 1 | S56: 1
A57: BPU-FP-FP-ISORELLE-179 | B57: Faux plafonds en plaquette d'isorelle ou | C57: LOT 11 | D57: FA_012 | E57: 26450 | F57: M2 | K57: 1 | S57: 1
A58: BPU-FP-STAFF-LISSE-181 | B58: Faux plafonds en staff lisse décorative | C58: LOT 11 | D58: FA_012 | E58: 23000 | F58: M2 | K58: 1 | S58: 1
A59: BPU-INSTALL-GEN-AXE-007 | B59: Ensemble des axes necessaires | C59: LOT 1 | D59: FA_001 | E59: 1265000 | F59: FORFAIT | G59: 1265000 | K59: 1 | S59: 1
A60: BPU-INSTALL-GEN-BASEVIE-002 | B60: Bureau de chantier, atelier, baraquement et clôture provisoire | C60: LOT 1 | D60: FA_001 | E60: 3758730 | F60: FORFAIT | G60: 3758730 | K60: 1 | S60: 1
A61: BPU-INSTALL-GEN-CONC-003 | B61: Abonnement, mensualité concessionnaires | C61: LOT 1 | D61: FA_001 | E61: 2507000 | F61: FORFAIT | G61: 2507000 | K61: 1 | S61: 1
A62: BPU-INSTALL-GEN-DIVERS-005 | B62: Divers (sécurité, ASE, panneau de chantier...) | C62: LOT 1 | D62: FA_001 | E62: 4945000 | F62: FORFAIT | G62: 4945000 | K62: 1 | S62: 1
A63: BPU-INSTALL-GEN-ETUDE-006 | B63: Études techniques et Essais | C63: LOT 1 | D63: FA_001 | E63: 4795500 | F63: FORFAIT | G63: 4795500 | K63: 1 | S63: 1
A64: BPU-INSTALL-GEN-MAT-004 | B64: Matériel de chantier (engins, manutention etc) | C64: LOT 1 | D64: FA_001 | E64: 4213438 | F64: FORFAIT | G64: 4213438 | K64: 1 | S64: 1
A65: BPU-INSTALL-GEN-MOB-001 | B65: Mobilisation | C65: LOT 1 | D65: FA_001 | E65: 4755250 | F65: FORFAIT | G65: 4755250 | K65: 1 | S65: 1
A66: BPU-MACON-AGGL-CREUX-20-046 | B66: Agglos creux 20x20x50 | C66: LOT 1 | D66: FA_001 | E66: 11185 | F66: M2 | G66: 11185 | K66: 1 | S66: 1
A67: BPU-MACON-ELEV-CH-AC-035 | B67: Acier | C67: LOT 1 | D67: FA_001 | E67: 1380 | F67: KG | K67: 1 | S67: 1
A68: BPU-MACON-ELEV-CH-BET-350-033 | B68: Béton 350 | C68: LOT 1 | D68: FA_001 | E68: 189175 | F68: M3 | K68: 1 | S68: 1
A69: BPU-MACON-ELEV-CH-COF-034 | B69: Coffrage | C69: LOT 1 | D69: FA_001 | E69: 5750 | F69: M2 | K69: 1 | S69: 1
A70: BPU-MACON-ELEV-DALL-AC-025 | B70: Acier | C70: LOT 1 | D70: FA_001 | E70: 1380 | F70: KG | K70: 1 | S70: 1
A71: BPU-MACON-ELEV-DALL-BET-023 | B71: Béton | C71: LOT 1 | D71: FA_001 | E71: 189175 | F71: M3 | K71: 1 | S71: 1
A72: BPU-MACON-ELEV-DALL-COF-024 | B72: Coffrage | C72: LOT 1 | D72: FA_001 | E72: 5750 | F72: M2 | K72: 1 | S72: 1
A73: BPU-MACON-ELEV-ESC-AC-041 | B73: Acier | C73: LOT 1 | D73: FA_001 | E73: 1380 | F73: KG | K73: 1 | S73: 1
A74: BPU-MACON-ELEV-ESC-BET-350-039 | B74: Béton 350 | C74: LOT 1 | D74: FA_001 | E74: 189175 | F74: M3 | K74: 1 | S74: 1
A75: BPU-MACON-ELEV-ESC-COF-040 | B75: Coffrage | C75: LOT 1 | D75: FA_001 | E75: 5750 | F75: M2 | K75: 1 | S75: 1
A76: BPU-MACON-ELEV-LINT-AC-038 | B76: Acier | C76: LOT 1 | D76: FA_001 | E76: 1380 | F76: KG | K76: 1 | S76: 1
A77: BPU-MACON-ELEV-LINT-BET-400-036 | B77: Béton 400 | C77: LOT 1 | D77: FA_001 | E77: 189175 | F77: M3 | K77: 1 | S77: 1
A78: BPU-MACON-ELEV-LINT-COF-037 | B78: Coffrage | C78: LOT 1 | D78: FA_001 | E78: 5750 | F78: M2 | K78: 1 | S78: 1
... A97: BPU-MACON-ELEV-VOILE-COF-054 | B97: Coffrage | C97: LOT 1 | D97: FA_001 | E97: 5750 | F97: M2 | K97: 1 | S97: 1
A98: BPU-MACON-END-INT-EXT-047 | B98: Enduits intérieurs et extérieurs sur murs | C98: LOT 1 | D98: FA_001 | E98: 3827 | F98: M2 | G98: 3827 | K98: 1 | S98: 1
A99: BPU-MACON-END-SOUS-PLF-048 | B99: Enduits sous plafond | C99: LOT 1 | D99: FA_001 | E99: 3827 | F99: M2 | G99: 3827 | K99: 1 | S99: 1
A100: BPU-MACON-FIN-TABL-056 | B100: Finition des tableaux | C100: LOT 1 | D100: FA_001 | E100: 2344172 | F100: FORFAIT | K100: 1 | S100: 1
A101: BPU-MACON-FOND-AC-016 | B101: Acier | C101: LOT 1 | D101: FA_001 | E101: 1380 | F101: KG | G101: 370 | K101: 1 | S101: 1
A102: BPU-MACON-FOND-BET-400-014 | B102: Béton 400 hydr | C102: LOT 1 | D102: FA_001 | E102: 189175 | F102: M3 | G102: 189175 | K102: 1 | S102: 1
A103: BPU-MACON-FOND-BET-PROP-013 | B103: Béton de propreté | C103: LOT 1 | D103: FA_001 | E103: 338720 | F103: M3 | G103: 338720 | K103: 1 | S103: 1
A104: BPU-MACON-FOND-COF-015 | B104: Coffrage | C104: LOT 1 | D104: FA_001 | E104: 5750 | F104: M2 | G104: 3350 | K104: 1 | S104: 1
A105: BPU-MACON-MARCH-BET-350-051 | B105: Béton 350 | C105: LOT 1 | D105: FA_001 | E105: 189175 | F105: M3 | K105: 1 | S105: 1
A106: BPU-MACON-MARCH-COF-052 | B106: Coffrage | C106: LOT 1 | D106: FA_001 | E106: 5750 | F106: M2 | K106: 1 | S106: 1
A107: BPU-MACON-RESERV-CALF-049 | B107: Réservations et calfeutrements divers | C107: LOT 1 | D107: FA_001 | E107: 1 | F107: FORFAIT | K107: 1 | S107: 1
A108: BPU-MACON-SCELL-RACC-050 | B108: Scellements et raccordements | C108: LOT 1 | D108: FA_001 | E108: 1 | F108: FORFAIT | K108: 1 | S108: 1
A109: BPU-MACON-SSO-AGGL-PLEIN-026 | B109: Agglos pleins 20x20x50 | C109: LOT 1 | D109: FA_001 | E109: 12180 | F109: M2 | G109: 12180 | K109: 1 | S109: 1
A110: BPU-MEN-ALUM-BAIE-069 | B110: Baie vitrée en alu (dimensions variables) | C110: LOT 4 | D110: FA_005 | E110: 138000 | F110: M2 | G110: 35075 | K110: 1 | S110: 1
A111: BPU-MEN-ALUM-GARDE-CORPS-070 | B111: Garde corps en alu | C111: LOT 4 | D111: FA_005 | E111: 138000 | F111: M2 | G111: 25925 | K111: 1 | S111: 1
A112: BPU-MEN-BOIS-ETAGERE-CUISINE-INF-080 | B112: Étagère inférieure de la cuisine | C112: LOT 6 | D112: FA_005 | E112: 402500 | F112: ML | G112: 47275 | K112: 1 | S112: 1
A113: BPU-MEN-BOIS-ETAGERE-CUISINE-SUP-079 | B113: Étagère supérieure de la cuisine | C113: LOT 6 | D113: FA_005 | E113: 345000 | F113: ML | G113: 41175 | K113: 1 | S113: 1
A114: BPU-MEN-BOIS-ETAGERE-VAIS-INF-082 | B114: Étagère inférieure de la vaissellerie | C114: LOT 6 | D114: FA_005 | E114: 402500 | F114: ML | G114: 47275 | K114: 1 | S114: 1
A115: BPU-MEN-BOIS-ETAGERE-VAIS-SUP-081 | B115: Étagère supérieure de la vaissellerie | C115: LOT 6 | D115: FA_005 | E115: 402500 | F115: ML | G115: 47275 | K115: 1 | S115: 1
A116: BPU-MEN-BOIS-PLACARD-077 | B116: Placard (dimensions variables) ouvrant à la française | C116: LOT 6 | D116: FA_005 | E116: 759000 | F116: FORFAIT | G116: 152500 | K116: 1 | S116: 1
A117: BPU-MEN-BOIS-PORTE-MDF-078 | B117: Porte MDF 90x220 ouvrant à la française | C117: LOT 6 | D117: FA_005 | E117: 341550 | F117: FORFAIT | G117: 35075 | K117: 1 | S117: 1
A118: BPU-MEN-METAL-ESCALIER-LABO-074 | B118: Escalier métallique du laboratoire y compris habillage des marches en bois | C118: LOT 5 | D118: FA_005 | E118: 1092500 | F118: FORFAIT | G118: 366000 | K118: 1 | S118: 1
A119: BPU-MEN-METAL-GARDE-CORPS-075 | B119: Garde corps métallique pour la mezzanine | C119: LOT 5 | D119: FA_005 | E119: 97750 | F119: M2 | G119: 22875 | K119: 1 | S119: 1
A120: BPU-MEN-METAL-GRILLAGE-MEZZ-076 | B120: Grillage de protection de la mezzanine | C120: LOT 5 | D120: FA_005 | E120: 97750 | F120: M2 | G120: 12200 | K120: 1 | S120: 1
... A127: BPU-PEINT-PLAF-PREP-SURF-187 | B127: Préparation de surface | C127: LOT 14 | D127: FA_014 | E127: 575 | F127: M2 | G127: 575 | K127: 1 | S127: 1
A128: BPU-PLOMB-BOUCHE-EXTR-ALIZE-01-174 | B128: Bouche d'extraction de type Alizé | C128: LOT 10 | D128: FA_011 | E128: 26450 | F128: FORFAIT | K128: 1 | S128: 1
A129: BPU-PLOMB-BOUCHE-EXTR-ALIZE-02-175 | B129: Bouche d'extraction de type Alizé | C129: LOT 10 | D129: FA_011 | E129: 28750 | F129: FORFAIT | K129: 1 | S129: 1
A130: BPU-PLOMB-CANAL-ALIM-PVC-D25-161 | B130: Canalisation alimentation en PVC D25 | C130: LOT 10 | D130: FA_011 | E130: 4255 | F130: ML | K130: 1 | S130: 1
A131: BPU-PLOMB-CANAL-ALIM-PVC-D32-160 | B131: Canalisation alimentation en PVC D32 | C131: LOT 10 | D131: FA_011 | E131: 4830 | F131: ML | K131: 1 | S131: 1
A132: BPU-PLOMB-CANAL-ALIM-PVC-D40-159 | B132: Canalisation alimentation en PVC D40 | C132: LOT 10 | D132: FA_011 | E132: 5405 | F132: ML | K132: 1 | S132: 1
A133: BPU-PLOMB-CANAL-ALIM-PVC-D75-158 | B133: Canalisation alimentation en PVC D75 | C133: LOT 10 | D133: FA_011 | E133: 5980 | F133: ML | K133: 1 | S133: 1
A134: BPU-PLOMB-CANAL-DIST-PER-13X16-162 | B134: Canalisation alimentation en PER 13x16 | C134: LOT 10 | D134: FA_011 | E134: 3450 | F134: ML | K134: 1 | S134: 1
A135: BPU-PLOMB-CANAL-DIST-PER-16X20-163 | B135: Canalisation alimentation en PER 16x20 | C135: LOT 10 | D135: FA_011 | E135: 4255 | F135: ML | K135: 1 | S135: 1
A136: BPU-PLOMB-CANAL-DIST-PER-20X25-164 | B136: Canalisation alimentation en PER 20x25 | C136: LOT 10 | D136: FA_011 | E136: 4830 | F136: ML | K136: 1 | S136: 1
A137: BPU-PLOMB-CANAL-DIST-PER-26X32-165 | B137: Canalisation alimentation en PER 26x32 | C137: LOT 10 | D137: FA_011 | E137: 7475 | F137: ML | K137: 1 | S137: 1
A138: BPU-PLOMB-CANAL-EU-PVC-D110-154 | B138: Canalisation évacuation en PVC D110 | C138: LOT 10 | D138: FA_011 | E138: 11224 | F138: ML | K138: 1 | S138: 1
A139: BPU-PLOMB-CANAL-EU-PVC-D125-155 | B139: Canalisation évacuation en PVC D125 | C139: LOT 10 | D139: FA_011 | E139: 13915 | F139: ML | K139: 1 | S139: 1
...

Sheet CLEAN_BPU_LOCAL
A1: CODE_BPU | B1: DESIGNATION | C1: LOT | D1: UNITE | E1: PU_LOCAL | F1: DATE_REFERENCE | G1: SOURCE | H1: PROJET_ID | I1: TYPE_COUT | J1: ACTIF | K1: FAM_ARTICLE_ID
A2: BPU-INSTALL-GEN-MOB-001 | B2: Mobilisation | C2: LOT 1 | D2: FORFAIT | E2: 4755250 | F2: 45882 | G2: DQE_MEDICAL CENTER_13-08-2025 | H2: PNMC_2025 | I2: MATERIAU | J2: 1 | K2: FA_001
A3: BPU-INSTALL-GEN-BASEVIE-002 | B3: Bureau de chantier, atelier, baraquement et clôture provisoire | C3: LOT 1 | D3: FORFAIT | E3: 3758730 | F3: 45882 | G3: DQE_MEDICAL CENTER_13-08-2025 | H3: PNMC_2025 | I3: MATERIAU | J3: 1 | K3: FA_001
A4: BPU-INSTALL-GEN-CONC-003 | B4: Abonnement, mensualité concessionnaires | C4: LOT 1 | D4: FORFAIT | E4: 2507000 | F4: 45882 | G4: DQE_MEDICAL CENTER_13-08-2025 | H4: PNMC_2025 | I4: MATERIAU | J4: 1 | K4: FA_001
A5: BPU-INSTALL-GEN-MAT-004 | B5: Matériel de chantier (engins, manutention etc) | C5: LOT 1 | D5: FORFAIT | E5: 4213438 | F5: 45882 | G5: DQE_MEDICAL CENTER_13-08-2025 | H5: PNMC_2025 | I5: MATERIAU | J5: 1 | K5: FA_001
A6: BPU-INSTALL-GEN-DIVERS-005 | B6: Divers (sécurité, ASE, panneau de chantier...) | C6: LOT 1 | D6: FORFAIT | E6: 4945000 | F6: 45882 | G6: DQE_MEDICAL CENTER_13-08-2025 | H6: PNMC_2025 | I6: MATERIAU | J6: 1 | K6: FA_001
A7: BPU-INSTALL-GEN-ETUDE-006 | B7: Études techniques et Essais | C7: LOT 1 | D7: FORFAIT | E7: 4795500 | F7: 45882 | G7: DQE_MEDICAL CENTER_13-08-2025 | H7: PNMC_2025 | I7: MATERIAU | J7: 1 | K7: FA_001
A8: BPU-INSTALL-GEN-AXE-007 | B8: Ensemble des axes necessaires | C8: LOT 1 | D8: FORFAIT | E8: 1265000 | F8: 45882 | G8: DQE_MEDICAL CENTER_13-08-2025 | H8: PNMC_2025 | I8: MATERIAU | J8: 1 | K8: FA_001
A9: BPU-DEMO-MUR-ESC-RDC-008 | B9: Démolition des murs et l'escalier (RDC) | C9: LOT 1 | D9: FORFAIT | E9: 1725000 | F9: 45882 | G9: DQE_MEDICAL CENTER_13-08-2025 | H9: PNMC_2025 | I9: MATERIAU | J9: 1 | K9: FA_001
A10: BPU-DEMO-MUR-ESC-ET1-ANNEXE-009 | B10: Démolition des murs et l'escalier y compris la dalle existente bâtiment annexe (ÉTAGE 1) | C10: LOT 1 | D10: FORFAIT | E10: 2587500 | F10: 45882 | G10: DQE_MEDICAL CENTER_13-08-2025 | H10: PNMC_2025 | I10: MATERIAU | J10: 1 | K10: FA_001
A11: BPU-DEMO-MUR-ESC-ET2-010 | B11: Démolition des murs et l'escalier (ÉTAGE 2) | C11: LOT 1 | D11: FORFAIT | E11: 1725000 | F11: 45882 | G11: DQE_MEDICAL CENTER_13-08-2025 | H11: PNMC_2025 | I11: MATERIAU | J11: 1 | K11: FA_001
A12: BPU-DEMO-EVAC-GRAVAT-011 | B12: Évacuation des gravats hors site | C12: LOT 1 | D12: FORFAIT | E12: 552000 | F12: 45882 | G12: DQE_MEDICAL CENTER_13-08-2025 | H12: PNMC_2025 | I12: MATERIAU | J12: 1 | K12: FA_001
A13: BPU-DEMO-DECAP-CARREAU-012 | B13: Décapage des carreaux sol existants en RDC | C13: LOT 1 | D13: M2 | E13: 5750 | F13: 45882 | G13: DQE_MEDICAL CENTER_13-08-2025 | H13: PNMC_2025 | I13: MATERIAU | J13: 1 | K13: FA_001
... A189: BPU-PEINT-PLAF-INT-PANTEX-188 | B189: Peinture intérieure comprissant une impression en pantiprim, 02 couches d'enduits repassés et 02 couches de finitions en pante 800 | C189: LOT 14 | D189: M2 | E189: 6325 | F189: 45882 | G189: DQE_MEDICAL CENTER_13-08-2025 | H189: PNMC_2025 | I189: MATERIAU | J189: 1 | K189: FA_014

Sheet CLEAN_BPU_CHINE
A1: CODE_BPU | B1: DESIGNATION | C1: LOT | D1: UNITE | E1: PU_CHINE_FOB | F1: TYPE_COUT | G1: SOURCE | H1: PROJET_ID | I1: FAM_ARTICLE_ID | J1: PU_IMPORT_NET | K1: DATE_VALIDATION | L1: STATUT
A2: BPU-INSTALL-GEN-MOB-001 | B2: Mobilisation | C2: LOT 1 | D2: FORFAIT | E2: 4755250 | F2: FORFAIT | G2: PU_CHINE_BPU_LOCAL_01_03 | H2: PNMC_2025 | J2: 4755250 | K2: 46084 | L2: VALIDE
A3: BPU-INSTALL-GEN-BASEVIE-002 | B3: Bureau de chantier, atelier, baraquement et clôture provisoire | C3: LOT 1 | D3: FORFAIT | E3: 3758730 | F3: FORFAIT | G3: PU_CHINE_BPU_LOCAL_01_03 | H3: PNMC_2025 | J3: 3758730 | K3: 46084 | L3: VALIDE
A4: BPU-INSTALL-GEN-CONC-003 | B4: Abonnement et mensualités concessionnaires | C4: LOT 1 | D4: FORFAIT | E4: 2507000 | F4: FORFAIT | G4: PU_CHINE_BPU_LOCAL_01_03 | H4: PNMC_2025 | J4: 2507000 | K4: 46084 | L4: VALIDE
A5: BPU-INSTALL-GEN-MAT-004 | B5: Matériel de chantier (engins, manutention) | C5: LOT 1 | D5: FORFAIT | E5: 4213438 | F5: MATERIAU | G5: PU_CHINE_BPU_LOCAL_01_03 | H5: PNMC_2025 | J5: 4213438 | K5: 46084 | L5: VALIDE
A6: BPU-INSTALL-GEN-DIVERS-005 | B6: Divers (sécurité, ASE, panneau de chantier) | C6: LOT 1 | D6: FORFAIT | E6: 4945000 | F6: MATERIAU | G6: PU_CHINE_BPU_LOCAL_01_03 | H6: PNMC_2025 | J6: 4945000 | K6: 46084 | L6: VALIDE
A7: BPU-INSTALL-GEN-ETUDE-006 | B7: Études techniques et Essais | C7: LOT 1 | D7: FORFAIT | E7: 4795500 | F7: MATERIAU | G7: PU_CHINE_BPU_LOCAL_01_03 | H7: PNMC_2025 | J7: 4795500 | K7: 46084 | L7: VALIDE
A8: BPU-INSTALL-GEN-AXE-007 | B8: Ensemble des axes nécessaires / piquetage | C8: LOT 1 | D8: FORFAIT | E8: 1265000 | F8: FORFAIT | G8: PU_CHINE_BPU_LOCAL_01_03 | H8: PNMC_2025 | J8: 1265000 | K8: 46084 | L8: VALIDE
A9: BPU-DEMO-MUR-ESC-RDC-008 | B9: Démolition murs et escalier (RDC) | C9: LOT 1 | D9: FORFAIT | E9: 1725000 | F9: MATERIAU | G9: PU_CHINE_BPU_LOCAL_01_03 | H9: PNMC_2025 | J9: 1725000 | K9: 46084 | L9: VALIDE
A10: BPU-DEMO-MUR-ESC-ET1-ANNEXE-009 | B10: Démolition murs, escalier et dalle existante (Bât. Annexe) | C10: LOT 1 | D10: FORFAIT | E10: 2587500 | F10: MATERIAU | G10: PU_CHINE_BPU_LOCAL_01_03 | H10: PNMC_2025 | J10: 2587500 | K10: 46084 | L10: VALIDE
A11: BPU-DEMO-MUR-ESC-ET2-010 | B11: Démolition murs et escalier (Étage 2) | C11: LOT 1 | D11: FORFAIT | E11: 1725000 | F11: MATERIAU | G11: PU_CHINE_BPU_LOCAL_01_03 | H11: PNMC_2025 | J11: 1725000 | K11: 46084 | L11: VALIDE
A12: BPU-DEMO-EVAC-GRAVAT-011 | B12: Évacuation des gravats hors site | C12: LOT 1 | D12: FORFAIT | E12: 552000 | F12: MATERIAU | G12: PU_CHINE_BPU_LOCAL_01_03 | H12: PNMC_2025 | J12: 552000 | K12: 46084 | L12: VALIDE
A13: BPU-MACON-FOND-BET-PROP-013 | B13: Béton de propreté | C13: LOT 1 | D13: M3 | E13: 338720 | F13: MATERIAU | G13: PU_CHINE_BPU_LOCAL_01_03 | H13: PNMC_2025 | J13: 338720 | K13: 46084 | L13: VALIDE
... A101: BPU-PEINT-PLAF-INT-PANTEX-188 | B101: Peinture intérieure plafond (primaire + 2 couches) | C101: LOT 14 | D101: M2 | E101: 6325 | F101: MATERIAU | G101: PU_CHINE_BPU_LOCAL_01_03 | H101: PNMC_2025 | J101: 6325 | K101: 46084 | L101: VALIDE

Sheet ---04_STAGING---

Sheet STAGING
A1: CODE_BPU | B1: DESIGNATION | C1: BATIMENT_ID | D1: NIVEAU_ID | E1: UNITE | F1: QTE | G1: DATE_MAJ | H1: PROJET_ID | I1: FAM_ARTICLE_ID | J1: PU_LOCAL | K1: TYPE_COUT | L1: PU_CHINE_FOB | M1: IMPORTABLE | N1: RISQUE_IMPORT | O1: PU_CHINE_FOB_E | P1: STATUT_PRIX | Q1: PU_IMPORT_NET | R1: PU_LOCAL_MARGE | S1: MONTANT_LOCAL | T1: MONTANT_IMPORT | U1: ECONOMIE_NETTE | V1: TAUX_ECONOMIE | W1: DECISION | X1: LOT_ID | Y1: SCORE_STRATEGIQUE
A2: BPU-INSTALL-GEN-MOB-001 | B2: Mobilisation | C2: BAT_PRINCIPAL | D2: GLOBAL | E2: FORFAIT | F2: 1 | G2: 46084 | H2: PNR_MEDICAL_CENTER | I2: FA_001 | J2: 4755250 | K2: MATERIAU | L2: 4755250 | M2: 0 | N2: 0 | O2: 4755250 | P2: PRIX_OK | Q2: 7472399.9 | R2: 5468537.5 | S2: 5468537.5 | T2: 7472399.9 | U2: -2003862.4 | V2: -0.36643478 | W2: LOCAL | X2: 1 | Y2: 0.08013913
A3: BPU-INSTALL-GEN-BASEVIE-002 | B3: Bureau de chantier, atelier, baraquement et clôture provisoire | C3: BAT_PRINCIPAL | D3: GLOBAL | E3: FORFAIT | F3: 1 | G3: 46084 | H3: PNR_MEDICAL_CENTER | I3: FA_001 | J3: 3758730 | K3: MATERIAU | L3: 3758730 | M3: 0 | N3: 0 | O3: 3758730 | P3: PRIX_OK | Q3: 5906468.3 | R3: 4322539.5 | S3: 4322539.5 | T3: 5906468.3 | U3: -1583928.8 | V3: -0.36643478 | W3: LOCAL | X3: 1 | Y3: 0.08013913
A4: BPU-INSTALL-GEN-CONC-003 | B4: Abonnement, mensualité concessionnaires | C4: BAT_PRINCIPAL | D4: GLOBAL | E4: FORFAIT | F4: 1 | G4: 46084 | H4: PNR_MEDICAL_CENTER | I4: FA_001 | J4: 2507000 | K4: MATERIAU | L4: 2507000 | M4: 0 | N4: 0 | O4: 2507000 | P4: PRIX_OK | Q4: 3939499.8 | R4: 2883050 | S4: 2883050 | T4: 3939499.8 | U4: -1056449.8 | V4: -0.36643478 | W4: LOCAL | X4: 1 | Y4: 0.08013913
A5: BPU-INSTALL-GEN-MAT-004 | B5: Matériel de chantier (engins, manutention etc) | C5: BAT_PRINCIPAL | D5: GLOBAL | E5: FORFAIT | F5: 1 | G5: 46084 | H5: PNR_MEDICAL_CENTER | I5: FA_001 | J5: 4213438 | K5: MATERIAU | L5: 4213438 | M5: 0 | N5: 0 | O5: 4213438 | P5: PRIX_OK | Q5: 6620996.5 | R5: 4845453.7 | S5: 4845453.7 | T5: 6620996.5 | U5: -1775542.8 | V5: -0.36643478 | W5: LOCAL | X5: 1 | Y5: 0.08013913
A6: BPU-INSTALL-GEN-DIVERS-005 | B6: Divers (sécurité, ASE, panneau de chantier...) | C6: BAT_PRINCIPAL | D6: GLOBAL | E6: FORFAIT | F6: 1 | G6: 46084 | H6: PNR_MEDICAL_CENTER | I6: FA_001 | J6: 4945000 | K6: MATERIAU | L6: 4945000 | M6: 0 | N6: 0 | O6: 4945000 | P6: PRIX_OK | Q6: 7770573 | R6: 5686750 | S6: 5686750 | T6: 7770573 | U6: -2083823 | V6: -0.36643478 | W6: LOCAL | X6: 1 | Y6: 0.08013913
A7: BPU-INSTALL-GEN-ETUDE-006 | B7: Études techniques et Essais | C7: BAT_PRINCIPAL | D7: GLOBAL | E7: FORFAIT | F7: 1 | G7: 46084 | H7: PNR_MEDICAL_CENTER | I7: FA_001 | J7: 4795500 | K7: MATERIAU | L7: 4795500 | M7: 0 | N7: 0 | O7: 4795500 | P7: PRIX_OK | Q7: 7535648.7 | R7: 5514825 | S7: 5514825 | T7: 7535648.7 | U7: -2020823.7 | V7: -0.36643478 | W7: LOCAL | X7: 1 | Y7: 0.08013913
A8: BPU-INSTALL-GEN-AXE-007 | B8: Ensemble des axes necessaires | C8: BAT_PRINCIPAL | D8: GLOBAL | E8: FORFAIT | F8: 1 | G8: 46084 | H8: PNR_MEDICAL_CENTER | I8: FA_001 | J8: 1265000 | K8: MATERIAU | L8: 1265000 | M8: 0 | N8: 0 | O8: 1265000 | P8: PRIX_OK | Q8: 1987821 | R8: 1454750 | S8: 1454750 | T8: 1987821 | U8: -533071 | V8: -0.36643478 | W8: LOCAL | X8: 1 | Y8: 0.08013913
A9: BPU-DEMO-MUR-ESC-RDC-008 | B9: Démolition des murs et l'escalier (RDC) | C9: BAT_PRINCIPAL | D9: RDC | E9: FORFAIT | F9: 1 | G9: 46084 | H9: PNR_MEDICAL_CENTER | I9: FA_001 | J9: 1725000 | K9: MATERIAU | L9: 1725000 | M9: 0 | N9: 0 | O9: 1725000 | P9: PRIX_OK | Q9: 2710665 | R9: 1983750 | S9: 1983750 | T9: 2710665 | U9: -726915 | V9: -0.36643478 | W9: LOCAL | X9: 1 | Y9: 0.08013913
A10: BPU-DEMO-MUR-ESC-ET1-ANNEXE-009 | B10: Démolition des murs et l'escalier y compris la dalle existente bâtiment annexe (ÉTAGE 1) | C10: BAT_ANNEXE | D10: ETAGE 1 | E10: FORFAIT | F10: 1 | G10: 46084 | H10: PNR_MEDICAL_CENTER | I10: FA_001 | J10: 2587500 | K10: MATERIAU | L10: 2587500 | M10: 0 | N10: 0 | O10: 2587500 | P10: PRIX_OK | Q10: 4065997.5 | R10: 2975625 | S10: 2975625 | T10: 4065997.5 | U10: -1090372.5 | V10: -0.36643478 | W10: LOCAL | X10: 1 | Y10: 0.08013913
A11: BPU-DEMO-MUR-ESC-ET2-010 | B11: Démolition des murs et l'escalier (ÉTAGE 2) | C11: BAT_PRINCIPAL | D11: ETAGE 2 | E11: FORFAIT | F11: 1 | G11: 46084 | H11: PNR_MEDICAL_CENTER | I11: FA_001 | J11: 1725000 | K11: MATERIAU | L11: 1725000 | M11: 0 | N11: 0 | O11: 1725000 | P11: PRIX_OK | Q11: 2710665 | R11: 1983750 | S11: 1983750 | T11: 2710665 | U11: -726915 | V11: -0.36643478 | W11: LOCAL | X11: 1 | Y11: 0.08013913
A12: BPU-DEMO-EVAC-GRAVAT-011 | B12: Évacuation des gravats hors site | C12: BAT_PRINCIPAL | D12: GLOBAL | E12: FORFAIT | F12: 1 | G12: 46084 | H12: PNR_MEDICAL_CENTER | I12: FA_001 | J12: 552000 | K12: MATERIAU | L12: 552000 | M12: 0 | N12: 0 | O12: 552000 | P12: PRIX_OK | Q12: 867412.8 | R12: 634800 | S12: 634800 | T12: 867412.8 | U12: -232612.8 | V12: -0.36643478 | W12: LOCAL | X12: 1 | Y12: 0.08013913
A13: BPU-DEMO-DECAP-CARREAU-012 | B13: Décapage des carreaux sol existants en RDC | C13: BAT_PRINCIPAL | D13: RDC | E13: M2 | F13: 460 | G13: 46084 | H13: PNR_MEDICAL_CENTER | I13: FA_001 | J13: 5750 | K13: MATERIAU | M13: 0 | N13: 0 | P13: MANQUANT_CHINE | R13: 6612.5 | S13: 3041750 | W13: LOCAL | X13: 1
A14: BPU-MACON-FOND-BET-PROP-013 | B14: Béton de propreté | C14: BAT_PRINCIPAL | D14: FONDATIONS | E14: M3 | F14: 3.07 | G14: 46084 | H14: PNR_MEDICAL_CENTER | I14: FA_001 | J14: 338720 | K14: MATERIAU | L14: 338720 | M14: 0 | N14: 0 | O14: 338720 | P14: PRIX_OK | Q14: 532264.61 | R14: 389528 | S14: 1195851 | T14: 1634052.3 | U14: -438201.39 | V14: -0.36643478 | W14: LOCAL | X14: 1 | Y14: 0.08013913
A15: BPU-MACON-FOND-BET-400-014 | B15: Béton 400 hydr | C15: BAT_PRINCIPAL | D15: FONDATIONS | E15: M3 | F15: 4.36 | G15: 46084 | H15: PNR_MEDICAL_CENTER | I15: FA_001 | J15: 189175 | K15: MATERIAU | L15: 189175 | M15: 0 | N15: 0 | O15: 189175 | P15: PRIX_OK | Q15: 297269.6 | R15: 217551.25 | S15: 948523.45 | T15: 1296095.4 | U15: -347571.98 | V15: -0.36643478 | W15: LOCAL | X15: 1 | Y15: 0.08013913
A16: BPU-MACON-FOND-COF-015 | B16: Coffrage | C16: BAT_PRINCIPAL | D16: FONDATIONS | E16: M2 | F16: 15.84 | G16: 46084 | H16: PNR_MEDICAL_CENTER | I16: FA_001 | J16: 5750 | K16: MATERIAU | L16: 3350 | M16: 0 | N16: 0 | O16: 3350 | P16: PRIX_OK | Q16: 5264.19 | R16: 6612.5 | S16: 104742 | T16: 83384.77 | U16: 21357.23 | V16: 0.20390321 | W16: LOCAL | X16: 1 | Y16: 0.42234193
A17: BPU-MACON-FOND-AC-016 | B17: Acier | C17: BAT_PRINCIPAL | D17: FONDATIONS | E17: KG | F17: 436 | G17: 46084 | H17: PNR_MEDICAL_CENTER | I17: FA_001 | J17: 1380 | K17: MATERIAU | L17: 370 | M17: 0 | N17: 0 | O17: 370 | P17: PRIX_OK | Q17: 581.418 | R17: 1587 | S17: 691932 | T17: 253498.25 | U17: 438433.75 | V17: 0.63363705 | W17: LOCAL | X17: 1 | Y17: 0.68018223
A18: BPU-MACON-SSO-AGGL-PLEIN-026 | B18: Agglos pleins 20x20x50 | C18: BAT_PRINCIPAL | D18: FONDATIONS | E18: M2 | F18: 78.98 | G18: 46084 | H18: PNR_MEDICAL_CENTER | I18: FA_001 | J18: 12180 | K18: MATERIAU | L18: 12180 | M18: 0 | N18: 0 | O18: 12180 | P18: PRIX_OK | Q18: 19139.652 | R18: 14007 | S18: 1106272.9 | T18: 1511649.7 | U18: -405376.85 | V18: -0.36643478 | W18: LOCAL | X18: 1 | Y18: 0.08013913
A19: BPU-MACON-ELEV-POT-BET-400-017 | B19: Béton 400 hydr (Amorces poteaux) | C19: BAT_PRINCIPAL | D19: FONDATIONS | E19: M3 | F19: 1.65 | G19: 46084 | H19: PNR_MEDICAL_CENTER | I19: FA_001 | J19: 189175 | K19: MATERIAU | M19: 0 | N19: 0 | P19: MANQUANT_CHINE | R19: 217551.25 | S19: 358959.56 | W19: LOCAL | X19: 1
A20: BPU-MACON-AGGL-CREUX-20-046 | B20: Agglos creux 20x20x50 | C20: BAT_PRINCIPAL | D20: RDC | E20: M2 | F20: 1 | G20: 46084 | H20: PNR_MEDICAL_CENTER | I20: FA_001 | J20: 11185 | K20: MATERIAU | L20: 11185 | M20: 0 | N20: 0 | O20: 11185 | P20: PRIX_OK | Q20: 17576.109 | R20: 12862.75 | S20: 12862.75 | T20: 17576.109 | U20: -4713.359 | V20: -0.36643478 | W20: LOCAL | X20: 1 | Y20: 0.08013913
A21: BPU-MACON-ELEV-POT-COF-018 | B21: Coffrage (Amorces poteaux) | C21: BAT_PRINCIPAL | D21: FONDATIONS | E21: M2 | F21: 26.4 | G21: 46084 | H21: PNR_MEDICAL_CENTER | I21: FA_001 | J21: 5750 | K21: MATERIAU | M21: 0 | N21: 0 | P21: MANQUANT_CHINE | R21: 6612.5 | S21: 174570 | W21: LOCAL | X21: 1
A22: BPU-MACON-END-INT-EXT-047 | B22: Enduits intérieurs et extérieurs sur murs | C22: BAT_PRINCIPAL | D22: RDC | E22: M2 | F22: 1 | G22: 46084 | H22: PNR_MEDICAL_CENTER | I22: FA_001 | J22: 3827 | K22: MATERIAU | L22: 3827 | M22: 0 | N22: 0 | O22: 3827 | P22: PRIX_OK | Q22: 6013.7478 | R22: 4401.05 | S22: 4401.05 | T22: 6013.7478 | U22: -1612.6978 | V22: -0.36643478 | W22: LOCAL | X22: 1 | Y22: 0.08013913
A23: BPU-MACON-ELEV-POT-AC-019 | B23: Acier (Amorces poteaux) | C23: BAT_PRINCIPAL | D23: FONDATIONS | E23: KG | F23: 198 | G23: 46084 | H23: PNR_MEDICAL_CENTER | I23: FA_001 | J23: 1380 | K23: MATERIAU | M23: 0 | N23: 0 | P23: MANQUANT_CHINE | R23: 1587 | S23: 314226 | W23: LOCAL | X23: 1
A24: BPU-MACON-END-SOUS-PLF-048 | B24: Enduits sous plafond | C24: BAT_PRINCIPAL | D24: RDC | E24: M2 | F24: 1 | G24: 46084 | H24: PNR_MEDICAL_CENTER | I24: FA_001 | J24: 3827 | K24: MATERIAU | L24: 3827 | M24: 0 | N24: 0 | O24: 3827 | P24: PRIX_OK | Q24: 6013.7478 | R24: 4401.05 | S24: 4401.05 | T24: 6013.7478 | U24: -1612.6978 | V24: -0.36643478 | W24: LOCAL | X24: 1 | Y24: 0.08013913
A25: BPU-MACON-ELEV-LONG-BET-400-020 | B25: Béton 400 hydr (Longrines) | C25: BAT_PRINCIPAL | D25: FONDATIONS | E25: M3 | F25: 3.72 | G25: 46084 | H25: PNR_MEDICAL_CENTER | I25: FA_001 | J25: 189175 | K25: MATERIAU | M25: 0 | N25: 0 | P25: MANQUANT_CHINE | R25: 217551.25 | S25: 809290.65 | W25: LOCAL | X25: 1
A26: BPU-ETANCH-TERR-ACC-FORME-059 | B26: Forme de pente | C26: BAT_PRINCIPAL | D26: DUPLEX 1 | E26: M2 | F26: 320 | G26: 46084 | H26: PNR_MEDICAL_CENTER | I26: FA_002 | J26: 11793 | K26: MATERIAU | L26: 11793 | M26: 1 | N26: 1 | O26: 11793 | P26: PRIX_OK | Q26: 18531.52 | R26: 13561.95 | S26: 4339824 | T26: 5930086.5 | U26: -1590262.5 | V26: -0.36643478 | W26: LOCAL | X26: 2 | Y26: 0.12013913
A27: BPU-MACON-ELEV-LONG-COF-021 | B27: Coffrage (Longrines) | C27: BAT_PRINCIPAL | D27: FONDATIONS | E27: M2 | F27: 37.33 | G27: 46084 | H27: PNR_MEDICAL_CENTER | I27: FA_001 | J27: 5750 | K27: MATERIAU | M27: 0 | N27: 0 | P27: MANQUANT_CHINE | R27: 6612.5 | S27: 246844.62 | W27: LOCAL | X27: 1
A28: BPU-ETANCH-TERR-ACC-BI-060 | B28: Revêtement bicouche sous protection lourde | C28: BAT_PRINCIPAL | D28: DUPLEX 1 | E28: M2 | F28: 320 | G28: 46084 | H28: PNR_MEDICAL_CENTER | I28: FA_002 | J28: 34552 | K28: MATERIAU | L28: 6100 | M28: 1 | N28: 1 | O28: 6100 | P28: PRIX_OK | Q28: 9585.54 | R28: 39734.8 | S28: 12715136 | T28: 3067372.8 | U28: 9647763.2 | V28: 0.75876209 | W28: IMPORT | X28: 2 | Y28: 0.79525726
A29: BPU-MACON-ELEV-LONG-AC-022 | B29: Acier (Longrines) | C29: BAT_PRINCIPAL | D29: FONDATIONS | E29: KG | F29: 484 | G29: 46084 | H29: PNR_MEDICAL_CENTER | I29: FA_001 | J29: 1380 | K29: MATERIAU | M29: 0 | N29: 0 | P29: MANQUANT_CHINE | R29: 1587 | S29: 768108 | W29: LOCAL | X29: 1
A30: BPU-ETANCH-TERR-ACC-RELEV-061 | B30: Relevé d'étanchéité h=50 cm | C30: BAT_PRINCIPAL | D30: DUPLEX 1 | E30: ML | F30: 120 | G30: 46084 | H30: PNR_MEDICAL_CENTER | I30: FA_002 | J30: 8641 | K30: MATERIAU | L30: 3050 | M30: 1 | N30: 1 | O30: 3050 | P30: PRIX_OK | Q30: 4792.77 | R30: 9937.15 | S30: 1192458 | T30: 575132.4 | U30: 617325.6 | V30: 0.51769169 | W30: IMPORT | X30: 2 | Y30: 0.65061502
A31: BPU-MACON-ELEV-DALL-BET-023 | B31: Béton (Dallage sol) | C31: BAT_PRINCIPAL | D31: FONDATIONS | E31: M3 | F31: 33.2 | G31: 46084 | H31: PNR_MEDICAL_CENTER | I31: FA_001 | J31: 189175 | K31: MATERIAU | M31: 0 | N31: 0 | P31: MANQUANT_CHINE | R31: 217551.25 | S31: 7222701.5 | W31: LOCAL | X31: 1
A32: BPU-ETANCH-TERR-INACC-FORME-062 | B32: Forme de pente | C32: BAT_PRINCIPAL | D32: DUPLEX 1 | E32: M2 | F32: 56.75 | G32: 46084 | H32: PNR_MEDICAL_CENTER | I32: FA_002 | J32: 11793 | K32: MATERIAU | L32: 11793 | M32: 1 | N32: 1 | O32: 11793 | P32: PRIX_OK | Q32: 18531.52 | R32: 13561.95 | S32: 769640.66 | T32: 1051663.8 | U32: -282023.11 | V32: -0.36643478 | W32: LOCAL | X32: 2 | Y32: 0.12013913
A33: BPU-ETANCH-TERR-INACC-FORME-062 | B33: Forme de pente | C33: BAT_PRINCIPAL | D33: TERRASSE | E33: M2 | F33: 83 | G33: 46084 | H33: PNR_MEDICAL_CENTER | I33: FA_002 | J33: 11793 | K33: MATERIAU | L33: 11793 | M33: 1 | N33: 1 | O33: 11793 | P33: PRIX_OK | Q33: 18531.52 | R33: 13561.95 | S33: 1125641.8 | T33: 1538116.2 | U33: -412474.33 | V33: -0.36643478 | W33: LOCAL | X33: 2 | Y33: 0.12013913
A34: BPU-ETANCH-TERR-INACC-FORME-062 | B34: Forme de pente | C34: BAT_ANNEXE | D34: TERRASSE | E34: M2 | F34: 231 | G34: 46084 | H34: PNR_MEDICAL_CENTER | I34: FA_002 | J34: 11793 | K34: MATERIAU | L34: 11793 | M34: 1 | N34: 1 | O34: 11793 | P34: PRIX_OK | Q34: 18531.52 | R34: 13561.95 | S34: 3132810.4 | T34: 4280781.2 | U34: -1147970.7 | V34: -0.36643478 | W34: LOCAL | X34: 2 | Y34: 0.12013913
A35: BPU-MACON-ELEV-DALL-COF-024 | B35: Coffrage (Dallage sol) | C35: BAT_PRINCIPAL | D35: FONDATIONS | E35: M2 | F35: 66.8 | G35: 46084 | H35: PNR_MEDICAL_CENTER | I35: FA_001 | J35: 5750 | K35: MATERIAU | M35: 0 | N35: 0 | P35: MANQUANT_CHINE | R35: 6612.5 | S35: 441715 | W35: LOCAL | X35: 1
A36: BPU-ETANCH-TERR-INACC-MONO-063 | B36: Revêtement monocouche sous protection lourde | C36: BAT_PRINCIPAL | D36: DUPLEX 1 | E36: M2 | F36: 56.75 | G36: 46084 | H36: PNR_MEDICAL_CENTER | I36: FA_002 | J36: 17276 | K36: MATERIAU | L36: 4575 | M36: 1 | N36: 1 | O36: 4575 | P36: PRIX_OK | Q36: 7189.155 | R36: 19867.4 | S36: 1127474.9 | T36: 407984.55 | U36: 719490.4 | V36: 0.63814314 | W36: IMPORT | X36: 2 | Y36: 0.72288588
A37: BPU-ETANCH-TERR-INACC-MONO-063 | B37: Revêtement monocouche sous protection | C37: BAT_PRINCIPAL | D37: TERRASSE | E37: M2 | F37: 83 | G37: 46084 | H37: PNR_MEDICAL_CENTER | I37: FA_002 | J37: 17276 | K37: MATERIAU | L37: 4575 | M37: 1 | N37: 1 | O37: 4575 | P37: PRIX_OK | Q37: 7189.155 | R37: 19867.4 | S37: 1648994.2 | T37: 596699.87 | U37: 1052294.3 | V37: 0.63814314 | W37: IMPORT | X37: 2 | Y37: 0.72288588
A38: BPU-ETANCH-TERR-INACC-MONO-063 | B38: Revêtement bicouche sous protection | C38: BAT_ANNEXE | D38: TERRASSE | E38: M2 | F38: 231 | G38: 46084 | H38: PNR_MEDICAL_CENTER | I38: FA_002 | J38: 17276 | K38: MATERIAU | L38: 4575 | M38: 1 | N38: 1 | O38: 4575 | P38: PRIX_OK | Q38: 7189.155 | R38: 19867.4 | S38: 4589369.4 | T38: 1660694.8 | U38: 2928674.6 | V38: 0.63814314 | W38: IMPORT | X38: 2 | Y38: 0.72288588
A39: BPU-MACON-ELEV-DALL-AC-025 | B39: Acier (Dallage sol) | C39: BAT_PRINCIPAL | D39: FONDATIONS | E39: KG | F39: 2324 | G39: 46084 | H39: PNR_MEDICAL_CENTER | I39: FA_001 | J39: 1380 | K39: MATERIAU | M39: 0 | N39: 0 | P39: MANQUANT_CHINE | R39: 1587 | S39: 3688188 | W39: LOCAL | X39: 1
A40: BPU-ETANCH-TERR-INACC-RELEV-064 | B40: Relevé d'étanchéité h=50 cm | C40: BAT_PRINCIPAL | D40: DUPLEX 1 | E40: ML | F40: 36 | G40: 46084 | H40: PNR_MEDICAL_CENTER | I40: FA_002 | J40: 8641 | K40: MATERIAU | L40: 3050 | M40: 1 | N40: 1 | O40: 3050 | P40: PRIX_OK | Q40: 4792.77 | R40: 9937.15 | S40: 357737.4 | T40: 172539.72 | U40: 185197.68 | V40: 0.51769169 | W40: IMPORT | X40: 2 | Y40: 0.65061502
A41: BPU-ETANCH-TERR-INACC-RELEV-064 | B41: Relevé d'étanchéité h=50 cm | C41: BAT_PRINCIPAL | D41: TERRASSE | E41: ML | F41: 11.87 | G41: 46084 | H41: PNR_MEDICAL_CENTER | I41: FA_002 | J41: 8641 | K41: MATERIAU | L41: 3050 | M41: 1 | N41: 1 | O41: 3050 | P41: PRIX_OK | Q41: 4792.77 | R41: 9937.15 | S41: 117953.97 | T41: 56890.18 | U41: 61063.791 | V41: 0.51769169 | W41: IMPORT | X41: 2 | Y41: 0.65061502
A42: BPU-ETANCH-TERR-INACC-RELEV-064 | B42: Relevé d'étanchéité h=50 cm | C42: BAT_ANNEXE | D42: TERRASSE | E42: ML | F42: 101.1 | G42: 46084 | H42: PNR_MEDICAL_CENTER | I42: FA_002 | J42: 8641 | K42: MATERIAU | L42: 3050 | M42: 1 | N42: 1 | O42: 3050 | P42: PRIX_OK | Q42: 4792.77 | R42: 9937.15 | S42: 1004645.9 | T42: 484549.05 | U42: 520096.82 | V42: 0.51769169 | W42: IMPORT | X42: 2 | Y42: 0.65061502
A43: BPU-REVET-FAIENCE-GRANIT-065 | B43: Faïence murale en granite ou similaire | C43: BAT_PRINCIPAL | D43: RDC | E43: M2 | F43: 314.59 | G43: 46084 | H43: PNR_MEDICAL_CENTER | I43: FA_004 | J43: 28175 | K43: MATERIAU | L43: 5490 | M43: 1 | N43: 2 | O43: 5490 | P43: PRIX_OK | Q43: 8626.986 | R43: 32401.25 | S43: 10193109 | T43: 2713963.5 | U43: 7479145.7 | V43: 0.73374527 | W43: IMPORT | X43: 3 | Y43: 0.72024716
A44: BPU-REVET-FAIENCE-GRANIT-065 | B44: Faïence murale en granite ou similaire | C44: BAT_PRINCIPAL | D44: ETAGE 1 | E44: M2 | F44: 351.33 | G44: 46084 | H44: PNR_MEDICAL_CENTER | I44: FA_004 | J44: 28175 | K44: MATERIAU | L44: 5490 | M44: 1 | N44: 2 | O44: 5490 | P44: PRIX_OK | Q44: 8626.986 | R44: 32401.25 | S44: 11383531 | T44: 3030919 | U44: 8352612.2 | V44: 0.73374527 | W44: IMPORT | X44: 3 | Y44: 0.72024716
A45: BPU-REVET-FAIENCE-GRANIT-065 | B45: Faïence murale en granite ou similaire | C45: BAT_PRINCIPAL | D45: ETAGE 2 | E45: M2 | F45: 278.2 | G45: 46084 | H45: PNR_MEDICAL_CENTER | I45: FA_004 | J45: 28175 | K45: MATERIAU | L45: 5490 | M45: 1 | N45: 2 | O45: 5490 | P45: PRIX_OK | Q45: 8626.986 | R45: 32401.25 | S45: 9014027.7 | T45: 2400027.5 | U45: 6614000.2 | V45: 0.73374527 | W45: IMPORT | X45: 3 | Y45: 0.72024716
A46: BPU-REVET-FAIENCE-GRANIT-065 | B46: Faïence murale en granite ou similaire | C46: BAT_PRINCIPAL | D46: DUPLEX 1 | E46: M2 | F46: 162.06 | G46: 46084 | H46: PNR_MEDICAL_CENTER | I46: FA_004 | J46: 28175 | K46: MATERIAU | L46: 5490 | M46: 1 | N46: 2 | O46: 5490 | P46: PRIX_OK | Q46: 8626.986 | R46: 32401.25 | S46: 5250946.6 | T46: 1398089.4 | U46: 3852857.2 | V46: 0.73374527 | W46: IMPORT | X46: 3 | Y46: 0.72024716
A47: BPU-REVET-FAIENCE-GRANIT-065 | B47: Faïence murale en granite ou similaire | C47: BAT_PRINCIPAL | D47: DUPLEX 2 | E47: M2 | F47: 99.33 | G47: 46084 | H47: PNR_MEDICAL_CENTER | I47: FA_004 | J47: 28175 | K47: MATERIAU | L47: 5490 | M47: 1 | N47: 2 | O47: 5490 | P47: PRIX_OK | Q47: 8626.986 | R47: 32401.25 | S47: 3218416.2 | T47: 856918.52 | U47: 2361497.6 | V47: 0.73374527 | W47: IMPORT | X47: 3 | Y47: 0.72024716
A48: BPU-REVET-FAIENCE-GRANIT-065 | B48: Faïence murale en granite ou similaire | C48: BAT_ANNEXE | D48: RDC | E48: M2 | F48: 87.52 | G48: 46084 | H48: PNR_MEDICAL_CENTER | I48: FA_004 | J48: 28175 | K48: MATERIAU | L48: 5490 | M48: 1 | N48: 2 | O48: 5490 | P48: PRIX_OK | Q48: 8626.986 | R48: 32401.25 | S48: 2835757.4 | T48: 755033.81 | U48: 2080723.6 | V48: 0.73374527 | W48: IMPORT | X48: 3 | Y48: 0.72024716
A49: BPU-REVET-FAIENCE-GRANIT-065 | B49: Faïence murale en granite ou similaire | C49: BAT_ANNEXE | D49: RDC | E49: M2 | F49: 56.71 | G49: 46084 | H49: PNR_MEDICAL_CENTER | I49: FA_004 | J49: 28175 | K49: MATERIAU | L49: 5490 | M49: 1 | N49: 2 | O49: 5490 | P49: PRIX_OK | Q49: 8626.986 | R49: 32401.25 | S49: 1837474.9 | T49: 489236.38 | U49: 1348238.5 | V49: 0.73374527 | W49: IMPORT | X49: 3 | Y49: 0.72024716
A50: BPU-REVET-FAIENCE-GRANIT-065 | B50: Faïence murale en granite ou similaire | C50: BAT_ANNEXE | D50: ETAGE 1 | E50: M2 | F50: 60.7 | G50: 46084 | H50: PNR_MEDICAL_CENTER | I50: FA_004 | J50: 28175 | K50: MATERIAU | L50: 5490 | M50: 1 | N50: 2 | O50: 5490 | P50: PRIX_OK | Q50: 8626.986 | R50: 32401.25 | S50: 1966755.9 | T50: 523658.05 | U50: 1443097.8 | V50: 0.73374527 | W50: IMPORT | X50: 3 | Y50: 0.72024716
A51: BPU-MACON-ELEV-POT-BET-400-027 | B51: Béton 400 hydr (Dallage sol - Annexe) | C51: BAT_ANNEXE | D51: FONDATIONS | E51: M3 | F51: 30.3 | G51: 46084 | H51: PNR_MEDICAL_CENTER | I51: FA_001 | J51: 189175 | K51: MATERIAU | M51: 0 | N51: 0 | P51: MANQUANT_CHINE | R51: 217551.25 | S51: 6591802.9 | W51: LOCAL | X51: 1
A52: BPU-REVET-SOL-GRANIT-60X60-066 | B52: Granite tile : SARADO Grey-Flamed 60x60 | C52: BAT_PRINCIPAL | D52: RDC | E52: M2 | F52: 559 | G52: 46084 | H52: PNR_MEDICAL_CENTER | I52: FA_004 | J52: 33925 | K52: MATERIAU | L52: 10065 | M52: 1 | N52: 2 | O52: 10065 | P52: PRIX_OK | Q52: 15816.141 | R52: 39013.75 | S52: 21808686 | T52: 8841222.8 | U52: 12967463 | V52: 0.59460085 | W52: IMPORT | X52: 3 | Y52: 0.63676051
A53: BPU-REVET-SOL-GRANIT-60X60-066 | B53: Granite tile : SARADO Grey-Flamed 60x60 | C53: BAT_PRINCIPAL | D53: ETAGE 1 | E53: M2 | F53: 594 | G53: 46084 | H53: PNR_MEDICAL_CENTER | I53: FA_004 | J53: 33925 | K53: MATERIAU | L53: 10065 | M53: 1 | N53: 2 | O53: 10065 | P53: PRIX_OK | Q53: 15816.141 | R53: 39013.75 | S53: 23174168 | T53: 9394787.8 | U53: 13779380 | V53: 0.59460085 | W53: IMPORT | X53: 3 | Y53: 0.63676051
A54: BPU-REVET-SOL-GRANIT-60X60-066 | B54: Granite tile : SARADO Grey-Flamed 60x60 | C54: BAT_PRINCIPAL | D54: ETAGE 2 | E54: M2 | F54: 557 | G54: 46084 | H54: PNR_MEDICAL_CENTER | I54: FA_004 | J54: 33925 | K54: MATERIAU | L54: 10065 | M54: 1 | N54: 2 | O54: 10065 | P54: PRIX_OK | Q54: 15816.141 | R54: 39013.75 | S54: 21730659 | T54: 8809590.5 | U54: 12921068 | V54: 0.59460085 | W54: IMPORT | X54: 3 | Y54: 0.63676051
A55: BPU-REVET-SOL-GRANIT-60X60-066 | B55: Granite tile : SARADO Grey-Flamed 60x60 | C55: BAT_PRINCIPAL | D55: DUPLEX 1 | E55: M2 | F55: 557 | G55: 46084 | H55: PNR_MEDICAL_CENTER | I55: FA_004 | J55: 33925 | K55: MATERIAU | L55: 10065 | M55: 1 | N55: 2 | O55: 10065 | P55: PRIX_OK | Q55: 15816.141 | R55: 39013.75 | S55: 21730659 | T55: 8809590.5 | U55: 12921068 | V55: 0.59460085 | W55: IMPORT | X55: 3 | Y55: 0.63676051
A56: BPU-REVET-SOL-GRANIT-60X60-066 | B56: Granite tile : SARADO Grey-Flamed 60x60 | C56: BAT_PRINCIPAL | D56: DUPLEX 2 | E56: M2 | F56: 182 | G56: 46084 | H56: PNR_MEDICAL_CENTER | I56: FA_004 | J56: 33925 | K56: MATERIAU | L56: 10065 | M56: 1 | N56: 2 | O56: 10065 | P56: PRIX_OK | Q56: 15816.141 | R56: 39013.75 | S56: 7100502.5 | T56: 2878537.7 | U56: 4221964.8 | V56: 0.59460085 | W56: IMPORT | X56: 3 | Y56: 0.63676051
A57: BPU-REVET-SOL-GRANIT-60X60-066 | B57: Granite tile : SARADO Grey-Flamed 60x60 | C57: BAT_ANNEXE | D57: RDC | E57: M2 | F57: 210 | G57: 46084 | H57: PNR_MEDICAL_CENTER | I57: FA_004 | J57: 33925 | K57: MATERIAU | L57: 10065 | M57: 1 | N57: 2 | O57: 10065 | P57: PRIX_OK | Q57: 15816.141 | R57: 39013.75 | S57: 8192887.5 | T57: 3321389.6 | U57: 4871497.9 | V57: 0.59460085 | W57: IMPORT | X57: 3 | Y57: 0.63676051
A58: BPU-REVET-SOL-GRANIT-60X60-066 | B58: Granite tile : SARADO Grey-Flamed 60x60 | C58: BAT_ANNEXE | D58: ETAGE 1 | E58: M2 | F58: 210 | G58: 46084 | H58: PNR_MEDICAL_CENTER | I58: FA_004 | J58: 33925 | K58: MATERIAU | L58: 10065 | M58: 1 | N58: 2 | O58: 10065 | P58: PRIX_OK | Q58: 15816.141 | R58: 39013.75 | S58: 8192887.5 | T58: 3321389.6 | U58: 4871497.9 | V58: 0.59460085 | W58: IMPORT | X58: 3 | Y58: 0.63676051
A59: BPU-MACON-ELEV-POT-COF-028 | B59: Coffrage (Dallage sol - Annexe) | C59: BAT_ANNEXE | D59: FONDATIONS | E59: M2 | F59: 10.8 | G59: 46084 | H59: PNR_MEDICAL_CENTER | I59: FA_001 | J59: 5750 | K59: MATERIAU | M59: 0 | N59: 0 | P59: MANQUANT_CHINE | R59: 6612.5 | S59: 71415 | W59: LOCAL | X59: 1
A60: BPU-REVET-PLINTH-GRANIT-067 | B60: Plinthe 10x60 Granite tile : SARADO Grey-Flamed | C60: BAT_PRINCIPAL | D60: RDC | E60: ML | F60: 418.68 | G60: 46084 | H60: PNR_MEDICAL_CENTER | I60: FA_004 | J60: 5750 | K60: MATERIAU | L60: 2745 | M60: 1 | N60: 2 | O60: 2745 | P60: PRIX_OK | Q60: 4313.493 | R60: 6612.5 | S60: 2768521.5 | T60: 1805973.2 | U60: 962548.25 | V60: 0.34767592 | W60: IMPORT | X60: 3 | Y60: 0.48860555
A61: BPU-REVET-PLINTH-GRANIT-067 | B61: Plinthe 10x60 Granite tile : SARADO Grey-Flamed | C61: BAT_PRINCIPAL | D61: ETAGE 1 | E61: ML | F61: 494.58 | G61: 46084 | H61: PNR_MEDICAL_CENTER | I61: FA_004 | J61: 5750 | K61: MATERIAU | L61: 2745 | M61: 1 | N61: 2 | O61: 2745 | P61: PRIX_OK | Q61: 4313.493 | R61: 6612.5 | S61: 3270410.2 | T61: 2133367.4 | U61: 1137042.9 | V61: 0.34767592 | W61: IMPORT | X61: 3 | Y61: 0.48860555
A62: BPU-REVET-PLINTH-GRANIT-067 | B62: Plinthe 10x60 Granite tile : SARADO Grey-Flamed | C62: BAT_PRINCIPAL | D62: ETAGE 2 | E62: ML | F62: 499.38 | G62: 46084 | H62: PNR_MEDICAL_CENTER | I62: FA_004 | J62: 5750 | K62: MATERIAU | L62: 2745 | M62: 1 | N62: 2 | O62: 2745 | P62: PRIX_OK | Q62: 4313.493 | R62: 6612.5 | S62: 3302150.2 | T62: 2154072.1 | U62: 1148078.1 | V62: 0.34767592 | W62: IMPORT | X62: 3 | Y62: 0.48860555
A63: BPU-REVET-PLINTH-GRANIT-067 | B63: Plinthe 10x60 Granite tile : SARADO Grey-Flamed | C63: BAT_PRINCIPAL | D63: DUPLEX 1 | E63: ML | F63: 300.82 | G63: 46084 | H63: PNR_MEDICAL_CENTER | I63: FA_004 | J63: 5750 | K63: MATERIAU | L63: 2745 | M63: 1 | N63: 2 | O63: 2745 | P63: PRIX_OK | Q63: 4313.493 | R63: 6612.5 | S63: 1989172.2 | T63: 1297585 | U63: 691587.29 | V63: 0.34767592 | W63: IMPORT | X63: 3 | Y63: 0.48860555
A64: BPU-REVET-PLINTH-GRANIT-067 | B64: Plinthe 10x60 Granite tile : SARADO Grey-Flamed | C64: BAT_PRINCIPAL | D64: DUPLEX 2 | E64: ML | F64: 172.84 | G64: 46084 | H64: PNR_MEDICAL_CENTER | I64: FA_004 | J64: 5750 | K64: MATERIAU | L64: 2745 | M64: 1 | N64: 2 | O64: 2745 | P64: PRIX_OK | Q64: 4313.493 | R64: 6612.5 | S64: 1142904.5 | T64: 745544.13 | U64: 397360.37 | V64: 0.34767592 | W64: IMPORT | X64: 3 | Y64: 0.48860555
A65: BPU-REVET-PLINTH-GRANIT-067 | B65: Plinthe 10x60 Granite tile : SARADO Grey-Flamed | C65: BAT_ANNEXE | D65: RDC | E65: ML | F65: 119.94 | G65: 46084 | H65: PNR_MEDICAL_CENTER | I65: FA_004 | J65: 5750 | K65: MATERIAU | L65: 2745 | M65: 1 | N65: 2 | O65: 2745 | P65: PRIX_OK | Q65: 4313.493 | R65: 6612.5 | S65: 793103.25 | T65: 517360.35 | U65: 275742.9 | V65: 0.34767592 | W65: IMPORT | X65: 3 | Y65: 0.48860555
A66: BPU-REVET-PLINTH-GRANIT-067 | B66: Plinthe 10x60 Granite tile : SARADO Grey-Flamed | C66: BAT_ANNEXE | D66: ETAGE 1 | E66: ML | F66: 192.38 | G66: 46084 | H66: PNR_MEDICAL_CENTER | I66: FA_004 | J66: 5750 | K66: MATERIAU | L66: 2745 | M66: 1 | N66: 2 | O66: 2745 | P66: PRIX_OK | Q66: 4313.493 | R66: 6612.5 | S66: 1272112.7 | T66: 829829.78 | U66: 442282.97 | V66: 0.34767592 | W66: IMPORT | X66: 3 | Y66: 0.48860555
A67: BPU-MACON-ELEV-POT-AC-029 | B67: Acier (Dallage sol - Annexe) | C67: BAT_ANNEXE | D67: FONDATIONS | E67: KG | F67: 1818 | G67: 46084 | H67: PNR_MEDICAL_CENTER | I67: FA_001 | J67: 1380 | K67: MATERIAU | M67: 0 | N67: 0 | P67: MANQUANT_CHINE | R67: 1587 | S67: 2885166 | W67: LOCAL | X67: 1
A68: BPU-REVET-PLAN-TRAV-GRANIT-068 | B68: Table de travail en granite ou similaire | C68: BAT_ANNEXE | D68: RDC | E68: ML | F68: 5.19 | G68: 46084 | H68: PNR_MEDICAL_CENTER | I68: FA_004 | J68: 517500 | K68: MATERIAU | L68: 42700 | M68: 1 | N68: 2 | O68: 42700 | P68: PRIX_OK | Q68: 67098.78 | R68: 595125 | S68: 3088698.8 | T68: 348242.67 | U68: 2740456.1 | V68: 0.88725263 | W68: IMPORT | X68: 3 | Y68: 0.81235158
A69: BPU-MACON-ELEV-POUT-BET-350-030 | B69: Béton 400 (Poteaux RDC) | C69: BAT_PRINCIPAL | D69: RDC | E69: M3 | F69: 2.48 | G69: 46084 | H69: PNR_MEDICAL_CENTER | I69: FA_001 | J69: 189175 | K69: MATERIAU | M69: 0 | N69: 0 | P69: MANQUANT_CHINE | R69: 217551.25 | S69: 539527.1 | W69: LOCAL | X69: 1
A70: BPU-MACON-ELEV-POUT-COF-031 | B70: Coffrage (Poteaux RDC) | C70: BAT_PRINCIPAL | D70: RDC | E70: M2 | F70: 39.6 | G70: 46084 | H70: PNR_MEDICAL_CENTER | I70: FA_001 | J70: 5750 | K70: MATERIAU | M70: 0 | N70: 0 | P70: MANQUANT_CHINE | R70: 6612.5 | S70: 261855 | W70: LOCAL | X70: 1
A71: BPU-MACON-ELEV-POUT-AC-032 | B71: Acier (Poteaux RDC) | C71: BAT_PRINCIPAL | D71: RDC | E71: KG | F71: 297.6 | G71: 46084 | H71: PNR_MEDICAL_CENTER | I71: FA_001 | J71: 1380 | K71: MATERIAU | M71: 0 | N71: 0 | P71: MANQUANT_CHINE | R71: 1587 | S71: 472291.2 | W71: LOCAL | X71: 1
A72: BPU-MACON-ELEV-CH-BET-350-033 | B72: Béton 350 (Poutres RDC) | C72: BAT_PRINCIPAL | D72: RDC | E72: M3 | F72: 3.72 | G72: 46084 | H72: PNR_MEDICAL_CENTER | I72: FA_001 | J72: 189175 | K72: MATERIAU | M72: 0 | N72: 0 | P72: MANQUANT_CHINE | R72: 217551.25 | S72: 809290.65 | W72: LOCAL | X72: 1
A73: BPU-MACON-ELEV-CH-COF-034 | B73: Coffrage (Poutres RDC) | C73: BAT_PRINCIPAL | D73: RDC | E73: M2 | F73: 46.46 | G73: 46084 | H73: PNR_MEDICAL_CENTER | I73: FA_001 | J73: 5750 | K73: MATERIAU | M73: 0 | N73: 0 | P73: MANQUANT_CHINE | R73: 6612.5 | S73: 307216.75 | W73: LOCAL | X73: 1
A74: BPU-MACON-ELEV-CH-AC-035 | B74: Acier (Poutres RDC) | C74: BAT_PRINCIPAL | D74: RDC | E74: KG | F74: 483.6 | G74: 46084 | H74: PNR_MEDICAL_CENTER | I74: FA_001 | J74: 1380 | K74: MATERIAU | M74: 0 | N74: 0 | P74: MANQUANT_CHINE | R74: 1587 | S74: 767473.2 | W74: LOCAL | X74: 1
A75: BPU-MACON-ELEV-LINT-BET-400-036 | B75: Béton 350 (Chainages RDC) | C75: BAT_PRINCIPAL | D75: RDC | E75: M3 | F75: 5.31 | G75: 46084 | H75: PNR_MEDICAL_CENTER | I75: FA_001 | J75: 189175 | K75: MATERIAU | M75: 0 | N75: 0 | P75: MANQUANT_CHINE | R75: 217551.25 | S75: 1155197.1 | W75: LOCAL | X75: 1
A76: BPU-MACON-ELEV-LINT-COF-037 | B76: Coffrage (Chainages RDC) | C76: BAT_PRINCIPAL | D76: RDC | E76: M2 | F76: 79.63 | G76: 46084 | H76: PNR_MEDICAL_CENTER | I76: FA_001 | J76: 5750 | K76: MATERIAU | M76: 0 | N76: 0 | P76: MANQUANT_CHINE | R76: 6612.5 | S76: 526553.37 | W76: LOCAL | X76: 1
A77: BPU-MACON-ELEV-LINT-AC-038 | B77: Acier (Chainages RDC) | C77: BAT_PRINCIPAL | D77: RDC | E77: KG | F77: 1113.6 | G77: 46084 | H77: PNR_MEDICAL_CENTER | I77: FA_001 | J77: 1380 | K77: MATERIAU | M77: 0 | N77: 0 | P77: MANQUANT_CHINE | R77: 1587 | S77: 1767283.2 | W77: LOCAL | X77: 1
A78: BPU-MACON-ELEV-ESC-BET-350-039 | B78: Béton 400 (Linteaux RDC) | C78: BAT_PRINCIPAL | D78: RDC | E78: M3 | F78: 4.74 | G78: 46084 | H78: PNR_MEDICAL_CENTER | I78: FA_001 | J78: 189175 | K78: MATERIAU | M78: 0 | N78: 0 | P78: MANQUANT_CHINE | R78: 217551.25 | S78: 1031192.9 | W78: LOCAL | X78: 1
A79: BPU-MACON-ELEV-ESC-COF-040 | B79: Coffrage (Linteaux RDC) | C79: BAT_PRINCIPAL | D79: RDC | E79: M2 | F79: 71.1 | G79: 46084 | H79: PNR_MEDICAL_CENTER | I79: FA_001 | J79: 5750 | K79: MATERIAU | M79: 0 | N79: 0 | P79: MANQUANT_CHINE | R79: 6612.5 | S79: 470148.75 | W79: LOCAL | X79: 1
A80: BPU-MACON-ELEV-ESC-AC-041 | B80: Acier (Linteaux RDC) | C80: BAT_PRINCIPAL | D80: RDC | E80: KG | F80: 331.8 | G80: 46084 | H80: PNR_MEDICAL_CENTER | I80: FA_001 | J80: 1380 | K80: MATERIAU | M80: 0 | N80: 0 | P80: MANQUANT_CHINE | R80: 1587 | S80: 526566.6 | W80: LOCAL | X80: 1
... A102: BPU-ETANCH-LOC-RELEV-058 | B102: Relevé d'étanchéité h=50 cm | C102: BAT_ANNEXE | D102: ETAGE 1 | E102: ML | F102: 77.72 | G102: 46084 | H102: PNR_MEDICAL_CENTER | I102: FA_002 | J102: 8641 | K102: MATERIAU | M102: 1 | N102: 1 | P102: MANQUANT_CHINE | R102: 9937.15 | S102: 772315.3 | W102: LOCAL | X102: 2
A103: BPU-MEN-ALUM-BAIE-069 | B103: Baie vitrée en alu 220x527 | C103: BAT_PRINCIPAL | D103: RDC | E103: M2 | F103: 46.38 | G103: 46084 | H103: PNR_MEDICAL_CENTER | I103: FA_005 | J103: 138000 | K103: MATERIAU | L103: 35075 | M103: 1 | N103: 2 | O103: 35075 | P103: PRIX_OK | Q103: 55116.855 | R103: 158700 | S103: 7360506 | T103: 2556319.7 | U103: 4804186.3 | V103: 0.65269783 | W103: IMPORT | X103: 4 | Y103: 0.6716187
A104: BPU-MEN-ALUM-BAIE-069 | B104: Baie vitrée en alu 220x242 | C104: BAT_PRINCIPAL | D104: RDC | E104: M2 | F104: 5.32 | G104: 46084 | H104: PNR_MEDICAL_CENTER | I104: FA_005 | J104: 138000 | K104: MATERIAU | L104: 35075 | M104: 1 | N104: 2 | O104: 35075 | P104: PRIX_OK | Q104: 55116.855 | R104: 158700 | S104: 844284 | T104: 293221.67 | U104: 551062.33 | V104: 0.65269783 | W104: IMPORT | X104: 4 | Y104: 0.6716187
A105: BPU-MEN-ALUM-BAIE-069 | B105: Baie vitrée en alu 120x200 | C105: BAT_PRINCIPAL | D105: RDC | E105: M2 | F105: 12 | G105: 46084 | H105: PNR_MEDICAL_CENTER | I105: FA_005 | J105: 138000 | K105: MATERIAU | L105: 35075 | M105: 1 | N105: 2 | O105: 35075 | P105: PRIX_OK | Q105: 55116.855 | R105: 158700 | S105: 1904400 | T105: 661402.26 | U105: 1242997.7 | V105: 0.65269783 | W105: IMPORT | X105: 4 | Y105: 0.6716187
A106: BPU-MEN-ALUM-BAIE-069 | B106: Baie vitrée en alu 120x140 | C106: BAT_PRINCIPAL | D106: RDC | E106: M2 | F106: 3.36 | G106: 46084 | H106: PNR_MEDICAL_CENTER | I106: FA_005 | J106: 138000 | K106: MATERIAU | L106: 35075 | M106: 1 | N106: 2 | O106: 35075 | P106: PRIX_OK | Q106: 55116.855 | R106: 158700 | S106: 533232 | T106: 185192.63 | U106: 348039.37 | V106: 0.65269783 | W106: IMPORT | X106: 4 | Y106: 0.6716187
A107: BPU-MEN-ALUM-BAIE-069 | B107: Baie vitrée en alu 120x160 | C107: BAT_PRINCIPAL | D107: RDC | E107: M2 | F107: 1.92 | G107: 46084 | H107: PNR_MEDICAL_CENTER | I107: FA_005 | J107: 138000 | K107: MATERIAU | L107: 35075 | M107: 1 | N107: 2 | O107: 35075 | P107: PRIX_OK | Q107: 55116.855 | R107: 158700 | S107: 304704 | T107: 105824.36 | U107: 198879.64 | V107: 0.65269783 | W107: IMPORT | X107: 4 | Y107: 0.6716187
A108: BPU-MEN-ALUM-BAIE-069 | B108: Baie vitrée en alu 100x120 | C108: BAT_PRINCIPAL | D108: RDC | E108: M2 | F108: 1.2 | G108: 46084 | H108: PNR_MEDICAL_CENTER | I108: FA_005 | J108: 138000 | K108: MATERIAU | L108: 35075 | M108: 1 | N108: 2 | O108: 35075 | P108: PRIX_OK | Q108: 55116.855 | R108: 158700 | S108: 190440 | T108: 66140.226 | U108: 124299.77 | V108: 0.65269783 | W108: IMPORT | X108: 4 | Y108: 0.6716187
A109: BPU-MEN-ALUM-BAIE-069 | B109: Baie vitrée en alu 60x60 | C109: BAT_PRINCIPAL | D109: RDC | E109: M2 | F109: 1.44 | G109: 46084 | H109: PNR_MEDICAL_CENTER | I109: FA_005 | J109: 138000 | K109: MATERIAU | L109: 35075 | M109: 1 | N109: 2 | O109: 35075 | P109: PRIX_OK | Q109: 55116.855 | R109: 158700 | S109: 228528 | T109: 79368.271 | U109: 149159.73 | V109: 0.65269783 | W109: IMPORT | X109: 4 | Y109: 0.6716187
A110: BPU-MEN-ALUM-BAIE-069 | B110: Baie vitrée en alu 220x245 | C110: BAT_PRINCIPAL | D110: RDC | E110: M2 | F110: 5.39 | G110: 46084 | H110: PNR_MEDICAL_CENTER | I110: FA_005 | J110: 138000 | K110: MATERIAU | L110: 35075 | M110: 1 | N110: 2 | O110: 35075 | P110: PRIX_OK | Q110: 55116.855 | R110: 158700 | S110: 855393 | T110: 297079.85 | U110: 558313.15 | V110: 0.65269783 | W110: IMPORT | X110: 4 | Y110: 0.6716187
A111: BPU-MEN-ALUM-BAIE-069 | B111: Baie vitrée en alu 220x150 | C111: BAT_PRINCIPAL | D111: RDC | E111: M2 | F111: 9.9 | G111: 46084 | H111: PNR_MEDICAL_CENTER | I111: FA_005 | J111: 138000 | K111: MATERIAU | L111: 35075 | M111: 1 | N111: 2 | O111: 35075 | P111: PRIX_OK | Q111: 55116.855 | R111: 158700 | S111: 1571130 | T111: 545656.86 | U111: 1025473.1 | V111: 0.65269783 | W111: IMPORT | X111: 4 | Y111: 0.6716187
A112: BPU-MEN-ALUM-BAIE-069 | B112: Baie vitrée en alu 220x120 | C112: BAT_PRINCIPAL | D112: RDC | E112: M2 | F112: 5.28 | G112: 46084 | H112: PNR_MEDICAL_CENTER | I112: FA_005 | J112: 138000 | K112: MATERIAU | L112: 35075 | M112: 1 | N112: 2 | O112: 35075 | P112: PRIX_OK | Q112: 55116.855 | R112: 158700 | S112: 837936 | T112: 291016.99 | U112: 546919.01 | V112: 0.65269783 | W112: IMPORT | X112: 4 | Y112: 0.6716187
A113: BPU-MEN-ALUM-BAIE-069 | B113: Baie vitrée en alu 220x90 | C113: BAT_PRINCIPAL | D113: RDC | E113: M2 | F113: 31.68 | G113: 46084 | H113: PNR_MEDICAL_CENTER | I113: FA_005 | J113: 138000 | K113: MATERIAU | L113: 35075 | M113: 1 | N113: 2 | O113: 35075 | P113: PRIX_OK | Q113: 55116.855 | R113: 158700 | S113: 5027616 | T113: 1746102 | U113: 3281514 | V113: 0.65269783 | W113: IMPORT | X113: 4 | Y113: 0.6716187
A114: BPU-MEN-ALUM-BAIE-069 | B114: Baie vitrée en alu 220x80 | C114: BAT_PRINCIPAL | D114: RDC | E114: M2 | F114: 19.36 | G114: 46084 | H114: PNR_MEDICAL_CENTER | I114: FA_005 | J114: 138000 | K114: MATERIAU | L114: 35075 | M114: 1 | N114: 2 | O114: 35075 | P114: PRIX_OK | Q114: 55116.855 | R114: 158700 | S114: 3072432 | T114: 1067062.3 | U114: 2005369.7 | V114: 0.65269783 | W114: IMPORT | X114: 4 | Y114: 0.6716187
... A214: BPU-CLIM-VRV-UI-GAINABLE-3CV-110 | B214: Unité intérieure 3CV type gainable encastrable de SAMSUNG et toutes sujétions de pose | C214: BAT_PRINCIPAL | D214: GLOBAL | E214: FORFAIT | F214: 12 | G214: 46084 | H214: PNR_MEDICAL_CENTER | I214: FA_009 | J214: 575000 | K214: MATERIAU | L214: 152500 | M214: 1 | N214: 2.5 | O214: 152500 | P214: PRIX_OK | Q214: 239638.5 | R214: 661250 | S214: 7935000 | T214: 2875662 | U214: 5059338 | V214: 0.63759773 | W214: IMPORT | X214: 8 | Y214: 0.63255864
A215: BPU-CLIM-KIT-REFNET-111 | B215: Kit de raccordement REFNET de différentes dimensions suivant plans | C215: BAT_PRINCIPAL | D215: GLOBAL | E215: FORFAIT | F215: 1 | G215: 46084 | H215: PNR_MEDICAL_CENTER | I215: FA_009 | J215: 690000 | K215: MATERIAU | M215: 1 | N215: 2.5 | P215: MANQUANT_CHINE | R215: 793500 | S215: 793500 | W215: LOCAL | X215: 8
A216: BPU-CLIM-TELECOM-IR-112 | B216: Télécommande à infrarouge pour les unités intérieures | C216: BAT_PRINCIPAL | D216: GLOBAL | E216: FORFAIT | F216: 62 | G216: 46084 | H216: PNR_MEDICAL_CENTER | I216: FA_009 | J216: 126500 | K216: MATERIAU | L216: 2745 | M216: 1 | N216: 2.5 | O216: 2745 | P216: PRIX_OK | Q216: 4313.493 | R216: 145475 | S216: 9019450 | T216: 267436.57 | U216: 8752013.4 | V216: 0.97034891 | W216: IMPORT | X216: 8 | Y216: 0.83220934
A217: BPU-CLIM-RACC-FRIGO-113 | B217: Raccordements frigorifiques y compris toutes sujétions | C217: BAT_PRINCIPAL | D217: GLOBAL | E217: FORFAIT | F217: 1 | G217: 46084 | H217: PNR_MEDICAL_CENTER | I217: FA_009 | J217: 1035000 | K217: MATERIAU | M217: 1 | N217: 2.5 | P217: MANQUANT_CHINE | R217: 1190250 | S217: 1190250 | W217: LOCAL | X217: 8
A218: BPU-CLIM-RACC-ELEC-114 | B218: Raccordements électriques et liaisons de communication | C218: BAT_PRINCIPAL | D218: GLOBAL | E218: FORFAIT | F218: 1 | G218: 46084 | H218: PNR_MEDICAL_CENTER | I218: FA_009 | J218: 1265000 | K218: MATERIAU | M218: 1 | N218: 2.5 | P218: MANQUANT_CHINE | R218: 1454750 | S218: 1454750 | W218: LOCAL | X218: 8
A219: BPU-CLIM-EVAC-COND-115 | B219: Evacuation des condensats | C219: BAT_PRINCIPAL | D219: GLOBAL | E219: FORFAIT | F219: 1 | G219: 46084 | H219: PNR_MEDICAL_CENTER | I219: FA_009 | J219: 1437500 | K219: MATERIAU | M219: 1 | N219: 2.5 | P219: MANQUANT_CHINE | R219: 1653125 | S219: 1653125 | W219: LOCAL | X219: 8
A220: BPU-CLIM-GAINE-SOUF-REPR-116 | B220: Gaine de soufflage et de reprise en laine de verre ou en acier galva ou équivalent y compris toutes sujétions | C220: BAT_PRINCIPAL | D220: GLOBAL | E220: FORFAIT | F220: 1 | G220: 46084 | H220: PNR_MEDICAL_CENTER | I220: FA_009 | J220: 13800000 | K220: MATERIAU | M220: 1 | N220: 2.5 | P220: MANQUANT_CHINE | R220: 15870000 | S220: 15870000 | W220: LOCAL | X220: 8
...

Sheet Fonction appelée
A1: Fonction appelée
A2: 0.18

Sheet ---05_FACT---

Sheet DIM_LOT
A1: LOT_ID | B1: CODE_LOT | C1: NOM_LOT | D1: DESCRIPTION_LOT | E1: ORDRE_LOT | F1: TYPE_LOT
A2: 1 | B2: L01 | C2: LOT 1 | D2: Gros œuvre et démolition | E2: 1 | F2: STRUCTURE
A3: 2 | B3: L02 | C3: LOT 2 | D3: Étanchéité | E3: 2 | F3: ARCHI
A4: 3 | B4: L03 | C4: LOT 3 | D4: Revêtement durs | E4: 3 | F4: ARCHI
A5: 4 | B5: L04 | C5: LOT 4 | D5: Menuiserie aluminium et vitrerie | E5: 4 | F5: ARCHI
A6: 5 | B6: L05 | C6: LOT 5 | D6: Menuiserie métallique et ferronnerie | E6: 5 | F6: ARCHI
A7: 6 | B7: L06 | C7: LOT 6 | D7: Menuiserie bois | E7: 6 | F7: ARCHI
A8: 7 | B8: L07 | C8: LOT 7 | D8: Electricité | E8: 7 | F8: TECH
A9: 8 | B9: L08 | C9: LOT 8 | D9: Climatisation | E9: 8 | F9: TECH
A10: 9 | B10: L09 | C10: LOT 9 | D10: Sécurité incendie et vidéo surveillance | E10: 9 | F10: TECH
A11: 10 | B11: L10 | C11: LOT 10 | D11: Plomberie sanitaire | E11: 10 | F11: TECH
A12: 11 | B12: L11 | C12: LOT 11 | D12: Faux plafond et cloisons BA13 | E12: 11 | F12: ARCHI
A13: 12 | B13: L12 | C13: L0T 12 | D13: Ascenseur | E13: 12 | F13: EQUIPEMENT
... A15: 14 | B15: L14 | C15: LOT 14 | D15: Peinture | E15: 14 | F15: FINITION

Sheet FACT_METRE
A1: PROJET_ID | B1: CODE_BPU | C1: LOT_ID | D1: FAM_ARTICLE_ID | E1: BATIMENT_ID | F1: NIVEAU_ID | G1: QTE | H1: MONTANT_LOCAL | I1: MONTANT_IMPORT | J1: DECISION | K1: NIVEAU_KEY
A2: PNR_MEDICAL_CENTER | B2: BPU-MEN-ALUM-BAIE-069 | C2: 4 | D2: FA_005 | E2: BAT_ANNEXE | F2: ETAGE 1 | G2: 19.2 | H2: 3047040 | I2: 1058243.6 | J2: IMPORT | K2: BAT_ANNEXE_ETAGE 1
A3: PNR_MEDICAL_CENTER | B3: BPU-MEN-ALUM-BAIE-069 | C3: 4 | D3: FA_005 | E3: BAT_ANNEXE | F3: ETAGE 1 | G3: 3.3 | H3: 523710 | I3: 181885.62 | J3: IMPORT | K3: BAT_ANNEXE_ETAGE 1
A4: PNR_MEDICAL_CENTER | B4: BPU-ETANCH-LOC-RELEV-058 | C4: 2 | D4: FA_002 | E4: BAT_ANNEXE | F4: ETAGE 1 | G4: 77.72 | H4: 772315.3 | J4: LOCAL | K4: BAT_ANNEXE_ETAGE 1
A5: PNR_MEDICAL_CENTER | B5: BPU-ETANCH-LOC-REV-MONO-057 | C5: 2 | D5: FA_002 | E5: BAT_ANNEXE | F5: ETAGE 1 | G5: 61.54 | H5: 1222639.8 | J5: LOCAL | K5: BAT_ANNEXE_ETAGE 1
A6: PNR_MEDICAL_CENTER | B6: BPU-MEN-ALUM-BAIE-069 | C6: 4 | D6: FA_005 | E6: BAT_ANNEXE | F6: ETAGE 1 | G6: 0.36 | H6: 57132 | I6: 19842.068 | J6: IMPORT | K6: BAT_ANNEXE_ETAGE 1
A7: PNR_MEDICAL_CENTER | B7: BPU-MEN-ALUM-BAIE-069 | C7: 4 | D7: FA_005 | E7: BAT_ANNEXE | F7: ETAGE 1 | G7: 12.47 | H7: 1978989 | I7: 687307.18 | J7: IMPORT | K7: BAT_ANNEXE_ETAGE 1
A8: PNR_MEDICAL_CENTER | B8: BPU-REVET-FAIENCE-GRANIT-065 | C8: 3 | D8: FA_004 | E8: BAT_ANNEXE | F8: ETAGE 1 | G8: 60.7 | H8: 1966755.9 | I8: 523658.05 | J8: IMPORT | K8: BAT_ANNEXE_ETAGE 1
A9: PNR_MEDICAL_CENTER | B9: BPU-MEN-ALUM-GARDE-CORPS-070 | C9: 4 | D9: FA_005 | E9: BAT_ANNEXE | F9: ETAGE 1 | G9: 28.18 | H9: 4472166 | I9: 1148012.2 | J9: IMPORT | K9: BAT_ANNEXE_ETAGE 1
A10: PNR_MEDICAL_CENTER | B10: BPU-DEMO-MUR-ESC-ET1-ANNEXE-009 | C10: 1 | D10: FA_001 | E10: BAT_ANNEXE | F10: ETAGE 1 | G10: 1 | H10: 2975625 | I10: 4065997.5 | J10: LOCAL | K10: BAT_ANNEXE_ETAGE 1
A11: PNR_MEDICAL_CENTER | B11: BPU-REVET-PLINTH-GRANIT-067 | C11: 3 | D11: FA_004 | E11: BAT_ANNEXE | F11: ETAGE 1 | G11: 192.38 | H11: 1272112.7 | I11: 829829.78 | J11: IMPORT | K11: BAT_ANNEXE_ETAGE 1
A12: PNR_MEDICAL_CENTER | B12: BPU-MEN-ALUM-BAIE-069 | C12: 4 | D12: FA_005 | E12: BAT_ANNEXE | F12: ETAGE 1 | G12: 8.89 | H12: 1410843 | I12: 489988.84 | J12: IMPORT | K12: BAT_ANNEXE_ETAGE 1
A13: PNR_MEDICAL_CENTER | B13: BPU-REVET-SOL-GRANIT-60X60-066 | C13: 3 | D13: FA_004 | E13: BAT_ANNEXE | F13: ETAGE 1 | G13: 210 | H13: 8192887.5 | I13: 3321389.6 | J13: IMPORT | K13: BAT_ANNEXE_ETAGE 1
A14: PNR_MEDICAL_CENTER | B14: BPU-MEN-ALUM-BAIE-069 | C14: 4 | D14: FA_005 | E14: BAT_ANNEXE | F14: ETAGE 1 | G14: 24.95 | H14: 3959565 | I14: 1375165.5 | J14: IMPORT | K14: BAT_ANNEXE_ETAGE 1
A15: PNR_MEDICAL_CENTER | B15: BPU-MEN-ALUM-BAIE-069 | C15: 4 | D15: FA_005 | E15: BAT_ANNEXE | F15: ETAGE 1 | G15: 5.28 | H15: 837936 | I15: 291016.99 | J15: IMPORT | K15: BAT_ANNEXE_ETAGE 1
A16: PNR_MEDICAL_CENTER | B16: BPU-MACON-ELEV-POT-BET-400-027 | C16: 1 | D16: FA_001 | E16: BAT_ANNEXE | F16: FONDATIONS | G16: 30.3 | H16: 6591802.9 | J16: LOCAL | K16: BAT_ANNEXE_FONDATIONS
A17: PNR_MEDICAL_CENTER | B17: BPU-MACON-ELEV-POT-AC-029 | C17: 1 | D17: FA_001 | E17: BAT_ANNEXE | F17: FONDATIONS | G17: 1818 | H17: 2885166 | J17: LOCAL | K17: BAT_ANNEXE_FONDATIONS
A18: PNR_MEDICAL_CENTER | B18: BPU-MACON-ELEV-POT-COF-028 | C18: 1 | D18: FA_001 | E18: BAT_ANNEXE | F18: FONDATIONS | G18: 10.8 | H18: 71415 | J18: LOCAL | K18: BAT_ANNEXE_FONDATIONS
A19: PNR_MEDICAL_CENTER | B19: BPU-ALUCOBOND-FP-184 | C19: 13 | D19: FA_003 | E19: BAT_ANNEXE | F19: GLOBAL | G19: 233.97 | H19: 47019196 | I19: 3588366.1 | J19: IMPORT | K19: BAT_ANNEXE_GLOBAL
A20: PNR_MEDICAL_CENTER | B20: BPU-REVET-FAIENCE-GRANIT-065 | C20: 3 | D20: FA_004 | E20: BAT_ANNEXE | F20: RDC | G20: 87.52 | H20: 2835757.4 | I20: 755033.81 | J20: IMPORT | K20: BAT_ANNEXE_RDC
A21: PNR_MEDICAL_CENTER | B21: BPU-MEN-ALUM-BAIE-069 | C21: 4 | D21: FA_005 | E21: BAT_ANNEXE | F21: RDC | G21: 1.44 | H21: 228528 | I21: 79368.271 | J21: IMPORT | K21: BAT_ANNEXE_RDC
A22: PNR_MEDICAL_CENTER | B22: BPU-MEN-ALUM-BAIE-069 | C22: 4 | D22: FA_005 | E22: BAT_ANNEXE | F22: RDC | G22: 0.36 | H22: 57132 | I22: 19842.068 | J22: IMPORT | K22: BAT_ANNEXE_RDC
A23: PNR_MEDICAL_CENTER | B23: BPU-REVET-FAIENCE-GRANIT-065 | C23: 3 | D23: FA_004 | E23: BAT_ANNEXE | F23: RDC | G23: 56.71 | H23: 1837474.9 | I23: 489236.38 | J23: IMPORT | K23: BAT_ANNEXE_RDC
A24: PNR_MEDICAL_CENTER | B24: BPU-REVET-PLAN-TRAV-GRANIT-068 | C24: 3 | D24: FA_004 | E24: BAT_ANNEXE | F24: RDC | G24: 5.19 | H24: 3088698.8 | I24: 348242.67 | J24: IMPORT | K24: BAT_ANNEXE_RDC
A25: PNR_MEDICAL_CENTER | B25: BPU-REVET-SOL-GRANIT-60X60-066 | C25: 3 | D25: FA_004 | E25: BAT_ANNEXE | F25: RDC | G25: 210 | H25: 8192887.5 | I25: 3321389.6 | J25: IMPORT | K25: BAT_ANNEXE_RDC
A26: PNR_MEDICAL_CENTER | B26: BPU-REVET-PLINTH-GRANIT-067 | C26: 3 | D26: FA_004 | E26: BAT_ANNEXE | F26: RDC | G26: 119.94 | H26: 793103.25 | I26: 517360.35 | J26: IMPORT | K26: BAT_ANNEXE_RDC
A27: PNR_MEDICAL_CENTER | B27: BPU-MEN-ALUM-BAIE-069 | C27: 4 | D27: FA_005 | E27: BAT_ANNEXE | F27: RDC | G27: 6.6 | H27: 1047420 | I27: 363771.24 | J27: IMPORT | K27: BAT_ANNEXE_RDC
A28: PNR_MEDICAL_CENTER | B28: BPU-MEN-ALUM-BAIE-069 | C28: 4 | D28: FA_005 | E28: BAT_ANNEXE | F28: RDC | G28: 0.96 | H28: 152352 | I28: 52912.181 | J28: IMPORT | K28: BAT_ANNEXE_RDC
A29: PNR_MEDICAL_CENTER | B29: BPU-MEN-ALUM-BAIE-069 | C29: 4 | D29: FA_005 | E29: BAT_ANNEXE | F29: RDC | G29: 5.28 | H29: 837936 | I29: 291016.99 | J29: IMPORT | K29: BAT_ANNEXE_RDC
A30: PNR_MEDICAL_CENTER | B30: BPU-MEN-BOIS-ETAGERE-CUISINE-SUP-079 | C30: 6 | D30: FA_005 | E30: BAT_ANNEXE | F30: RDC | G30: 2.94 | H30: 1166445 | I30: 190225.04 | J30: IMPORT | K30: BAT_ANNEXE_RDC
... A39: PNR_MEDICAL_CENTER | B39: BPU-MEN-BOIS-ETAGERE-CUISINE-INF-080 | C39: 6 | D39: FA_005 | E39: BAT_PRINCIPAL | F39: DUPLEX 1 | G39: 3.36 | H39: 1555260 | I39: 249607.46 | J39: IMPORT | K39: BAT_PRINCIPAL_DUPLEX 1
A40: PNR_MEDICAL_CENTER | B40: BPU-MACON-ELEV-VOILE-BET-350-053 | C40: 1 | D40: FA_001 | E40: BAT_PRINCIPAL | F40: DUPLEX 1 | G40: 21.9 | H40: 4764372.4 | J40: LOCAL | K40: BAT_PRINCIPAL_DUPLEX 1
A41: PNR_MEDICAL_CENTER | B41: BPU-FP-STAFF-LISSE-181 | C41: 11 | D41: FA_012 | E41: BAT_PRINCIPAL | F41: DUPLEX 1 | G41: 182 | H41: 4813900 | J41: LOCAL | K41: BAT_PRINCIPAL_DUPLEX 1
A42: PNR_MEDICAL_CENTER | B42: BPU-FP-CORNICHE-182 | C42: 11 | D42: FA_012 | E42: BAT_PRINCIPAL | F42: DUPLEX 1 | G42: 172.84 | H42: 1142904.5 | J42: LOCAL | K42: BAT_PRINCIPAL_DUPLEX 1
A43: PNR_MEDICAL_CENTER | B43: BPU-PEINT-MURS-PREP-SURF-185 | C43: 14 | D43: FA_014 | E43: BAT_PRINCIPAL | F43: DUPLEX 1 | G43: 415.08 | H43: 274471.65 | I43: 375047.61 | J43: LOCAL | K43: BAT_PRINCIPAL_DUPLEX 1
A44: PNR_MEDICAL_CENTER | B44: BPU-PEINT-MURS-INT-PANTEX-186 | C44: 14 | D44: FA_014 | E44: BAT_PRINCIPAL | F44: DUPLEX 1 | G44: 415.08 | H44: 3019188.1 | I44: 4125523.7 | J44: LOCAL | K44: BAT_PRINCIPAL_DUPLEX 1
A45: PNR_MEDICAL_CENTER | B45: BPU-MACON-ELEV-VOILE-COF-054 | C45: 1 | D45: FA_001 | E45: BAT_PRINCIPAL | F45: DUPLEX 1 | G45: 101.18 | H45: 669052.75 | J45: LOCAL | K45: BAT_PRINCIPAL_DUPLEX 1
A46: PNR_MEDICAL_CENTER | B46: BPU-MACON-ELEV-VOILE-AC-055 | C46: 1 | D46: FA_001 | E46: BAT_PRINCIPAL | F46: DUPLEX 1 | G46: 2628 | H46: 4170636 | J46: LOCAL | K46: BAT_PRINCIPAL_DUPLEX 1
A47: PNR_MEDICAL_CENTER | B47: BPU-ETANCH-LOC-REV-MONO-057 | C47: 2 | D47: FA_002 | E47: BAT_PRINCIPAL | F47: DUPLEX 1 | G47: 24.95 | H47: 495691.63 | J47: LOCAL | K47: BAT_PRINCIPAL_DUPLEX 1
A48: PNR_MEDICAL_CENTER | B48: BPU-MEN-BOIS-PORTE-MDF-078 | C48: 6 | D48: FA_005 | E48: BAT_PRINCIPAL | F48: DUPLEX 1 | G48: 7 | H48: 2749477.5 | I48: 385817.99 | J48: IMPORT | K48: BAT_PRINCIPAL_DUPLEX 1
A49: PNR_MEDICAL_CENTER | B49: BPU-ETANCH-LOC-RELEV-058 | C49: 2 | D49: FA_002 | E49: BAT_PRINCIPAL | F49: DUPLEX 1 | G49: 56.14 | H49: 557871.6 | J49: LOCAL | K49: BAT_PRINCIPAL_DUPLEX 1
A50: PNR_MEDICAL_CENTER | B50: BPU-MEN-BOIS-PLACARD-077 | C50: 6 | D50: FA_005 | E50: BAT_PRINCIPAL | F50: DUPLEX 1 | G50: 1 | H50: 872850 | I50: 239638.5 | J50: IMPORT | K50: BAT_PRINCIPAL_DUPLEX 1
A51: PNR_MEDICAL_CENTER | B51: BPU-MEN-ALUM-BAIE-069 | C51: 4 | D51: FA_005 | E51: BAT_PRINCIPAL | F51: DUPLEX 1 | G51: 14.4 | H51: 2285280 | I51: 793682.71 | J51: IMPORT | K51: BAT_PRINCIPAL_DUPLEX 1
A52: PNR_MEDICAL_CENTER | B52: BPU-MEN-ALUM-BAIE-069 | C52: 4 | D52: FA_005 | E52: BAT_PRINCIPAL | F52: DUPLEX 1 | G52: 13.2 | H52: 2094840 | I52: 727542.49 | J52: IMPORT | K52: BAT_PRINCIPAL_DUPLEX 1
A53: PNR_MEDICAL_CENTER | B53: BPU-MEN-ALUM-BAIE-069 | C53: 4 | D53: FA_005 | E53: BAT_PRINCIPAL | F53: DUPLEX 1 | G53: 9 | H53: 1428300 | I53: 496051.7 | J53: IMPORT | K53: BAT_PRINCIPAL_DUPLEX 1
A54: PNR_MEDICAL_CENTER | B54: BPU-MEN-ALUM-BAIE-069 | C54: 4 | D54: FA_005 | E54: BAT_PRINCIPAL | F54: DUPLEX 1 | G54: 1.2 | H54: 190440 | I54: 66140.226 | J54: IMPORT | K54: BAT_PRINCIPAL_DUPLEX 1
A55: PNR_MEDICAL_CENTER | B55: BPU-MEN-ALUM-BAIE-069 | C55: 4 | D55: FA_005 | E55: BAT_PRINCIPAL | F55: DUPLEX 1 | G55: 2.16 | H55: 342792 | I55: 119052.41 | J55: IMPORT | K55: BAT_PRINCIPAL_DUPLEX 1
A56: PNR_MEDICAL_CENTER | B56: BPU-MEN-ALUM-BAIE-069 | C56: 4 | D56: FA_005 | E56: BAT_PRINCIPAL | F56: DUPLEX 1 | G56: 13.2 | H56: 2094840 | I56: 727542.49 | J56: IMPORT | K56: BAT_PRINCIPAL_DUPLEX 1
A57: PNR_MEDICAL_CENTER | B57: BPU-MEN-BOIS-PLACARD-077 | C57: 6 | D57: FA_005 | E57: BAT_PRINCIPAL | F57: DUPLEX 1 | G57: 2 | H57: 1745700 | I57: 479277 | J57: IMPORT | K57: BAT_PRINCIPAL_DUPLEX 1
A58: PNR_MEDICAL_CENTER | B58: BPU-MEN-ALUM-GARDE-CORPS-070 | C58: 4 | D58: FA_005 | E58: BAT_PRINCIPAL | F58: DUPLEX 1 | G58: 45.22 | H58: 7176414 | I58: 1842197 | J58: IMPORT | K58: BAT_PRINCIPAL_DUPLEX 1
A59: PNR_MEDICAL_CENTER | B59: BPU-PEINT-PLAF-PREP-SURF-187 | C59: 14 | D59: FA_014 | E59: BAT_PRINCIPAL | F59: DUPLEX 1 | G59: 182 | H59: 120347.5 | I59: 164447.01 | J59: LOCAL | K59: BAT_PRINCIPAL_DUPLEX 1
A60: PNR_MEDICAL_CENTER | B60: BPU-MACON-FIN-TABL-056 | C60: 1 | D60: FA_001 | E60: BAT_PRINCIPAL | F60: DUPLEX 1 | G60: 1 | H60: 2695797.8 | J60: LOCAL | K60: BAT_PRINCIPAL_DUPLEX 1
A61: PNR_MEDICAL_CENTER | B61: BPU-REVET-PLINTH-GRANIT-067 | C61: 3 | D61: FA_004 | E61: BAT_PRINCIPAL | F61: DUPLEX 1 | G61: 300.82 | H61: 1989172.2 | I61: 1297585 | J61: IMPORT | K61: BAT_PRINCIPAL_DUPLEX 1
A62: PNR_MEDICAL_CENTER | B62: BPU-PEINT-PLAF-INT-PANTEX-188 | C62: 14 | D62: FA_014 | E62: BAT_PRINCIPAL | F62: DUPLEX 1 | G62: 182 | H62: 1323822.5 | I62: 1808917.1 | J62: LOCAL | K62: BAT_PRINCIPAL_DUPLEX 1
A63: PNR_MEDICAL_CENTER | B63: BPU-ETANCH-TERR-INACC-FORME-062 | C63: 2 | D63: FA_002 | E63: BAT_PRINCIPAL | F63: DUPLEX 1 | G63: 56.75 | H63: 769640.66 | I63: 1051663.8 | J63: LOCAL | K63: BAT_PRINCIPAL_DUPLEX 1
A64: PNR_MEDICAL_CENTER | B64: BPU-REVET-FAIENCE-GRANIT-065 | C64: 3 | D64: FA_004 | E64: BAT_PRINCIPAL | F64: DUPLEX 1 | G64: 162.06 | H64: 5250946.6 | I64: 1398089.4 | J64: IMPORT | K64: BAT_PRINCIPAL_DUPLEX 1
A65: PNR_MEDICAL_CENTER | B65: BPU-REVET-SOL-GRANIT-60X60-066 | C65: 3 | D65: FA_004 | E65: BAT_PRINCIPAL | F65: DUPLEX 1 | G65: 557 | H65: 21730659 | I65: 8809590.5 | J65: IMPORT | K65: BAT_PRINCIPAL_DUPLEX 1
A66: PNR_MEDICAL_CENTER | B66: BPU-ETANCH-TERR-INACC-RELEV-064 | C66: 2 | D66: FA_002 | E66: BAT_PRINCIPAL | F66: DUPLEX 1 | G66: 36 | H66: 357737.4 | I66: 172539.72 | J66: IMPORT | K66: BAT_PRINCIPAL_DUPLEX 1
A67: PNR_MEDICAL_CENTER | B67: BPU-ETANCH-TERR-INACC-MONO-063 | C67: 2 | D67: FA_002 | E67: BAT_PRINCIPAL | F67: DUPLEX 1 | G67: 56.75 | H67: 1127474.9 | I67: 407984.55 | J67: IMPORT | K67: BAT_PRINCIPAL_DUPLEX 1
A68: PNR_MEDICAL_CENTER | B68: BPU-ETANCH-TERR-ACC-RELEV-061 | C68: 2 | D68: FA_002 | E68: BAT_PRINCIPAL | F68: DUPLEX 1 | G68: 120 | H68: 1192458 | I68: 575132.4 | J68: IMPORT | K68: BAT_PRINCIPAL_DUPLEX 1
A69: PNR_MEDICAL_CENTER | B69: BPU-ETANCH-TERR-ACC-BI-060 | C69: 2 | D69: FA_002 | E69: BAT_PRINCIPAL | F69: DUPLEX 1 | G69: 320 | H69: 12715136 | I69: 3067372.8 | J69: IMPORT | K69: BAT_PRINCIPAL_DUPLEX 1
A70: PNR_MEDICAL_CENTER | B70: BPU-ETANCH-TERR-ACC-FORME-059 | C70: 2 | D70: FA_002 | E70: BAT_PRINCIPAL | F70: DUPLEX 1 | G70: 320 | H70: 4339824 | I70: 5930086.5 | J70: LOCAL | K70: BAT_PRINCIPAL_DUPLEX 1
A71: PNR_MEDICAL_CENTER | B71: BPU-ETANCH-LOC-RELEV-058 | C71: 2 | D71: FA_002 | E71: BAT_PRINCIPAL | F71: DUPLEX 2 | G71: 89.96 | H71: 893946.01 | J71: LOCAL | K71: BAT_PRINCIPAL_DUPLEX 2
A72: PNR_MEDICAL_CENTER | B72: BPU-ETANCH-LOC-REV-MONO-057 | C72: 2 | D72: FA_002 | E72: BAT_PRINCIPAL | F72: DUPLEX 2 | G72: 55.52 | H72: 1103038 | J72: LOCAL | K72: BAT_PRINCIPAL_DUPLEX 2
A73: PNR_MEDICAL_CENTER | B73: BPU-REVET-FAIENCE-GRANIT-065 | C73: 3 | D73: FA_004 | E73: BAT_PRINCIPAL | F73: DUPLEX 2 | G73: 99.33 | H73: 3218416.2 | I73: 856918.52 | J73: IMPORT | K73: BAT_PRINCIPAL_DUPLEX 2
A74: PNR_MEDICAL_CENTER | B74: BPU-MEN-ALUM-BAIE-069 | C74: 4 | D74: FA_005 | E74: BAT_PRINCIPAL | F74: DUPLEX 2 | G74: 7.2 | H74: 1142640 | I74: 396841.36 | J74: IMPORT | K74: BAT_PRINCIPAL_DUPLEX 2
A75: PNR_MEDICAL_CENTER | B75: BPU-MEN-ALUM-BAIE-069 | C75: 4 | D75: FA_005 | E75: BAT_PRINCIPAL | F75: DUPLEX 2 | G75: 5.4 | H75: 856980 | I75: 297631.02 | J75: IMPORT | K75: BAT_PRINCIPAL_DUPLEX 2
A76: PNR_MEDICAL_CENTER | B76: BPU-MEN-ALUM-BAIE-069 | C76: 4 | D76: FA_005 | E76: BAT_PRINCIPAL | F76: DUPLEX 2 | G76: 1.08 | H76: 171396 | I76: 59526.203 | J76: IMPORT | K76: BAT_PRINCIPAL_DUPLEX 2
A77: PNR_MEDICAL_CENTER | B77: BPU-MEN-ALUM-BAIE-069 | C77: 4 | D77: FA_005 | E77: BAT_PRINCIPAL | F77: DUPLEX 2 | G77: 0.72 | H77: 114264 | I77: 39684.136 | J77: IMPORT | K77: BAT_PRINCIPAL_DUPLEX 2
A78: PNR_MEDICAL_CENTER | B78: BPU-MEN-ALUM-BAIE-069 | C78: 4 | D78: FA_005 | E78: BAT_PRINCIPAL | F78: DUPLEX 2 | G78: 13.2 | H78: 2094840 | I78: 727542.49 | J78: IMPORT | K78: BAT_PRINCIPAL_DUPLEX 2
A79: PNR_MEDICAL_CENTER | B79: BPU-MEN-ALUM-BAIE-069 | C79: 4 | D79: FA_005 | E79: BAT_PRINCIPAL | F79: DUPLEX 2 | G79: 9.6 | H79: 1523520 | I79: 529121.81 | J79: IMPORT | K79: BAT_PRINCIPAL_DUPLEX 2
A80: PNR_MEDICAL_CENTER | B80: BPU-MEN-ALUM-GARDE-CORPS-070 | C80: 4 | D80: FA_005 | E80: BAT_PRINCIPAL | F80: DUPLEX 2 | G80: 26.88 | H80: 4265856 | I80: 1095052.1 | J80: IMPORT | K80: BAT_PRINCIPAL_DUPLEX 2
A81: PNR_MEDICAL_CENTER | B81: BPU-REVET-PLINTH-GRANIT-067 | C81: 3 | D81: FA_004 | E81: BAT_PRINCIPAL | F81: DUPLEX 2 | G81: 172.84 | H81: 1142904.5 | I81: 745544.13 | J81: IMPORT | K81: BAT_PRINCIPAL_DUPLEX 2
A82: PNR_MEDICAL_CENTER | B82: BPU-MEN-BOIS-PORTE-MDF-078 | C82: 6 | D82: FA_005 | E82: BAT_PRINCIPAL | F82: DUPLEX 2 | G82: 4 | H82: 1571130 | I82: 220467.42 | J82: IMPORT | K82: BAT_PRINCIPAL_DUPLEX 2
A83: PNR_MEDICAL_CENTER | B83: BPU-REVET-SOL-GRANIT-60X60-066 | C83: 3 | D83: FA_004 | E83: BAT_PRINCIPAL | F83: DUPLEX 2 | G83: 182 | H83: 7100502.5 | I83: 2878537.7 | J83: IMPORT | K83: BAT_PRINCIPAL_DUPLEX 2
A84: PNR_MEDICAL_CENTER | B84: BPU-MEN-BOIS-PLACARD-077 | C84: 6 | D84: FA_005 | E84: BAT_PRINCIPAL | F84: DUPLEX 2 | G84: 2 | H84: 1745700 | I84: 479277 | J84: IMPORT | K84: BAT_PRINCIPAL_DUPLEX 2
A85: PNR_MEDICAL_CENTER | B85: BPU-MEN-BOIS-PLACARD-077 | C85: 6 | D85: FA_005 | E85: BAT_PRINCIPAL | F85: DUPLEX 2 | G85: 2 | H85: 1745700 | I85: 479277 | J85: IMPORT | K85: BAT_PRINCIPAL_DUPLEX 2
A86: PNR_MEDICAL_CENTER | B86: BPU-FP-STAFF-LISSE-181 | C86: 11 | D86: FA_012 | E86: BAT_PRINCIPAL | F86: DUPLEX 2 | G86: 182 | H86: 4813900 | J86: LOCAL | K86: BAT_PRINCIPAL_DUPLEX 2
A87: PNR_MEDICAL_CENTER | B87: BPU-FP-CORNICHE-182 | C87: 11 | D87: FA_012 | E87: BAT_PRINCIPAL | F87: DUPLEX 2 | G87: 172.84 | H87: 1142904.5 | J87: LOCAL | K87: BAT_PRINCIPAL_DUPLEX 2
A88: PNR_MEDICAL_CENTER | B88: BPU-MEN-BOIS-PLACARD-077 | C88: 6 | D88: FA_005 | E88: BAT_PRINCIPAL | F88: ETAGE 1 | G88: 1 | H88: 872850 | I88: 239638.5 | J88: IMPORT | K88: BAT_PRINCIPAL_ETAGE 1
A89: PNR_MEDICAL_CENTER | B89: BPU-MEN-ALUM-BAIE-069 | C89: 4 | D89: FA_005 | E89: BAT_PRINCIPAL | F89: ETAGE 1 | G89: 7.92 | H89: 1256904 | I89: 436525.49 | J89: IMPORT | K89: BAT_PRINCIPAL_ETAGE 1
A90: PNR_MEDICAL_CENTER | B90: BPU-MEN-ALUM-BAIE-069 | C90: 4 | D90: FA_005 | E90: BAT_PRINCIPAL | F90: ETAGE 1 | G90: 17.28 | H90: 2742336 | I90: 952419.25 | J90: IMPORT | K90: BAT_PRINCIPAL_ETAGE 1
A91: PNR_MEDICAL_CENTER | B91: BPU-MEN-ALUM-BAIE-069 | C91: 4 | D91: FA_005 | E91: BAT_PRINCIPAL | F91: ETAGE 1 | G91: 1.2 | H91: 190440 | I91: 66140.226 | J91: IMPORT | K91: BAT_PRINCIPAL_ETAGE 1
A92: PNR_MEDICAL_CENTER | B92: BPU-MEN-ALUM-BAIE-069 | C92: 4 | D92: FA_005 | E92: BAT_PRINCIPAL | F92: ETAGE 1 | G92: 2.52 | H92: 399924 | I92: 138894.47 | J92: IMPORT | K92: BAT_PRINCIPAL_ETAGE 1
A93: PNR_MEDICAL_CENTER | B93: BPU-MEN-ALUM-BAIE-069 | C93: 4 | D93: FA_005 | E93: BAT_PRINCIPAL | F93: ETAGE 1 | G93: 33 | H93: 5237100 | I93: 1818856.2 | J93: IMPORT | K93: BAT_PRINCIPAL_ETAGE 1
A94: PNR_MEDICAL_CENTER | B94: BPU-MEN-ALUM-BAIE-069 | C94: 4 | D94: FA_005 | E94: BAT_PRINCIPAL | F94: ETAGE 1 | G94: 39.6 | H94: 6284520 | I94: 2182627.5 | J94: IMPORT | K94: BAT_PRINCIPAL_ETAGE 1
A95: PNR_MEDICAL_CENTER | B95: BPU-MEN-ALUM-BAIE-069 | C95: 4 | D95: FA_005 | E95: BAT_PRINCIPAL | F95: ETAGE 1 | G95: 28.16 | H95: 4468992 | I95: 1552090.6 | J95: IMPORT | K95: BAT_PRINCIPAL_ETAGE 1
A96: PNR_MEDICAL_CENTER | B96: BPU-MEN-ALUM-BAIE-069 | C96: 4 | D96: FA_005 | E96: BAT_PRINCIPAL | F96: ETAGE 1 | G96: 8.94 | H96: 1418778 | I96: 492744.68 | J96: IMPORT | K96: BAT_PRINCIPAL_ETAGE 1
A97: PNR_MEDICAL_CENTER | B97: BPU-MEN-ALUM-GARDE-CORPS-070 | C97: 4 | D97: FA_005 | E97: BAT_PRINCIPAL | F97: ETAGE 1 | G97: 32.4 | H97: 5141880 | I97: 1319928.9 | J97: IMPORT | K97: BAT_PRINCIPAL_ETAGE 1
A98: PNR_MEDICAL_CENTER | B98: BPU-MEN-BOIS-PLACARD-077 | C98: 6 | D98: FA_005 | E98: BAT_PRINCIPAL | F98: ETAGE 1 | G98: 1 | H98: 872850 | I98: 239638.5 | J98: IMPORT | K98: BAT_PRINCIPAL_ETAGE 1
A99: PNR_MEDICAL_CENTER | B99: BPU-MEN-BOIS-PLACARD-077 | C99: 6 | D99: FA_005 | E99: BAT_PRINCIPAL | F99: ETAGE 1 | G99: 1 | H99: 872850 | I99: 239638.5 | J99: IMPORT | K99: BAT_PRINCIPAL_ETAGE 1
... A106: PNR_MEDICAL_CENTER | B106: BPU-REVET-FAIENCE-GRANIT-065 | C106: 3 | D106: FA_004 | E106: BAT_PRINCIPAL | F106: ETAGE 1 | G106: 351.33 | H106: 11383531 | I106: 3030919 | J106: IMPORT | K106: BAT_PRINCIPAL_ETAGE 1
A107: PNR_MEDICAL_CENTER | B107: BPU-ETANCH-LOC-RELEV-058 | C107: 2 | D107: FA_002 | E107: BAT_PRINCIPAL | F107: ETAGE 1 | G107: 182.88 | H107: 1817306 | J107: LOCAL | K107: BAT_PRINCIPAL_ETAGE 1
A108: PNR_MEDICAL_CENTER | B108: BPU-FP-CLOISON-BA13-LV-180 | C108: 11 | D108: FA_012 | E108: BAT_PRINCIPAL | F108: ETAGE 1 | G108: 60.74 | H108: 2731174.1 | J108: LOCAL | K108: BAT_PRINCIPAL_ETAGE 1
A109: PNR_MEDICAL_CENTER | B109: BPU-ETANCH-LOC-REV-MONO-057 | C109: 2 | D109: FA_002 | E109: BAT_PRINCIPAL | F109: ETAGE 1 | G109: 107.66 | H109: 2138924.3 | J109: LOCAL | K109: BAT_PRINCIPAL_ETAGE 1
A110: PNR_MEDICAL_CENTER | B110: BPU-PEINT-MURS-PREP-SURF-185 | C110: 14 | D110: FA_014 | E110: BAT_PRINCIPAL | F110: ETAGE 1 | G110: 1649 | H110: 1090401.2 | I110: 1489962.2 | J110: LOCAL | K110: BAT_PRINCIPAL_ETAGE 1
A111: PNR_MEDICAL_CENTER | B111: BPU-PEINT-MURS-INT-PANTEX-186 | C111: 14 | D111: FA_014 | E111: BAT_PRINCIPAL | F111: ETAGE 1 | G111: 1649 | H111: 11994414 | I111: 16389584 | J111: LOCAL | K111: BAT_PRINCIPAL_ETAGE 1
A112: PNR_MEDICAL_CENTER | B112: BPU-PEINT-PLAF-PREP-SURF-187 | C112: 14 | D112: FA_014 | E112: BAT_PRINCIPAL | F112: ETAGE 1 | G112: 804 | H112: 531645 | I112: 726458.22 | J112: LOCAL | K112: BAT_PRINCIPAL_ETAGE 1
A113: PNR_MEDICAL_CENTER | B113: BPU-REVET-SOL-GRANIT-60X60-066 | C113: 3 | D113: FA_004 | E113: BAT_PRINCIPAL | F113: ETAGE 1 | G113: 594 | H113: 23174168 | I113: 9394787.8 | J113: IMPORT | K113: BAT_PRINCIPAL_ETAGE 1
A114: PNR_MEDICAL_CENTER | B114: BPU-MEN-ALUM-BAIE-069 | C114: 4 | D114: FA_005 | E114: BAT_PRINCIPAL | F114: ETAGE 2 | G114: 12.32 | H114: 1955184 | I114: 679039.65 | J114: IMPORT | K114: BAT_PRINCIPAL_ETAGE 2
...

Sheet --------06_DIM---------

Sheet DIM_FAM_METIER 
A1: FAM_METIER_ID | B1: CODE_FAM_METIER | C1: LIBELLE_FAM_METIER | D1: ACTIF
A2: FM_01 | B2: STRUCTURE | C2: Structure | D2: 1
A3: FM_02 | B3: ENVELOPPE | C3: Enveloppe | D3: 1
A4: FM_03 | B4: SECOND_OEUVRE | C4: Second Œuvre | D4: 1
A5: FM_04 | B5: LOTS_TECHNIQUES | C5: Lots Techniques | D5: 1

Sheet DIM_FAM_ARTICLE
A1: FAM_ARTICLE_ID | B1: CODE_FAM_ARTICLE | C1: LIBELLE_FAM_ARTICLE | D1: FAM_METIER_ID | E1: IMPORTABLE | F1: TAUX_MAIN_OEUVRE | G1: RISQUE_IMPORT
A2: FA_001 | B2: GROS_OEUVRE | C2: Gros Œuvre & Démolition | D2: FM_01 | E2: 0 | F2: 0.4 | G2: 0
A3: FA_002 | B3: ETANCHEITE | C3: Étanchéité | D3: FM_02 | E3: 1 | F3: 0.3 | G3: 1
A4: FA_003 | B4: ALUCOBOND | C4: Alucobond – Bardage Façade | D4: FM_02 | E4: 1 | F4: 0.2 | G4: 2
A5: FA_004 | B5: REVETEMENTS_DURS | C5: Revêtements Durs | D5: FM_03 | E5: 1 | F5: 0.2 | G5: 2
A6: FA_005 | B6: MENUISERIE_ALU | C6: Menuiserie Aluminium & Vitrerie | D6: FM_03 | E6: 1 | F6: 0.25 | G6: 2
A7: FA_006 | B7: MENUISERIE_MET | C7: Menuiserie Métallique | D7: FM_03 | E7: 1 | F7: 0.3 | G7: 2
A8: FA_007 | B8: MENUISERIE_BOIS | C8: Menuiserie Bois | D8: FM_03 | E8: 1 | F8: 0.2 | G8: 2
A9: FA_008 | B9: ELECTRICITE | C9: Électricité | D9: FM_04 | E9: 1 | F9: 0.15 | G9: 3
A10: FA_009 | B10: CLIMATISATION | C10: Climatisation | D10: FM_04 | E10: 1 | F10: 0.1 | G10: 2.5
A11: FA_010 | B11: SECURITE_INCENDIE | C11: Sécurité Incendie & Vidéo | D11: FM_04 | E11: 1 | F11: 0.25 | G11: 2
A12: FA_011 | B12: PLOMBERIE | C12: Plomberie Sanitaire | D12: FM_04 | E12: 1 | F12: 0.2 | G12: 1.5
A13: FA_012 | B13: FAUX_PLAFONDS | C13: Faux Plafonds & Cloisons | D13: FM_03 | E13: 1 | F13: 0.1 | G13: 3.5
... A18: FA_017 | B18: GROUPE_ELECTROGENE | C18: Groupe Électrogène | D18: FM_04 | E18: 1 | F18: 0.1 | G18: 3

Sheet DIM_NIVEAU
A1: PROJET_ID | B1: BATIMENT_ID | C1: NIVEAU_ID | D1: NIVEAU_KEY | E1: ORDRE_NIVEAU
A2: PNR_MEDICAL_CENTER | B2: BAT_ANNEXE | C2: FONDATIONS | D2: BAT_ANNEXE_FONDATIONS | E2: 0
A3: PNR_MEDICAL_CENTER | B3: BAT_ANNEXE | C3: RDC | D3: BAT_ANNEXE_RDC | E3: 1
A4: PNR_MEDICAL_CENTER | B4: BAT_ANNEXE | C4: ETAGE 1 | D4: BAT_ANNEXE_ETAGE 1 | E4: 2
A5: PNR_MEDICAL_CENTER | B5: BAT_ANNEXE | C5: TERRASSE | D5: BAT_ANNEXE_TERRASSE | E5: 4
A6: PNR_MEDICAL_CENTER | B6: BAT_ANNEXE | C6: GLOBAL | D6: BAT_ANNEXE_GLOBAL | E6: 99
A7: PNR_MEDICAL_CENTER | B7: BAT_PRINCIPAL | C7: FONDATIONS | D7: BAT_PRINCIPAL_FONDATIONS | E7: 0
A8: PNR_MEDICAL_CENTER | B8: BAT_PRINCIPAL | C8: RDC | D8: BAT_PRINCIPAL_RDC | E8: 1
A9: PNR_MEDICAL_CENTER | B9: BAT_PRINCIPAL | C9: ETAGE 1 | D9: BAT_PRINCIPAL_ETAGE 1 | E9: 2
A10: PNR_MEDICAL_CENTER | B10: BAT_PRINCIPAL | C10: ETAGE 2 | D10: BAT_PRINCIPAL_ETAGE 2 | E10: 3
A11: PNR_MEDICAL_CENTER | B11: BAT_PRINCIPAL | C11: TERRASSE | D11: BAT_PRINCIPAL_TERRASSE | E11: 4
A12: PNR_MEDICAL_CENTER | B12: BAT_PRINCIPAL | C12: DUPLEX 1 | D12: BAT_PRINCIPAL_DUPLEX 1 | E12: 5
A13: PNR_MEDICAL_CENTER | B13: BAT_PRINCIPAL | C13: DUPLEX 2 | D13: BAT_PRINCIPAL_DUPLEX 2 | E13: 5
A14: PNR_MEDICAL_CENTER | B14: BAT_PRINCIPAL | C14: GLOBAL | D14: BAT_PRINCIPAL_GLOBAL | E14: 99

Sheet DIM_BATIMENT
A1: BATIMENT_ID | B1: NOM_BATIMENT | C1: PROJET_ID | D1: ORDRE_AFFICHAGE | E1: TYPE_BATIMENT
A2: BAT_ANNEXE | B2: Bâtiment Annexe | C2: PNR_MEDICAL_CENTER | D2: 0 | E2: BATIMENT_TECHNIQUE
A3: BAT_PRINCIPAL | B3: Bâtiment Principal | C3: PNR_MEDICAL_CENTER | D3: 1 | E3: BATIMENT_MEDICAL
A4: BAT_SITE | B4: Site / Aménagement extérieur | C4: PNR_MEDICAL_CENTER | D4: 99 | E4: INFRASTRUCTURE_SITE

Sheet 05_DM_LOT
A1: LOT | B1: NOM_LOT | C1: FAM_ARTICLE_ID | D1: NB_ARTICLES | E1: TOTAL_LOCAL | F1: TOTAL_CHINE | G1: GAIN | H1: TAUX_GAIN | I1: NB_IMPORT | J1: NB_LOCAL | K1: TAUX_IMPORT
A2: Lot 1 | B2: Gros Œuvre et Démolition | C2: FA_001 | D2: 142 | E2: 2.0945185e+08 | F2: 2.0945185e+08 | G2: 0 | H2: 0 | I2: 0 | J2: 142 | K2: 0
A3: Lot 2 | B3: Étanchéité | C3: FA_002 | D3: 2 | E3: 7302400 | F3: 2900100 | G3: 4402300 | H3: 0.6028566 | I3: 2 | J3: 0 | K3: 1
A4: Lot 3 | B4: Revêtements Durs | C4: FA_004 | D4: 6 | E4: 1.5929048e+08 | F4: 119132500 | G4: 40157978 | H4: 0.25210533 | I4: 6 | J4: 0 | K4: 1
A5: Lot 4 | B5: Menuiserie Aluminium et Vitrerie | C5: FA_005 | D5: 39 | E5: 43886340 | F5: 30723519 | G5: 13162821 | H5: 0.2999298 | I5: 30 | J5: 9 | K5: 0.76923077
A6: Lot 5 | B6: Menuiserie Métallique | C6: FA_006 | D6: 2 | E6: 575000 | F6: 402500 | G6: 172500 | H6: 0.3 | I6: 2 | J6: 0 | K6: 1
A7: Lot 6 | B7: Menuiserie Bois | C7: FA_007 | D7: 4 | E7: 4008900 | F7: 2605785 | G7: 1403115 | H7: 0.35 | I7: 4 | J7: 0 | K7: 1
A8: Lot 7 | B8: Électricité | C8: FA_008 | D8: 55 | E8: 68801225 | F8: 45971000 | G8: 22830225 | H8: 0.33182876 | I8: 53 | J8: 2 | K8: 0.96363636
A9: Lot 8 | B9: Climatisation | C9: FA_009 | D9: 6 | E9: 16699510 | F9: 3270500 | G9: 13429010 | H9: 0.80415593 | I9: 4 | J9: 2 | K9: 0.66666667
A10: Lot 9 | B10: Sécurité Incendie & Vidéo | C10: FA_010 | D10: 13 | E10: 13570000 | F10: 7463500 | G10: 6106500 | H10: 0.45 | I10: 13 | J10: 0 | K10: 1
A11: Lot 10 | B11: Plomberie Sanitaire | C11: FA_011 | D11: 32 | E11: 28038380 | F11: 10140400 | G11: 17897980 | H11: 0.63833859 | I11: 32 | J11: 0 | K11: 1
A12: Lot 11 | B12: Faux Plafonds & Cloisons | C12: FA_012 | D12: 2 | E12: 15682458 | F12: 3036000 | G12: 12646458 | H12: 0.8064079 | I12: 2 | J12: 0 | K12: 1
A13: Lot 12 | B13: Ascenseur | C13: FA_013 | D13: 1 | E13: 25300000 | F13: 10000000 | G13: 15300000 | H13: 0.60474308 | I13: 1 | J13: 0 | K13: 1
... A18: Lot 17 | B18: Groupe Électrogène | C18: FA_017 | D18: 1 | E18: 17250000 | F18: 11000000 | G18: 6250000 | H18: 0.36231884 | I18: 1 | J18: 0 | K18: 1
A19: TOTAL | D19: =SUM(D2:D18) -> 318 | E19: =SUM(E2:E18) -> 8.1360596e+08 | F19: =SUM(F2:F18) -> 5.3393046e+08 | G19: =SUM(G2:G18) -> 2.796755e+08 | I19: =SUM(I2:I18) -> 163 | J19: =SUM(J2:J18) -> 155

Sheet 05_DM_FAM_ARTICLE
A1: FAM_ARTICLE_ID | B1: CODE_FAM_ARTICLE | C1: LIBELLE | D1: FAM_METIER_ID | E1: NB_ARTICLES | F1: TOTAL_LOCAL | G1: TOTAL_CHINE | H1: GAIN | I1: TAUX_GAIN
A2: FA_001 | B2: GROS_OEUVRE | C2: Gros Œuvre & Démolition | D2: FM_01 | E2: 142 | F2: 2.0945185e+08 | G2: 2.0945185e+08 | H2: 0 | I2: 0
A3: FA_002 | B3: ETANCHEITE | C3: Étanchéité | D3: FM_02 | E3: 2 | F3: 7302400 | G3: 2900100 | H3: 4402300 | I3: 0.6028566
A4: FA_003 | B4: ALUCOBOND | C4: Alucobond | D4: FM_02 | E4: 2 | F4: 1.5958938e+08 | G4: 56184002 | H4: 1.0340538e+08 | I4: 0.64794649
A5: FA_004 | B5: REVETEMENTS_DURS | C5: Revêtements Durs | D5: FM_03 | E5: 6 | F5: 1.5929048e+08 | G5: 119132500 | H5: 40157978 | I5: 0.25210533
A6: FA_005 | B6: MENUISERIE_ALU | C6: Menuiserie Aluminium | D6: FM_03 | E6: 39 | F6: 43886340 | G6: 30723519 | H6: 13162821 | I6: 0.2999298
A7: FA_006 | B7: MENUISERIE_MET | C7: Menuiserie Métallique | D7: FM_03 | E7: 2 | F7: 575000 | G7: 402500 | H7: 172500 | I7: 0.3
A8: FA_007 | B8: MENUISERIE_BOIS | C8: Menuiserie Bois | D8: FM_03 | E8: 4 | F8: 4008900 | G8: 2605785 | H8: 1403115 | I8: 0.35
A9: FA_008 | B9: ELECTRICITE | C9: Électricité | D9: FM_04 | E9: 55 | F9: 68801225 | G9: 45971000 | H9: 22830225 | I9: 0.33182876
A10: FA_009 | B10: CLIMATISATION | C10: Climatisation | D10: FM_04 | E10: 6 | F10: 16699510 | G10: 3270500 | H10: 13429010 | I10: 0.80415593
A11: FA_010 | B11: SECURITE | C11: Sécurité Incendie | D11: FM_04 | E11: 13 | F11: 13570000 | G11: 7463500 | H11: 6106500 | I11: 0.45
A12: FA_011 | B12: PLOMBERIE | C12: Plomberie Sanitaire | D12: FM_04 | E12: 32 | F12: 28038380 | G12: 10140400 | H12: 17897980 | I12: 0.63833859
A13: FA_012 | B13: FAUX_PLAFONDS | C13: Faux Plafonds | D13: FM_03 | E13: 2 | F13: 15682458 | G13: 3036000 | H13: 12646458 | I13: 0.8064079
... A18: FA_017 | B18: GROUPE_ELEC | C18: Groupe Électrogène | D18: FM_04 | E18: 1 | F18: 17250000 | G18: 11000000 | H18: 6250000 | I18: 0.36231884

Sheet DIM_PROJET
A1: PROJET_ID | B1: NOM_PROJET | C1: TYPE_PROJET | D1: STATUT | E1: DATE_CREATION | F1: DEVISE | G1: MODE_SOURCING | H1: NB_LOTS
A2: PNR_MEDICAL_CENTER | B2: Centre Médical Pointe Noire | C2: Médical | D2: Etude | E2: 46023 | F2: FCFA | G2: Mixte | H2: 17

Sheet 05_DM_PROJET
A1: PROJET_ID | B1: NOM_PROJET | C1: CAPEX_LOCAL | D1: CAPEX_IMPORT | E1: ECONOMIE_GLOBALE | F1: TAUX_ECONOMIE | G1: NB_TOTAL | H1: NB_IMPORT | I1: NB_LOCAL | J1: NB_ARBITRAGE | K1: TAUX_IMPORT_LIGNES | L1: RISQUE_MOYEN | M1: IGC_FINAL
A2: PNR_MEDICAL_CENTER | B2: Centre Médical Pointe Noire | C2: 8.1360596e+08 | D2: 5.3393046e+08 | E2: 2.796755e+08 | F2: 0.34374809 | G2: 318 | H2: 163 | I2: 142 | J2: 13 | K2: 0.51257862 | L2: 1.1336478 | M2: 0.26581024

Sheet -----06_ANALYTICS-------

Sheet DOCUMENTATION_ANALYTCS

Sheet DASHBOARD_HIERARCHIE
A1: BATIMENT_ID | B1: NIVEAU_ID | C1: LOT_ID | D1: FAM_ARTICLE_ID | E1: TOTAL_LOCAL | F1: TOTAL_IMPORT | G1: TOTAL_ECONOMIE | H1: TAUX_ECO | I1: NOTE_STRATEGIQUE | J1: ZONE_STRATEGIQUE
A2: BAT_ANNEXE | B2: ETAGE 1 | C2: 1 | D2: FA_001 | E2: 2975625 | F2: 4065997.5
A3: BAT_ANNEXE | B3: ETAGE 1 | C3: 2 | D3: FA_002 | E3: 1994955.1
A4: BAT_ANNEXE | B4: ETAGE 1 | C4: 3 | D4: FA_004 | E4: 11431756 | F4: 4674877.4
A5: BAT_ANNEXE | B5: ETAGE 1 | C5: 4 | D5: FA_005 | E5: 16287381 | F5: 5251462.1
A6: BAT_ANNEXE | B6: FONDATIONS | C6: 1 | D6: FA_001 | E6: 9548383.9
A7: BAT_ANNEXE | B7: GLOBAL | C7: 13 | D7: FA_003 | E7: 47019196 | F7: 3588366.1
A8: BAT_ANNEXE | B8: RDC | C8: 3 | D8: FA_004 | E8: 16747922 | F8: 5431262.8
A9: BAT_ANNEXE | B9: RDC | C9: 4 | D9: FA_005 | E9: 4208724 | F9: 1461699
A10: BAT_ANNEXE | B10: RDC | C10: 6 | D10: FA_005 | E10: 4610235 | F10: 742927.28
A11: BAT_ANNEXE | B11: TERRASSE | C11: 2 | D11: FA_002 | E11: 8726825.7 | F11: 6426025
A12: BAT_PRINCIPAL | B12: DUPLEX 1 | C12: 1 | D12: FA_001 | E12: 12299859
A13: BAT_PRINCIPAL | B13: DUPLEX 1 | C13: 11 | D13: FA_012 | E13: 5956804.5
A14: BAT_PRINCIPAL | B14: DUPLEX 1 | C14: 14 | D14: FA_014 | E14: 4737829.8 | F14: 6473935.4
A15: BAT_PRINCIPAL | B15: DUPLEX 1 | C15: 2 | D15: FA_002 | E15: 21555834 | F15: 11204780
A16: BAT_PRINCIPAL | B16: DUPLEX 1 | C16: 3 | D16: FA_004 | E16: 28970778 | F16: 11505265
A17: BAT_PRINCIPAL | B17: DUPLEX 1 | C17: 4 | D17: FA_005 | E17: 15612906 | F17: 4772209
A18: BAT_PRINCIPAL | B18: DUPLEX 1 | C18: 6 | D18: FA_005 | E18: 8256367.5 | F18: 1571741
A19: BAT_PRINCIPAL | B19: DUPLEX 2 | C19: 11 | D19: FA_012 | E19: 5956804.5
A20: BAT_PRINCIPAL | B20: DUPLEX 2 | C20: 2 | D20: FA_002 | E20: 1996984.1
A21: BAT_PRINCIPAL | B21: DUPLEX 2 | C21: 3 | D21: FA_004 | E21: 11461823 | F21: 4481000.3
A22: BAT_PRINCIPAL | B22: DUPLEX 2 | C22: 4 | D22: FA_005 | E22: 10169496 | F22: 3145399.1
A23: BAT_PRINCIPAL | B23: DUPLEX 2 | C23: 6 | D23: FA_005 | E23: 5062530 | F23: 1179021.4
A24: BAT_PRINCIPAL | B24: ETAGE 1 | C24: 11 | D24: FA_012 | E24: 2731174.1
A25: BAT_PRINCIPAL | B25: ETAGE 1 | C25: 14 | D25: FA_014 | E25: 19464555 | F25: 26597045
A26: BAT_PRINCIPAL | B26: ETAGE 1 | C26: 2 | D26: FA_002 | E26: 3956230.3
A27: BAT_PRINCIPAL | B27: ETAGE 1 | C27: 3 | D27: FA_004 | E27: 37828109 | F27: 14559074
A28: BAT_PRINCIPAL | B28: ETAGE 1 | C28: 4 | D28: FA_005 | E28: 27369402 | F28: 9039595.6
A29: BAT_PRINCIPAL | B29: ETAGE 1 | C29: 6 | D29: FA_005 | E29: 5237100 | F29: 1437831
A30: BAT_PRINCIPAL | B30: ETAGE 2 | C30: 1 | D30: FA_001 | E30: 1983750 | F30: 2710665
A31: BAT_PRINCIPAL | B31: ETAGE 2 | C31: 2 | D31: FA_002 | E31: 3561780.4
A32: BAT_PRINCIPAL | B32: ETAGE 2 | C32: 3 | D32: FA_004 | E32: 34046837 | F32: 13363690
A33: BAT_PRINCIPAL | B33: ETAGE 2 | C33: 4 | D33: FA_005 | E33: 29077014 | F33: 9632652.9
A34: BAT_PRINCIPAL | B34: FONDATIONS | C34: 1 | D34: FA_001 | E34: 18071925 | F34: 4778680.5
A35: BAT_PRINCIPAL | B35: GLOBAL | C35: 1 | D35: FA_001 | E35: 30810706 | F35: 42100820
A36: BAT_PRINCIPAL | B36: GLOBAL | C36: 10 | D36: FA_011 | E36: 73980679 | F36: 3497763.5
A37: BAT_PRINCIPAL | B37: GLOBAL | C37: 13 | D37: FA_003 | E37: 38182875 | F37: 2914004.2
A38: BAT_PRINCIPAL | B38: GLOBAL | C38: 5 | D38: FA_005 | E38: 13356853 | F38: 4047925.6
A39: BAT_PRINCIPAL | B39: GLOBAL | C39: 7 | D39: FA_008 | E39: 34996282 | F39: 9607068.2
A40: BAT_PRINCIPAL | B40: GLOBAL | C40: 8 | D40: FA_009 | E40: 78728425 | F40: 15715493
A41: BAT_PRINCIPAL | B41: GLOBAL | C41: 9 | D41: FA_010 | E41: 14517082 | F41: 1552378.2
A42: BAT_PRINCIPAL | B42: GLOBAL | C42: 9 | D42: FA_015 | E42: 6273940 | F42: 733293.81
A43: BAT_PRINCIPAL | B43: RDC | C43: 1 | D43: FA_001 | E43: 25895814 | F43: 2740268.6
A44: BAT_PRINCIPAL | B44: RDC | C44: 11 | D44: FA_012 | E44: 17003382
A45: BAT_PRINCIPAL | B45: RDC | C45: 14 | D45: FA_014 | E45: 15163785 | F45: 20720323
A46: BAT_PRINCIPAL | B46: RDC | C46: 3 | D46: FA_004 | E46: 34770317 | F46: 13361160
A47: BAT_PRINCIPAL | B47: RDC | C47: 4 | D47: FA_005 | E47: 22730601 | F47: 7894387.1
A48: BAT_PRINCIPAL | B48: TERRASSE | C48: 2 | D48: FA_002 | E48: 2892590 | F48: 2191706.2

Sheet DASHBOARD_BATIMENT
A1: BATIMENT_ID | B1: TOTAL_LOCAL | C1: TOTAL_IMPORT | D1: TOTAL_ECONOMIE | E1: TAUX_ECO | F1: TAUX_IMPORT_LIGNES | G1: NOTE_STRATEGIQUE | H1: ZONE_STRATEGIQUE
A2: BAT_PRINCIPAL | B2: 7.2466922e+08 | C2: 2.5352918e+08 | F2: 0.52272727
A3: BAT_ANNEXE | B3: 1.23551e+08 | C3: 31642617 | F3: 0.80555556

Sheet FACT_METRE_AUDIT
A1: FAM_ARTICLE_ID | B1: NB_LIGNES | C1: NB_IMPORT | D1: NB_LOCAL | E1: NB_ARBITRAGE | F1: TAUX_ECO_MOYEN
A2: FA_001 | B2: 56 | C2: 0 | D2: 56 | E2: 0 | F2: 0.62496847
A3: FA_002 | B3: 22 | C3: 18 | D3: 0 | E3: 4 | F3: 0.65865501
A4: FA_004 | B4: 22 | C4: 22 | D4: 0 | E4: 0 | F4: 0.63287102
A5: FA_005 | B5: 84 | C5: 84 | D5: 0 | E5: 0 | F5: 0.72749434
A6: FA_008 | B6: 24 | C6: 22 | D6: 0 | E6: 2 | F6: 0.70863968
A7: FA_009 | B7: 13 | C7: 13 | D7: 0 | E7: 0 | F7: 0.89200946
A8: FA_010 | B8: 17 | C8: 17 | D8: 0 | E8: 0 | F8: 0.93250864
A9: FA_015 | B9: 5 | C9: 5 | D9: 0 | E9: 0 | F9: 0.85678435
A10: FA_011 | B10: 37 | C10: 37 | D10: 0 | E10: 0 | F10: 0.97178375
A11: FA_012 | B11: 6 | C11: 6 | D11: 0 | E11: 0 | F11: 1
A12: FA_013 | B12: 1 | C12: 1 | D12: 0 | E12: 0 | F12: 1
A13: FA_003 | B13: 2 | C13: 2 | D13: 0 | E13: 0 | F13: 0.93428983
A14: FA_014 | B14: 12 | C14: 0 | D14: 0 | E14: 12 | F14: -0.17652174

Sheet ------------07_DASHOARD--------

Sheet DASHBOARD_CHANTIER
A1: BATIMENT_ID | B1: NIVEAU_ID | C1: TOTAL_LOCAL | D1: TOTAL_IMPORT | E1: TOTAL_ECONOMIE | F1: TAUX_ECO | G1: TAUX_IMPORT_LIGNES
A2: BAT_ANNEXE | B2: ETAGE 1 | C2: 32689717 | D2: 13992337 | E2: 16702425 | F2: 0.5109382 | G2: 0.78571429
A3: BAT_ANNEXE | B3: FONDATIONS | C3: 9548383.9 | G3: 0
A4: BAT_ANNEXE | B4: GLOBAL | C4: 47019196 | D4: 3588366.1 | E4: 43430830 | F4: 0.92368296 | G4: 1
A5: BAT_ANNEXE | B5: RDC | C5: 25566881 | D5: 7635889.1 | E5: 17930992 | F5: 0.7013367 | G5: 1
A6: BAT_ANNEXE | B6: TERRASSE | C6: 8726825.7 | D6: 6426025 | E6: 2300800.7 | F6: 0.26364692 | G6: 0.66666667
A7: BAT_PRINCIPAL | B7: DUPLEX 1 | C7: 97390379 | D7: 35527930 | E7: 42552222 | F7: 0.43692429 | G7: 0.57575758
A8: BAT_PRINCIPAL | B8: DUPLEX 2 | C8: 34647638 | D8: 8805420.8 | E8: 17888428 | F8: 0.51629576 | G8: 0.76470588
A9: BAT_PRINCIPAL | B9: ETAGE 1 | C9: 96586570 | D9: 51633546 | E9: 38265620 | F9: 0.39617951 | G9: 0.73076923
A10: BAT_PRINCIPAL | B10: ETAGE 2 | C10: 68669381 | D10: 25707008 | E10: 39400593 | F10: 0.57377236 | G10: 0.8125
A11: BAT_PRINCIPAL | B11: FONDATIONS | C11: 18071925 | D11: 4778680.5 | E11: -731359.24 | F11: -0.040469361 | G11: 0
A12: BAT_PRINCIPAL | B12: GLOBAL | C12: 3.1994184e+08 | D12: 80168746 | E12: 1.36749e+08 | F12: 0.42741829 | G12: 0.51351351
A13: BAT_PRINCIPAL | B13: RDC | C13: 1.155639e+08 | D13: 44716139 | E13: 29953979 | F13: 0.25919841 | G13: 0.33333333
A14: BAT_PRINCIPAL | B14: TERRASSE | C14: 2892590 | D14: 2191706.2 | E14: 700883.8 | F14: 0.24230319 | G14: 0.66666667

Sheet DASHBOARD_LOTS
A1: LOT_ID | B1: TOTAL_LOCAL | C1: TOTAL_IMPORT | D1: TOTAL_ECONOMIE | E1: IPI_LOT | F1: TAUX_IMPORT_LIGNES | G1: DECISION_DOMINANTE
A2: 3 | B2: 1.7525754e+08 | C2: 67376329 | D2: 1.0788121e+08 | E2: 0.61555817 | F2: 1 | G2: IMPORT_DOMINANT
A3: 4 | B3: 125455524 | C3: 41197405 | D3: 84258119 | E3: 0.67161745 | F3: 1 | G3: IMPORT_DOMINANT
A4: 1 | B4: 1.0158606e+08 | C4: 56396432 | D4: 45189631 | E4: 0.44484086 | F4: 0.035714286 | G4: IMPORT_DOMINANT
A5: 13 | B5: 85202071 | C5: 6502370.2 | D5: 78699701 | E5: 0.92368296 | F5: 1 | G5: IMPORT_DOMINANT
A6: 8 | B6: 78728425 | C6: 15715493 | D6: 63012932 | E6: 0.8003835 | F6: 0.61538462 | G6: IMPORT_DOMINANT
A7: 10 | B7: 73980679 | C7: 3497763.5 | D7: 70482915 | E7: 0.95272058 | F7: 0.19444444 | G7: IMPORT_DOMINANT
A8: 2 | B8: 44685200 | C8: 19822511 | D8: 24862689 | E8: 0.5563965 | F8: 0.36363636 | G8: IMPORT_DOMINANT
A9: 14 | B9: 39366170 | C9: 53791304 | D9: -14425134 | E9: -0.36643478 | F9: 0 | G9: LOCAL_DOMINANT
A10: 7 | B10: 34996282 | C10: 9607068.2 | D10: 25389214 | E10: 0.72548318 | F10: 0.91666667 | G10: IMPORT_DOMINANT
A11: 11 | B11: 31648166 | C11: 0 | D11: 31648166 | E11: 1 | F11: 0 | G11: IMPORT_DOMINANT
A12: 6 | B12: 23166232 | C12: 4931520.7 | D12: 18234712 | E12: 0.78712461 | F12: 1 | G12: IMPORT_DOMINANT
A13: 9 | B13: 20791022 | C13: 2285672 | D13: 18505350 | E13: 0.89006447 | F13: 0.59090909 | G13: IMPORT_DOMINANT
A14: 5 | B14: 13356853 | C14: 4047925.6 | D14: 9308927.6 | E14: 0.69694017 | F14: 1 | G14: IMPORT_DOMINANT

Sheet DASHBOARD_FAMILLES
A1: FAM_ARTICLE_ID | B1: TOTAL_LOCAL | C1: TOTAL_IMPORT | D1: IPI_FAM | E1: RISQUE_MOYEN | F1: DECISION_DOMINANTE | G1: CAUSE_DOMINANTE
A2: FA_004 | B2: 1.7525754e+08 | C2: 67376329 | D2: 0.61555817 | E2: 2 | F2: IMPORT_DOMINANT | G2: IMPORT_STRATEGIQUE
A3: FA_005 | B3: 1.6197861e+08 | C3: 50176851 | D3: 0.69022545 | E3: 2 | F3: IMPORT_DOMINANT | G3: IMPORT_STRATEGIQUE
A4: FA_001 | B4: 1.0158606e+08 | C4: 56396432 | D4: -0.14346077 | E4: 0 | F4: LOCAL_DOMINANT | G4: NON_IMPORTABLE_STRUCTUREL
A5: FA_003 | B5: 85202071 | C5: 6502370.2 | D5: 0.92368296 | E5: 2 | F5: IMPORT_DOMINANT | G5: IMPORT_STRATEGIQUE
A6: FA_009 | B6: 78728425 | C6: 15715493 | D6: 0.53413119 | E6: 2.5 | F6: IMPORT_DOMINANT | G6: IMPORT_STRATEGIQUE
A7: FA_011 | B7: 73980679 | C7: 3497763.5 | D7: 0.30684987 | E7: 1.5 | F7: LOCAL_DOMINANT | G7: IMPORT_STRATEGIQUE
A8: FA_002 | B8: 44685200 | C8: 19822511 | D8: 0.27524048 | E8: 1 | F8: MIXTE | G8: IMPORT_STRATEGIQUE
A9: FA_014 | B9: 39366170 | C9: 53791304 | D9: -0.36643478 | E9: 2 | F9: LOCAL_DOMINANT | G9: IMPORT_PLUS_CHER
A10: FA_008 | B10: 34996282 | C10: 9607068.2 | D10: 0.72548318 | E10: 3 | F10: IMPORT_DOMINANT | G10: IMPORT_STRATEGIQUE
A11: FA_012 | B11: 31648166 | E11: 3.5 | F11: LOCAL_DOMINANT
A12: FA_013 | B12: 29095000 | E12: 2 | F12: LOCAL_DOMINANT
A13: FA_010 | B13: 14517082 | C13: 1552378.2 | D13: 0.58141378 | E13: 2 | F13: MIXTE | G13: IMPORT_STRATEGIQUE
A14: FA_015 | B14: 6273940 | C14: 733293.81 | D14: 0.77772439 | E14: 2.5 | F14: IMPORT_DOMINANT | G14: IMPORT_STRATEGIQUE

Sheet DASHBOARD_DIRECTION
A1: TOTAL_LOCAL | B1: TOTAL_IMPORT | C1: TOTAL_ECONOMIE | D1: IPI_PROJET | E1: SCORE_GLOBAL | F1: TAUX_IMPORT_LIGNES | G1: NB_FAMILLES_IMPORT | H1: NB_LOTS_IMPORT
A2: 8.4822023e+08 | B2: 2.8517179e+08 | E2: [Table] | F2: 0.55666667 | G2: 9 | H2: 10

Sheet 07_INTELLIGENCE__DECISION
A1: 🎯 INTELLIGENCE DÉCISIONNELLE — MATRICE IMPORT / LOCAL / ARBITRAGE · PNMC
A2: LOT | B2: NOM_LOT | C2: TOTAL LOCAL | D2: ÉCONOMIE | E2: TAUX GAIN | F2: ROI | G2: RISQUE | H2: POIDS PROJET | I2: SCORE GLOBAL | J2: CLASSE | K2: IPI | L2: QUADRANT | M2: DÉCISION STRATÉGIQUE | N2: NIVEAU PRIORITÉ | O2: DRAPEAU RISQUE | P2: RECOMMANDATION
A3: Lot 1 | B3: Gros Œuvre et Démolition | C3: 2.0945185e+08 | D3: 0 | E3: 0 | F3: 0 | G3: 0 | H3: 0.25743648 | I3: 0 | J3: — | K3: 0 | L3: ⬜ Gain Nul / Local | M3: LOCAL | N3: 🟢 FAIBLE | O3: ✅ OK | P3: Exécution locale obligatoire — structure
A4: Lot 2 | B4: Étanchéité | C4: 7302400 | D4: 4402300 | E4: 0.6028566 | F4: 1.5179821 | G4: 1 | H4: 0.0089753522 | I4: 0.76198448 | J4: A | K4: 0.0054108503 | L4: 🟢 Gain Fort / Risque Faible | M4: IMPORT PRIORITAIRE | N4: 🟢 FAIBLE | O4: ✅ OK | P4: Import fortement recommandé — économies >60%
A5: Lot 3 | B5: Revêtements Durs | C5: 1.5929048e+08 | D5: 40157978 | E5: 0.25210533 | F5: 0.33708667 | G5: 1 | H5: 0.19578332 | I5: 0.3544813 | J5: A | K5: 0.049358018 | L5: 🟢 Gain Fort / Risque Faible | M5: IMPORT PRIORITAIRE | N5: 🟢 FAIBLE | O5: ✅ OK | P5: Analyser sourcing mixte ou négocier local
A6: Lot 4 | B6: Menuiserie Alu & Vitrerie | C6: 43886340 | D6: 13162821 | E6: 0.2999298 | F6: 0.42842817 | G6: 2 | H6: 0.053940534 | I6: 0.36517004 | J6: A | K6: 0.016178373 | L6: 🟢 Gain Fort / Risque Faible | M6: IMPORT PRIORITAIRE | N6: 🟡 MOYENNE | O6: ➡️ MODÉRÉ | P6: Analyser sourcing mixte ou négocier local
A7: Lot 5 | B7: Menuiserie Métallique | C7: 575000 | D7: 172500 | E7: 0.3 | F7: 0.42857143 | G7: 2 | H7: 0.00070673032 | I7: 0.35724887 | J7: A | K7: 0.0002120191 | L7: 🟢 Gain Fort / Risque Faible | M7: IMPORT PRIORITAIRE | N7: 🟡 MOYENNE | O7: ➡️ MODÉRÉ | P7: Import recommandé — vérifier délais & logistique
A8: Lot 6 | B8: Menuiserie Bois | C8: 4008900 | D8: 1403115 | E8: 0.35 | F8: 0.53846154 | G8: 2 | H8: 0.0049273238 | I8: 0.40535448 | J8: A | K8: 0.0017245633 | L8: 🟢 Gain Fort / Risque Faible | M8: IMPORT PRIORITAIRE | N8: 🟡 MOYENNE | O8: ➡️ MODÉRÉ | P8: Import recommandé — vérifier délais & logistique
A9: Lot 7 | B9: Électricité | C9: 68801225 | D9: 22830225 | E9: 0.33182876 | F9: 0.49662233 | G9: 2 | H9: 0.084563325 | I9: 0.39957158 | J9: A | K9: 0.028060543 | L9: 🟢 Gain Fort / Risque Faible | M9: IMPORT PRIORITAIRE | N9: 🟡 MOYENNE | O9: ➡️ MODÉRÉ | P9: Import recommandé — vérifier délais & logistique
A10: Lot 8 | B10: Climatisation | C10: 16699510 | D10: 13429010 | E10: 0.80415593 | F10: 4.106103 | G10: 3 | H10: 0.020525305 | I10: 1.4712669 | J10: A | K10: 0.016505545 | L10: 🟡 Gain Fort / Risque Élevé | M10: IMPORT PRIORITAIRE | N10: 🔴 CRITIQUE | O10: ⚠️ ÉLEVÉ | P10: Import fortement recommandé — économies >60%
A11: Lot 9 | B11: Sécurité Incendie & Vidéo | C11: 13570000 | D11: 6106500 | E11: 0.45 | F11: 0.81818182 | G11: 2.5 | H11: 0.016678836 | I11: 0.51204728 | J11: A | K11: 0.007505476 | L11: 🟡 Gain Fort / Risque Élevé | M11: IMPORT PRIORITAIRE | N11: 🟠 HAUTE | O11: ➡️ MODÉRÉ | P11: Import recommandé — vérifier délais & logistique
A12: Lot 10 | B12: Plomberie Sanitaire | C12: 28038380 | D12: 17897980 | E12: 0.63833859 | F12: 1.7650172 | G12: 2 | H12: 0.034461867 | I12: 0.83175901 | J12: A | K12: 0.021998339 | L12: 🟢 Gain Fort / Risque Faible | M12: IMPORT PRIORITAIRE | N12: 🟡 MOYENNE | O12: ➡️ MODÉRÉ | P12: Import fortement recommandé — économies >60%
A13: Lot 11 | B13: Faux Plafonds & Cloisons | C13: 15682458 | D13: 12646458 | E13: 0.8064079 | F13: 4.1655 | G13: 1.5 | H13: 0.01927525 | I13: 1.5018294 | J13: A | K13: 0.015543714 | L13: 🟢 Gain Fort / Risque Faible | M13: IMPORT PRIORITAIRE | N13: 🟡 MOYENNE | O13: ✅ OK | P13: Import fortement recommandé — économies >60%
A14: Lot 12 | B14: Ascenseur | C14: 25300000 | D14: 15300000 | E14: 0.60474308 | F14: 1.53 | G14: 3.5 | H14: 0.031096134 | I14: 0.74406165 | J14: A | K14: 0.018805172 | L14: 🟡 Gain Fort / Risque Élevé | M14: IMPORT PRIORITAIRE | N14: 🔴 CRITIQUE | O14: ⚠️ ÉLEVÉ | P14: Import fortement recommandé — économies >60%
... A19: Lot 17 | B19: Groupe Électrogène | C19: 17250000 | D19: 6250000 | E19: 0.36231884 | F19: 0.56818182 | G19: 3 | H19: 0.02120191 | I19: 0.41015328 | J19: A | K19: 0.0076818513 | L19: 🟡 Gain Fort / Risque Élevé | M19: IMPORT PRIORITAIRE | N19: 🔴 CRITIQUE | O19: ⚠️ ÉLEVÉ | P19: Import recommandé — vérifier délais & logistique

Sheet 08_KPI__PROJET
A1: 📊 KPI PROJET — PNMC MEDICAL CENTER POINTE NOIRE | B1: Colonne1 | C1: Colonne2 | D1: Colonne3
A2: INDICATEUR | B2: VALEUR | C2: UNITÉ | D2: DESCRIPTION
A3: ── KPI FINANCIERS ──
A4: CAPEX Local Total | B4: 8.1360596e+08 | D4: Budget total exécution 100% locale
A5: CAPEX Optimisé Chine | B5: 5.3393046e+08 | D5: Budget si sourcing Chine maximisé
A6: Économie Globale Nette | B6: 2.796755e+08 | D6: Gain potentiel sourcing Chine
A7: Taux Économie Global | B7: 0.34374809 | D7: Réduction CAPEX par import
A8: ROI Import Global | B8: 0.5238051 | D8: Rendement brut du sourcing Chine
A9: IGC — Indice Global Comp. | B9: 0.26581024 | D9: Gain net ajusté risque logistique
A10: ── KPI OPÉRATIONNELS ──
A11: NB Articles Total | B11: 318 | D11: Articles dans le DQE complet
A12: NB Articles Import | B12: 163 | D12: Articles orientation IMPORT (gain>5%)
A13: NB Articles Local | B13: 142 | D13: Articles sans avantage Chine
A14: NB Articles Arbitrage | B14: 13 | D14: Articles à décision mixte
A15: Taux Import (lignes) | B15: 0.51257862 | D15: % lignes orientées import
A16: ── KPI RISQUE & STRATÉGIE ──
A17: Risque Moyen Global | B17: 1.1336478 | D17: Score /5 — logistique & douane
A18: Lots Risque Critique (≥3) | B18: 3 | D18: Lots nécessitant plan de mitigation
A19: Lots Classe A (top) | B19: 16 | D19: Lots priorité maximale import
A20: Score Stratégique Max | B20: 1.5018294 | D20: Meilleur score calculé
A21: IPI Max | B21: 0.12709516 | D21: Indice Priorité Import le plus élevé
A22: ── TOP OPPORTUNITÉS ──
A23: Meilleur Taux Gain | B23: 0.8064079 | D23: Lot : Lot 11
A24: Meilleure Économie Absolue | B24: 1.0340538e+08 | D24: Lot : Lot 13
A25: Lot Meilleur Score | B25: Lot 11 | D25: Score stratégique le plus élevé

Sheet 09_DM_MATRICE_GAIN_RISQUE
A1: 📍 MATRICE GAIN / RISQUE — DONNÉES GRAPHIQUE DIRECTIONNEL · PNMC
A2: LOT | B2: NOM_LOT | C2: TOTAL LOCAL | D2: ÉCONOMIE | E2: TAUX GAIN | F2: ROI | G2: RISQUE MOY. | H2: POIDS PROJET | I2: SCORE GLOBAL | J2: QUADRANT
A3: Lot 1 | B3: Gros Œuvre et Démolition | C3: 2.0945185e+08 | D3: 0 | E3: 0 | F3: 0 | G3: 0 | H3: 0.25743648 | I3: 0 | J3: ⬜ Gain Nul / Local
A4: Lot 2 | B4: Étanchéité | C4: 7302400 | D4: 4402300 | E4: 0.6028566 | F4: 1.5179821 | G4: 1 | H4: 0.0089753522 | I4: 0.76198448 | J4: 🟢 Gain Fort / Risque Faible
A5: Lot 3 | B5: Revêtements Durs | C5: 1.5929048e+08 | D5: 40157978 | E5: 0.25210533 | F5: 0.33708667 | G5: 1 | H5: 0.19578332 | I5: 0.3544813 | J5: 🟢 Gain Fort / Risque Faible
A6: Lot 4 | B6: Menuiserie Alu & Vitrerie | C6: 43886340 | D6: 13162821 | E6: 0.2999298 | F6: 0.42842817 | G6: 2 | H6: 0.053940534 | I6: 0.36517004 | J6: 🟢 Gain Fort / Risque Faible
A7: Lot 5 | B7: Menuiserie Métallique | C7: 575000 | D7: 172500 | E7: 0.3 | F7: 0.42857143 | G7: 2 | H7: 0.00070673032 | I7: 0.35724887 | J7: 🟢 Gain Fort / Risque Faible
A8: Lot 6 | B8: Menuiserie Bois | C8: 4008900 | D8: 1403115 | E8: 0.35 | F8: 0.53846154 | G8: 2 | H8: 0.0049273238 | I8: 0.40535448 | J8: 🟢 Gain Fort / Risque Faible
A9: Lot 7 | B9: Électricité | C9: 68801225 | D9: 22830225 | E9: 0.33182876 | F9: 0.49662233 | G9: 2 | H9: 0.084563325 | I9: 0.39957158 | J9: 🟢 Gain Fort / Risque Faible
A10: Lot 8 | B10: Climatisation | C10: 16699510 | D10: 13429010 | E10: 0.80415593 | F10: 4.106103 | G10: 3 | H10: 0.020525305 | I10: 1.4712669 | J10: 🟡 Gain Fort / Risque Élevé
A11: Lot 9 | B11: Sécurité Incendie & Vidéo | C11: 13570000 | D11: 6106500 | E11: 0.45 | F11: 0.81818182 | G11: 2.5 | H11: 0.016678836 | I11: 0.51204728 | J11: 🟡 Gain Fort / Risque Élevé
A12: Lot 10 | B12: Plomberie Sanitaire | C12: 28038380 | D12: 17897980 | E12: 0.63833859 | F12: 1.7650172 | G12: 2 | H12: 0.034461867 | I12: 0.83175901 | J12: 🟢 Gain Fort / Risque Faible
A13: Lot 11 | B13: Faux Plafonds & Cloisons | C13: 15682458 | D13: 12646458 | E13: 0.8064079 | F13: 4.1655 | G13: 1.5 | H13: 0.01927525 | I13: 1.5018294 | J13: 🟢 Gain Fort / Risque Faible
A14: Lot 12 | B14: Ascenseur | C14: 25300000 | D14: 15300000 | E14: 0.60474308 | F14: 1.53 | G14: 3.5 | H14: 0.031096134 | I14: 0.74406165 | J14: 🟡 Gain Fort / Risque Élevé
... A19: Lot 17 | B19: Groupe Électrogène | C19: 17250000 | D19: 6250000 | E19: 0.36231884 | F19: 0.56818182 | G19: 3 | H19: 0.02120191 | I19: 0.41015328 | J19: 🟡 Gain Fort / Risque Élevé

Sheet 10_DASHBOARD__DIRECTION
B1: 📊 DASHBOARD DIRECTION — PNMC MEDICAL CENTER POINTE NOIRE
B2: Moteur Décisionnel Import / Local · V2.0 · 2026-03-01 · Devise FCFA · 318 articles · 17 lots
B4: 💰 CAPEX LOCAL | D4: 🇨🇳 CAPEX OPTIMISÉ | F4: ✅ ÉCONOMIE NETTE
B5: 0.814 Mrd FCFA | D5: 0.534 Mrd FCFA | F5: 279.7 M FCFA
B6: 813,605,955 FCFA | D6: 533,930,459 FCFA | F6: Taux : 34.4%
B8: ▌ SYNTHÈSE PAR LOT — Comparaison Local vs Chine
B9: LOT | C9: DÉSIGNATION | D9: TOTAL LOCAL | E9: TOTAL CHINE | F9: ÉCONOMIE | G9: GAIN % | H9: DÉCISION
B10: Lot 1 | C10: Gros Œuvre et Démolition | D10: 2.0945185e+08 | E10: 2.0945185e+08 | F10: 0 | G10: 0 | H10: LOCAL
B11: Lot 2 | C11: Étanchéité | D11: 7302400 | E11: 2900100 | F11: 4402300 | G11: 0.6028566 | H11: IMPORT PRIORITAIRE
B12: Lot 3 | C12: Revêtements Durs | D12: 1.5929048e+08 | E12: 119132500 | F12: 40157978 | G12: 0.25210533 | H12: IMPORT PRIORITAIRE
B13: Lot 4 | C13: Menuiserie Aluminium et Vitrerie | D13: 43886340 | E13: 30723519 | F13: 13162821 | G13: 0.2999298 | H13: IMPORT PRIORITAIRE
B14: Lot 5 | C14: Menuiserie Métallique et Ferronnerie | D14: 575000 | E14: 402500 | F14: 172500 | G14: 0.3 | H14: IMPORT PRIORITAIRE
B15: Lot 6 | C15: Menuiserie Bois | D15: 4008900 | E15: 2605785 | F15: 1403115 | G15: 0.35 | H15: IMPORT PRIORITAIRE
B16: Lot 7 | C16: Électricité | D16: 68801225 | E16: 45971000 | F16: 22830225 | G16: 0.33182876 | H16: IMPORT PRIORITAIRE
B17: Lot 8 | C17: Climatisation | D17: 16699510 | E17: 3270500 | F17: 13429010 | G17: 0.80415593 | H17: IMPORT PRIORITAIRE
B18: Lot 9 | C18: Sécurité Incendie et Vidéo Surveillance | D18: 13570000 | E18: 7463500 | F18: 6106500 | G18: 0.45 | H18: IMPORT PRIORITAIRE
B19: Lot 10 | C19: Plomberie Sanitaire | D19: 28038380 | E19: 10140400 | F19: 17897980 | G19: 0.63833859 | H19: IMPORT PRIORITAIRE
B20: Lot 11 | C20: Faux Plafonds et Cloisons BA13 | D20: 15682458 | E20: 3036000 | F20: 12646458 | G20: 0.8064079 | H20: IMPORT PRIORITAIRE
B21: Lot 12 | C21: Ascenseur | D21: 25300000 | E21: 10000000 | F21: 15300000 | G21: 0.60474308 | H21: IMPORT PRIORITAIRE
... B26: Lot 17 | C26: Groupe Électrogène | D26: 17250000 | E26: 11000000 | F26: 6250000 | G26: 0.36231884 | H26: IMPORT PRIORITAIRE
B27: TOTAL | D27: =SUM(D10:D26) -> 8.1360596e+08 | E27: =SUM(E10:E26) -> 5.3393046e+08 | F27: =SUM(F10:F26) -> 2.796755e+08
B29: ▌ TOP 5 LOTS — MEILLEURES OPPORTUNITÉS D'IMPORT
B30: LOT | C30: NOM_LOT | D30: TAUX GAIN | E30: ÉCONOMIE (FCFA) | F30: CLASSE | G30: DÉCISION
B31: Lot 11 | C31: Faux Plafonds & Cloisons | D31: 0.8064079 | E31: 12646458 | F31: A | G31: IMPORT PRIORITAIRE
B32: Lot 8 | C32: Climatisation | D32: 0.80415593 | E32: 13429010 | F32: A | G32: IMPORT PRIORITAIRE
B33: Lot 15 | C33: Vidéo Surveillance | D33: 0.69227209 | E33: 2812030 | F33: A | G33: IMPORT PRIORITAIRE
B34: Lot 13 | C34: Alucobond – Bardage Façade | D34: 0.64794649 | E34: 1.0340538e+08 | F34: A | G34: IMPORT PRIORITAIRE
B35: Lot 10 | C35: Plomberie Sanitaire | D35: 0.63833859 | E35: 17897980 | F35: A | G35: IMPORT PRIORITAIRE
B37: ▌ LOTS À RISQUE ÉLEVÉ — Mitigation requise
B38: LOT | C38: NOM_LOT | D38: RISQUE MOY. | E38: QUADRANT | F38: NIVEAU | G38: DRAPEAU | H38: RECOMMANDATION
B39: Lot 12 | C39: Ascenseur | D39: 3.5 | E39: 🟡 Gain Fort / Risque Élevé | F39: 🔴 CRITIQUE | G39: ⚠️ ÉLEVÉ | H39: Import fortement recommandé — économies >60%
B40: Lot 17 | C40: Groupe Électrogène | D40: 3 | E40: 🟡 Gain Fort / Risque Élevé | F40: 🔴 CRITIQUE | G40: ⚠️ ÉLEVÉ | H40: Import recommandé — vérifier délais & logistique
B41: Lot 8 | C41: Climatisation | D41: 3 | E41: 🟡 Gain Fort / Risque Élevé | F41: 🔴 CRITIQUE | G41: ⚠️ ÉLEVÉ | H41: Import fortement recommandé — économies >60%
B42: Lot 9 | C42: Sécurité Incendie & Vidéo | D42: 2.5 | E42: 🟡 Gain Fort / Risque Élevé | F42: 🟠 HAUTE | G42: ➡️ MODÉRÉ | H42: Import recommandé — vérifier délais & logistique
B43: Lot 15 | C43: Vidéo Surveillance | D43: 2.5 | E43: 🟡 Gain Fort / Risque Élevé | F43: 🟠 HAUTE | G43: ➡️ MODÉRÉ | H43: Import fortement recommandé — économies >60%
B44: Lot 7 | C44: Électricité | D44: 2 | E44: 🟢 Gain Fort / Risque Faible | F44: 🟡 MOYENNE | G44: ➡️ MODÉRÉ | H44: Import recommandé — vérifier délais & logistique
B45: Lot 6 | C45: Menuiserie Bois | D45: 2 | E45: 🟢 Gain Fort / Risque Faible | F45: 🟡 MOYENNE | G45: ➡️ MODÉRÉ | H45: Import recommandé — vérifier délais & logistique
B46: Lot 5 | C46: Menuiserie Métallique | D46: 2 | E46: 🟢 Gain Fort / Risque Faible | F46: 🟡 MOYENNE | G46: ➡️ MODÉRÉ | H46: Import recommandé — vérifier délais & logistique
B47: Lot 4 | C47: Menuiserie Alu & Vitrerie | D47: 2 | E47: 🟢 Gain Fort / Risque Faible | F47: 🟡 MOYENNE | G47: ➡️ MODÉRÉ | H47: Analyser sourcing mixte ou négocier local
B48: Lot 13 | C48: Alucobond – Bardage Façade | D48: 2 | E48: 🟢 Gain Fort / Risque Faible | F48: 🟡 MOYENNE | G48: ➡️ MODÉRÉ | H48: Import fortement recommandé — économies >60%
B49: Lot 10 | C49: Plomberie Sanitaire | D49: 2 | E49: 🟢 Gain Fort / Risque Faible | F49: 🟡 MOYENNE | G49: ➡️ MODÉRÉ | H49: Import fortement recommandé — économies >60%
B50: Lot 14 | C50: Peinture | D50: 2 | E50: 🟢 Gain Fort / Risque Faible | F50: 🟡 MOYENNE | G50: ➡️ MODÉRÉ | H50: Import recommandé — vérifier délais & logistique
B51: Lot 16 | C51: Centrale Solaire | D51: 2 | E51: 🟢 Gain Fort / Risque Faible | F51: 🟡 MOYENNE | G51: ➡️ MODÉRÉ | H51: Import recommandé — vérifier délais & logistique

Sheet RECAP_DASHBOARD
B1: 📊 RÉCAPITULATIF — PROJET MÉDICAL CENTER POINTE NOIRE
B3: CAPEX LOCAL TOTAL | C3: 8.1360596e+08
B4: CAPEX OPTIMISÉ CHINE | C4: 5.3393046e+08
B5: ÉCONOMIE GLOBALE | C5: 2.796755e+08
B6: TAUX D'ÉCONOMIE | C6: 0.34374809
B7: NB ARTICLES TOTAL | C7: 318
B8: NB ARTICLES IMPORT | C8: 163
B9: RISQUE MOYEN | C9: 1.1336478
B11: LOT | C11: DÉSIGNATION | D11: TOTAL LOCAL | E11: TOTAL CHINE | F11: GAIN | G11: GAIN %
B12: Lot 1 | C12: Gros Œuvre et Démolition | D12: 2.0945185e+08 | E12: 2.0945185e+08 | F12: 0 | G12: 0
B13: Lot 2 | C13: Étanchéité | D13: 7302400 | E13: 2900100 | F13: 4402300 | G13: 0.6028566
B14: Lot 3 | C14: Revêtements Durs | D14: 1.5929048e+08 | E14: 119132500 | F14: 40157978 | G14: 0.25210533
B15: Lot 4 | C15: Menuiserie Aluminium et Vitrerie | D15: 43886340 | E15: 30723519 | F15: 13162821 | G15: 0.2999298
B16: Lot 5 | C16: Menuiserie Métallique | D16: 575000 | E16: 402500 | F16: 172500 | G16: 0.3
B17: Lot 6 | C17: Menuiserie Bois | D17: 4008900 | E17: 2605785 | F17: 1403115 | G17: 0.35
B18: Lot 7 | C18: Électricité | D18: 68801225 | E18: 45971000 | F18: 22830225 | G18: 0.33182876
B19: Lot 8 | C19: Climatisation | D19: 16699510 | E19: 3270500 | F19: 13429010 | G19: 0.80415593
B20: Lot 9 | C20: Sécurité Incendie & Vidéo | D20: 13570000 | E20: 7463500 | F20: 6106500 | G20: 0.45
B21: Lot 10 | C21: Plomberie Sanitaire | D21: 28038380 | E21: 10140400 | F21: 17897980 | G21: 0.63833859
B22: Lot 11 | C22: Faux Plafonds & Cloisons | D22: 15682458 | E22: 3036000 | F22: 12646458 | G22: 0.8064079
B23: Lot 12 | C23: Ascenseur | D23: 25300000 | E23: 10000000 | F23: 15300000 | G23: 0.60474308
... B28: Lot 17 | C28: Groupe Électrogène | D28: 17250000 | E28: 11000000 | F28: 6250000 | G28: 0.36231884
B29: TOTAL | D29: =SUM(C12:C28) -> 0 | E29: =SUM(D12:D28) -> 8.1360596e+08 | F29: =SUM(E12:E28) -> 5.3393046e+08

Sheet AUDIT_04_ANALYSE_CHANTIER
A1: 🔍 AUDIT COMPLET — MODULE 04_ANALYSE_CHANTIER · SP2i · PNMC
A2: Centre Médical Pointe-Noire · Moteur Décisionnel Chantier V2.0 · Date audit : 2026-03-09
A3: ÉLÉMENT AUDITÉ | B3: STATUT | C3: SÉVÉRITÉ | D3: DÉTAIL / RECOMMANDATION
A4: ═══ PARTIE 1 : AUDIT STRUCTUREL DU MODÈLE ═══
A5: 1.1 Architecture FACT/DIM — Conformité étoile | B5: ✅ CONFORME | C5: — | D5: Schéma en étoile : 1 FACT_METRE (301 lignes, 13 cols) reliée à 5 DIM. Conforme standards BI.
A6: → FACT_METRE (table de faits) | B6: ✅ OK | C6: — | D6: 301 lignes · 13 colonnes · Clés : PROJET_ID, LOT_ID, FAM_ARTICLE_ID, BATIMENT_ID, NIVEAU_KEY
A7: → DIM_PROJET (1 ligne) | B7: ⚠️ ALERTE | C7: 🟡 MOYENNE | D7: PROJET_ID = 'PNR_MEDICAL_CENTER' (DIM) vs 'PROJ-MED-PNR-2025' (FACT). JOINTURE ROMPUE.
A8: → DIM_BATIMENT (2 lignes) | B8: ✅ OK | C8: — | D8: BAT_PRINCIPAL + BAT_ANNEXE alignés. Même incohérence PROJET_ID.
A9: → DIM_LOT (14 lignes) | B9: ✅ OK | C9: — | D9: 14 lots DIM = 14 LOT_ID FACT. Aucun orphelin. Jointure intégrale.
A10: → DIM_NIVEAU (13 lignes) | B10: ✅ OK | C10: — | D10: 13 NIVEAU_KEY uniques, 0 doublon. Clé composite fonctionnelle.
A11: → DIM_FAM_ARTICLE (17 lignes) | B11: ⚠️ ALERTE | C11: 🟡 MOYENNE | D11: 17 DIM vs 13 FACT. Absentes : FA_006, FA_007, FA_016, FA_017.
A12: 1.2 Cardinalité des relations
A13: FACT → DIM_PROJET | B13: 🔴 RUPTURE | C13: 🔴 CRITIQUE | D13: Clé PROJET_ID incohérente. Jointure IMPOSSIBLE sans correction.
A14: FACT → DIM_BATIMENT | B14: ✅ N:1 | C14: — | D14: 2 valeurs dans FACT = 2 lignes DIM. Correct.
A15: FACT → DIM_LOT | B15: ✅ N:1 | C15: — | D15: 14 LOT_ID concordants. Couverture 100%.
A16: FACT → DIM_NIVEAU | B16: ✅ N:1 | C16: — | D16: 13 NIVEAU_KEY concordants. Jointure OK.
A17: FACT → DIM_FAM_ARTICLE | B17: ⚠️ PARTIELLE | C17: 🟡 MOYENNE | D17: 13/17 familles couvertes. 4 orphelines dans DIM.
A18: 1.3 Qualité des clés
A19: NIVEAU_KEY | B19: ✅ BONNE | C19: — | D19: Format BATIMENT_NIVEAU · 13 uniques · 0 doublon.
A20: LOT_ID | B20: ⚠️ RISQUE | C20: 🟡 MOYENNE | D20: Nombre dans FACT, texte dans certains analytics. Risque non-jointure Power BI.
A21: PROJET_ID | B21: 🔴 ERREUR | C21: 🔴 CRITIQUE | D21: PROJ-MED-PNR-2025' (FACT/DIM_NIVEAU) vs 'PNR_MEDICAL_CENTER' (DIM_PROJET/BAT).
A23: ═══ PARTIE 2 : AUDIT DES MESURES / CALCULS ═══
A24: 2.1 MONTANT_LOCAL | B24: ✅ OK | C24: — | D24: Total FACT : 877 315 229 FCFA = ANALYTICS_SYNTHESE (877 315 229). 0 écart.
A25: 2.2 MONTANT_IMPORT | B25: ⚠️ ALERTE | C25: 🟡 MOYENNE | D25: 97 cellules vides / 301 (32.2%). Articles LOCAL sans prix Chine. Risque si agrégé sans gestion null.
A26: 2.3 ECONOMIE_NETTE | B26: ⚠️ ATTENTION | C26: 🟡 MOYENNE | D26: 35 lignes négatives (11.6%). Normal (import + cher). Mais total analytics inclut tout sans filtre.
A27: 2.4 TAUX_ECONOMIE | B27: ✅ OK | C27: — | D27: {=ECONOMIE / MONTANT_LOCAL. Négatif si import plus cher. Logique correcte.} -> #NAME?
A28: 2.5 DECISION | B28: ✅ OK | C28: — | D28: IMPORT: 227 · LOCAL: 56 · ARBITRAGE: 18 · Total = 301. Cohérent.
A29: 2.6 ÉCART CRITIQUE DES TOTAUX | B29: 🔴 CRITIQUE | C29: 🔴 CRITIQUE | D29: 3 totaux CAPEX : FACT=877.3M · 05_DM=813.6M · IPI=725.4M. Source erreur majeure.
A30: → Écart FACT vs 05_DM | D30: 05_DM utilise un périmètre différent (-63.7M). Non documenté.
A31: → Écart IPI_PROJET | D31: IPI exclut probablement Gros Œuvre non importable. Non documenté.
A32: 2.7 IPI (Indice Performance Import) | B32: ⚠️ ALERTE | C32: 🟡 MOYENNE | D32: Deux IPI : 0.720 (SYNTHESE) vs 0.810 (IPI_PROJET). Périmètres divergents.
A33: 2.8 Double agrégation | B33: ✅ OK | C33: — | D33: Chaque couche ANALYTICS agrège depuis FACT. Pas de cascade.
A34: 2.9 Gestion nulls | B34: ⚠️ RISQUE | C34: 🟡 MOYENNE | D34: 97 MONTANT_IMPORT vides. SUM OK mais AVERAGE biaisé en Power BI.
A36: ═══ PARTIE 3 : AUDIT DES AGRÉGATIONS CHANTIER ═══
A37: 3.1 Agrégation par LOT | B37: ✅ VÉRIFIÉ | C37: — | D37: 14 lots concordants FACT ↔ ANALYTICS à l'arrondi flottant près.
A38: 3.2 Agrégation par BATIMENT | B38: ✅ VÉRIFIÉ | C38: — | D38: BAT_PRINCIPAL: 753.8M · BAT_ANNEXE: 123.6M · Concordance parfaite.
A39: 3.3 Agrégation par NIVEAU | B39: ✅ VÉRIFIÉ | C39: — | D39: 13 niveaux dans ANALYTICS_BAT_NIVEAU = 13 NIVEAU_KEY FACT.
A40: 3.4 Agrégation par FAM_ARTICLE | B40: ✅ VÉRIFIÉ | C40: — | D40: 13 familles concordantes FACT ↔ ANALYTICS_DIAGNOSTIC_FAM.
A41: 3.5 Agrégation PROJET global | B41: 🔴 INCOHÉRENT | C41: 🔴 CRITIQUE | D41: 877.3M vs 813.6M vs 725.4M. Le dirigeant voit 813.6M mais analytics calcule 877.3M. Écart 63.7M (7.3%).
A42: 3.6 Lot 1 : anomalie DECISION | B42: ⚠️ ANOMALIE | C42: 🟡 MOYENNE | D42: 0 articles IMPORT mais DECISION_DOMINANTE = 'IMPORT_DOMINANT'. Règle incohérente.
A43: 3.7 Lot 14 : économie négative | B43: ✅ LOGIQUE | C43: — | D43: ECO = -6.9M. Import plus cher. DECISION = LOCAL. Cohérent.
A44: 3.8 VUE_CHANTIER granularité | B44: ✅ OK | C44: — | D44: 49 lignes (LOT×BAT×NIV×FAM). Drill-down correct.
A46: ═══ PARTIE 4 : AUDIT DÉCISIONNEL — 4 QUESTIONS CLÉS ═══
A47: Q1 : Combien coûte le projet ? | B47: ⚠️ AMBIGU | C47: 🟡 MOYENNE | D47: 3 réponses : 877.3M / 813.6M / 725.4M. Le dirigeant ne peut pas répondre.
A48: → Recommandation Q1 | D48: Créer hiérarchie : CAPEX_BRUT (877.3M) → CAPEX_DECISION (813.6M) → CAPEX_IMPORTABLE (725.4M).
A49: Q2 : Où est le budget ? | B49: ✅ RÉPONDU | C49: — | D49: Pareto + hiérarchie LOT/BAT/NIV. Top 3 lots = 46% du budget.
A50: → Top 3 | D50: Lot 3 : 175.3M (20%) · Lot 4 : 125.5M (14.3%) · Lot 1 : 101.6M (11.6%)
A51: Q3 : Quels articles importer ? | B51: ✅ RÉPONDU | C51: — | D51: DECISION_MATRIX + DIAGNOSTIC_FAM + Score multicritères. 227 IMPORT / 56 LOCAL / 18 ARBITRAGE.
A52: → Pareto top 4 | D52: 4 articles = 43.8% de l'économie. BPU-ALUCOBOND seul = 13.5%.
A53: Q4 : Impact financier import ? | B53: ⚠️ PARTIEL | C53: 🟡 MOYENNE | D53: IPI + Score Global existent mais fragmentés entre 3 modules (07/08/09). Pas de vue consolidée.
A54: → Écart économie | D54: Dashboard : 279.7M (34.4%). Analytics : 631.8M (72%). Périmètres différents.
A55: → ROI dispersé | D55: ROI moyen 52.4% mais de 0.33x (Lot 3) à 4.17x (Lot 11). Moyenne trompeuse.
A57: PARTIE 5 : RECOMMANDATIONS EXPERTES
A58: R1 : Harmoniser PROJET_ID | B58: URGENTE | C58: CRITIQUE | D58: Unifier PROJ-MED-PNR-2025 partout
A59: R2 : Reconcilier CAPEX | B59: URGENTE | C59: CRITIQUE | D59: 3 totaux differents non reconcilies
A60: R3 : Corriger DECISION Lot 1 | B60: URGENTE | C60: CRITIQUE | D60: NB_IMPORT=0 mais DECISION=IMPORT_DOMINANT
A61: R4 : Completer 4 familles | B61: IMPORTANTE | C61: MOYENNE | D61: FA_006 FA_007 FA_016 FA_017 absentes FACT
A62: R5 : Normaliser nulls | B62: IMPORTANTE | C62: MOYENNE | D62: 97 MONTANT_IMPORT vides - mettre 0
A63: R6 : Enrichir DIM_LOT | B63: IMPORTANTE | C63: MOYENNE | D63: Ajouter NOM_LOT DESCRIPTION FAM_ARTICLE_ID
A64: R7 : Creer CAPEX_OPTIMISE | B64: IMPORTANTE | C64: MOYENNE | D64: IF DECISION=IMPORT MONTANT_IMPORT else LOCAL
A65: R8 : Nouvelles mesures | B65: SOUHAITEE | C65: FAIBLE
A66: TAUX_COUVERTURE_IMPORT | D66: NB_IMPORT / NB_IMPORTABLE
A67: GAIN_MARGINAL_PAR_ARTICLE | D67: ECONOMIE / NB_ARTICLES par famille
A68: INDICE_CONCENTRATION HHI | D68: Herfindahl distribution montants par LOT
A69: SEUIL_RENTABILITE_IMPORT | D69: COUT_LOGISTIQUE / ECONOMIE = point mort
A70: VARIANCE_ECONOMIE | D70: STDEV TAUX_ECO par famille
A71: R9 : Optimisations Power BI | B71: SOUHAITEE | C71: FAIBLE
A72: Typer LOT_ID texte partout | D72: Eviter erreurs jointure nombre/texte
A73: Creer DIM_DATE | D73: Suivi temporel versions et scenarios
A74: Ajouter RLS | D74: Securite par BATIMENT_ID
A75: Bookmark Navigator | D75: Signets Direction / Chantier / Import / Risque
A76: R10 : Dashboard Direction | B76: SOUHAITEE | C76: FAIBLE
A77: KPI Card triple CAPEX | D77: Brut / Optimise / Economie sur 1 carte
A78: Waterfall Chart | D78: CAPEX Local - Economie = CAPEX Optimise
A79: Treemap Budget | D79: LOT > FAM_ARTICLE visualiser concentration
A80: Scatter Gain/Risque | D80: X=Gain% Y=Risque Taille=Montant
A82: SYNTHESE GLOBALE DE L'AUDIT
A83: Score conformite structurelle | B83: 78 / 100 | D83: Etoile correcte mais PROJET_ID brise
A84: Score fiabilite calculs | B84: 65 / 100 | D84: Agregations ok mais 3 totaux incoherents
A85: Score decisionnel | B85: 72 / 100 | D85: 3/4 questions couvertes
A86: Score documentation | B86: 45 / 100 | D86: Formules non documentees
A87: SCORE GLOBAL AUDIT | B87: 65 / 100 | C87: MOYEN | D87: Module fonctionnel. R1-R3 URGENTES.
